Workbook

Sheet RESUME
A1: ELECTRO COOL
A2: RESUME FACTURATION 2026 | D2: au | E2: 46053
F6: PRODUITS | M6: TOTAL
B7: CLIM | D7: ASCENSEUR | E7: TVA | F7: Total | I7: SN | K7: Total | M7: FACTURATION
H8: Plomberie | I8: CLIM | J8: ASC
A9: JANVIER | B9: ='FACTURES NORMALISEES'!I53 -> 42114.94 | D9: ='FACTURES NORMALISEES'!H53 -> 18739.23 | E9: ='FACTURES NORMALISEES'!F53+'FACTURES NORMALISEES'!G53 -> 5063.3655 | F9: =+B9+D9+E9 -> 65917.536 | H9: ='FACTURES SN'!F39 -> 0 | I9: ='FACTURES SN'!G39 -> 691 | J9: ='FACTURES SN'!H39 -> 10684.2 | K9: =+H9+I9+J9 -> 11375.2 | M9: =+F9+K9 -> 77292.736
A10: FEVRIER | B10: ='FACTURES NORMALISEES'!I114 -> 141888.13 | D10: ='FACTURES NORMALISEES'!H114 -> 21558.18 | E10: ='FACTURES NORMALISEES'!F114+'FACTURES NORMALISEES'!G114 -> 21908.801 | F10: =+B10+D10+E10 -> 185355.11 | H10: ='FACTURES SN'!F92 -> 0 | I10: ='FACTURES SN'!G92 -> 56900 | J10: ='FACTURES SN'!H92 -> 0 | K10: =+H10+I10+J10 -> 56900 | M10: =+F10+K10 -> 242255.11
A11: MARS | B11: ='FACTURES NORMALISEES'!I191 -> 233055.09 | D11: ='FACTURES NORMALISEES'!E191 -> 218770.45 | E11: ='FACTURES NORMALISEES'!G191 -> 1670.7214 | F11: ='FACTURES NORMALISEES'!H191 -> 15370.23 | H11: ='FACTURES SN'!F93 -> 0 | I11: ='FACTURES SN'!G93 -> 0 | J11: ='FACTURES SN'!H93 -> 367.5 | K11: =+H11+I11+J11 -> 367.5 | M11: =+F11+K11 -> 15737.73
A12: AVRIL | B12: ='FACTURES NORMALISEES'!I235 -> 46656.74 | D12: ='FACTURES NORMALISEES'!E235 -> 49355.534 | E12: ='FACTURES NORMALISEES'!G235 -> 1012.3834 | F12: ='FACTURES NORMALISEES'!H235 -> 9847.28 | H12: ='FACTURES SN'!F94 -> 0 | I12: ='FACTURES SN'!G94 -> 0 | J12: ='FACTURES SN'!H94 -> 183.75 | K12: =+H12+I12+J12 -> 183.75 | M12: =+F12+K12 -> 10031.03
A13: MAI | B13: ='FACTURES NORMALISEES'!I279 -> 41393.22 | D13: ='FACTURES NORMALISEES'!E279 -> 89471.526 | E13: ='FACTURES NORMALISEES'!G279 -> 8164.7241 | F13: ='FACTURES NORMALISEES'!H279 -> 61551.75 | H13: ='FACTURES SN'!F95 -> 0 | I13: ='FACTURES SN'!G95 -> 0 | J13: ='FACTURES SN'!H95 -> 577.5 | K13: =+H13+I13+J13 -> 577.5 | M13: =+F13+K13 -> 62129.25
A14: JUIN | B14: ='FACTURES NORMALISEES'!I339 -> 0 | D14: ='FACTURES NORMALISEES'!E339 -> 0 | E14: ='FACTURES NORMALISEES'!G339 -> 0 | F14: ='FACTURES NORMALISEES'!H339 -> 0 | H14: ='FACTURES SN'!F96 -> 0 | I14: ='FACTURES SN'!G96 -> 0 | J14: ='FACTURES SN'!H96 -> 288.75 | K14: =+H14+I14+J14 -> 288.75 | M14: =+F14+K14 -> 288.75
A15: JUILLET | B15: ='FACTURES NORMALISEES'!I342 -> 0 | D15: ='FACTURES NORMALISEES'!E342 -> 0 | E15: ='FACTURES NORMALISEES'!G342 -> 0 | F15: ='FACTURES NORMALISEES'!H342 -> 0 | H15: ='FACTURES SN'!F97 -> 0 | I15: ='FACTURES SN'!G97 -> 0 | J15: ='FACTURES SN'!H97 -> 420 | K15: =+H15+I15+J15 -> 420 | M15: =+F15+K15 -> 420
A16: AOUT | B16: ='FACTURES NORMALISEES'!I345 -> 0 | D16: ='FACTURES NORMALISEES'!E345 -> 0 | E16: ='FACTURES NORMALISEES'!G345 -> 0 | F16: ='FACTURES NORMALISEES'!H345 -> 0 | H16: ='FACTURES SN'!F98 -> 0 | I16: ='FACTURES SN'!G98 -> 0 | J16: ='FACTURES SN'!H98 -> 420 | K16: =+H16+I16+J16 -> 420 | M16: =+F16+K16 -> 420
A17: SEPTEMBRE | B17: ='FACTURES NORMALISEES'!I348 -> 0 | D17: ='FACTURES NORMALISEES'!E348 -> 0 | E17: ='FACTURES NORMALISEES'!G348 -> 0 | F17: ='FACTURES NORMALISEES'!H348 -> 0 | H17: ='FACTURES SN'!F99 -> 0 | I17: ='FACTURES SN'!G99 -> 6562.5 | J17: ='FACTURES SN'!H99 -> 0 | K17: =+H17+I17+J17 -> 6562.5 | M17: =+F17+K17 -> 6562.5
A18: OCTOBRE | B18: ='FACTURES NORMALISEES'!I351 -> 0 | D18: ='FACTURES NORMALISEES'!E351 -> 0 | E18: ='FACTURES NORMALISEES'!G351 -> 0 | F18: ='FACTURES NORMALISEES'!H351 -> 0 | H18: ='FACTURES SN'!F100 -> 0 | I18: ='FACTURES SN'!G100 -> 0 | J18: ='FACTURES SN'!H100 -> 400 | K18: =+H18+I18+J18 -> 400 | M18: =+F18+K18 -> 400
A19: NOVEMBRE | B19: ='FACTURES NORMALISEES'!I354 -> 0 | D19: ='FACTURES NORMALISEES'!E354 -> 0 | E19: ='FACTURES NORMALISEES'!G354 -> 0 | F19: ='FACTURES NORMALISEES'!H354 -> 0 | H19: ='FACTURES SN'!F101 -> 0 | I19: ='FACTURES SN'!G101 -> 0 | J19: ='FACTURES SN'!H101 -> 400 | K19: =+H19+I19+J19 -> 400 | M19: =+F19+K19 -> 400
A20: DECEMBRE | B20: ='FACTURES NORMALISEES'!I357 -> 0 | D20: ='FACTURES NORMALISEES'!E357 -> 0 | E20: ='FACTURES NORMALISEES'!G357 -> 0 | F20: ='FACTURES NORMALISEES'!H357 -> 0 | H20: ='FACTURES SN'!F102 -> 0 | I20: ='FACTURES SN'!G102 -> 0 | J20: ='FACTURES SN'!H102 -> 600 | K20: =+H20+I20+J20 -> 600 | M20: =+F20+K20 -> 600
B21: =SUM(B9:B20) -> 505108.12 | D21: =SUM(D9:D20) -> 397894.92 | E21: =SUM(E9:E20) -> 37819.996 | F21: =SUM(F9:F20) -> 338041.91 | H21: =SUM(H9:H20) -> 0 | I21: =SUM(I9:I20) -> 64153.5 | J21: =SUM(J9:J20) -> 14341.7 | K21: =SUM(K9:K20) -> 78495.2 | M21: =SUM(M9:M20) -> 416537.11
I24: TOTAL FACT. | J24: Encaissé | M24: A recouvrer
D26: CLIMATISATION | I26: =B21 -> 505108.12 | J26: ='FACTURES NORMALISEES'!#REF! -> #REF! | M26: =I26-J26 -> #REF!
D27: ASCENSEUR | I27: =D21 -> 397894.92 | J27: ='FACTURES NORMALISEES'!#REF! -> #REF! | M27: =I27-J27 -> #REF!
D28: TVA | I28: =E21 -> 37819.996
D29: TOTAL FACTURES NORMALISEES | I29: =SUM(I26:I28) -> 940823.03 | J29: =SUM(J26:J28) -> #REF! | M29: =SUM(M26:M28) -> #REF!
D31: SN | I31: =K21 -> 78495.2 | J31: ='FACTURES SN'!J263 -> 18450 | M31: =+I31-J31 -> 60045.2
D33: TOTAL | I33: =+I29+I31 -> 1019318.2 | J33: =+J29+J31 -> #REF! | M33: =+M29+M31 -> #REF!

Sheet SUIVI TVA
A1: ELECTROCOOL SARL
A2: SUIVI TVA 2026
E3: PRODUITS | G3: ENCAISSEMENTS | I3: FACTURES | J3: TVA RECOLTEE | N3: TVA CDF | O3: TAXABLE | P3: EXONERE
C4: N / Facture | D4: FACT.Normalisée | E4: ASCENSEUR | F4: CLIM | G4: ASC | H4: CLIM | I4: EXONEREES | J4: A PAYER | K4: PAYE
B6: IMMEUBLE DELPHIN | C6: 2026/DA/01/1 | D6: 136/1-1/2026 | E6: ='FACTURES NORMALISEES'!E6 -> 200 | G6: 232 | J6: =G6-E6 -> 32 | K6: 32 | N6: 68452.57 | O6: 427828.59
B7: C.H.MONKOLE | C7: 2026/DA/01/2 | D7: 136/1-2/2026 | E7: ='FACTURES NORMALISEES'!E7 -> 700 | I7: 700 | P7: 1497380
B8: AMBABEL | C8: 2026/DA/01/3 | D8: 136/1-3/2026 | E8: ='FACTURES NORMALISEES'!E8 -> 750 | I8: 750 | P8: 1604346
B9: Ambassade BRITANNIQUE | C9: 2026/DA/01/4 | D9: 136/1-4/2026 | E9: ='FACTURES NORMALISEES'!E9 -> 150 | I9: 150 | P9: 320868.32
B10: BANQUE MONDIALE | C10: 2026/DA/01/5 | D10: 136/1-5/2026 | E10: ='FACTURES NORMALISEES'!E10 -> 400 | I10: 400 | P10: 855651.52
B11: IMMEUBLE SERKAS | C11: 2026/DA/01/6 | D11: 136/1-6/2026 | E11: ='FACTURES NORMALISEES'!E11 -> 172.80172 | G11: 200.45 | J11: =G11-E11 -> 27.648276 | K11: 27.65 | N11: 60467.9 | O11: 377924.35
B12: COMMUNAUTE HELENIQUE | C12: 2026/DA/01/7 | D12: 136/1-7/2026 | E12: ='FACTURES NORMALISEES'!E12 -> 120 | G12: 139.2 | J12: =G12-E12 -> 19.2 | K12: 19.2 | N12: 41991.18 | O12: 262444.84
B13: EBALE RESIDENCE | C13: 2026/DA/01/8 | D13: 136/1-8/2026 | E13: ='FACTURES NORMALISEES'!E13 -> 166.25
B14: SOGIC - BOULEVARD | C14: 2026/DA/01/9 | D14: 136/1-9/2026 | E14: ='FACTURES NORMALISEES'!E14 -> 183 | G14: 212.28 | J14: =G14-E14 -> 29.28 | K14: 29.28 | N14: 64036.54 | O14: 400228.4
B15: AFRICANA PALACE | C15: 2026/DA/01/10 | D15: 136/1-10/2026 | E15: ='FACTURES NORMALISEES'!E15 -> 180 | G15: 208.8 | J15: 28.8 | K15: 28.8 | N15: 62986.76 | O15: 393667.28
B16: LFRD | C16: 2026/DA/01/11 | D16: 136/1-11/2026 | E16: ='FACTURES NORMALISEES'!E16 -> 500 | G16: 500 | I16: 500 | P16: 1093520.2
B17: SOGIC | C17: 2026/DA/01/12 | D17: 136/1-12/2026 | E17: ='FACTURES NORMALISEES'!E17 -> 183 | G17: 212.28 | J17: =G17-E17 -> 29.28 | K17: 29.28 | N17: 64036.54 | O17: 400228.4
B18: IMMEUBLE IMANI | C18: 2026/DA/01/13 | D18: 136/1-13/2026 | E18: ='FACTURES NORMALISEES'!E18 -> 200 | G18: 232 | J18: =G18-E18 -> 32 | K18: 32 | N18: 69985.29 | O18: 437408.08
B19: TMB / DG | C19: 2026/DA/01/18 | D19: 136/1-23/2026 | E19: ='FACTURES NORMALISEES'!E28 -> 1327.5 | G19: 212.4 | J19: 212.4 | K19: 212.4 | N19: 467213.24 | O19: 2920082.8
B20: UNICEF | C20: 2026/DT/01/2 | D20: 136/1-26/2026 | F20: ='FACTURES NORMALISEES'!E31 -> 13000 | I20: 13000 | P20: 29077912
B21: LFRD | C21: 2026/DT/01/10 | D21: 136/1-28/2026 | F21: ='FACTURES NORMALISEES'!E33 -> 2940 | I21: 2940 | P21: 6576081.8
B22: C.H.MONKOLE | C22: 2026/DA/01/20 | D22: 136/1-31/2026 | E22: ='FACTURES NORMALISEES'!E36 -> 4000 | G22: 4000 | I22: 4000 | P22: 8947050
B23: US EMBASSY | C23: 2026/DA/01/21 | D23: 136/1-32/2026 | E23: ='FACTURES NORMALISEES'!E37 -> 674.45 | I23: 674.45 | P23: 1508584.5
B24: C.H. MONKOLE | C24: 2026/DA/01/19 | D24: 136/1-33/2026 | E24: ='FACTURES NORMALISEES'!E38 -> 780.32 | G24: 780.32 | I24: 780.32 | P24: 1745390.5
B25: US EMBASSY | C25: 2026/DA/01/22 | D25: 136/1-34/2026 | E25: ='FACTURES NORMALISEES'!E39 -> 250 | I25: 250 | P25: 559190.62
B27: 46023 | E27: =SUM(E5:E26) -> 10937.322 | F27: =SUM(F5:F26) -> 15940 | G27: =SUM(G5:G26) -> 6929.73 | H27: =SUM(H5:H26) -> 0 | I27: =SUM(I5:I26) -> 24144.77 | J27: =SUM(J5:J26) -> 410.60828 | K27: =SUM(K5:K26) -> 410.61 | N27: =SUM(N5:N26) -> 899170.02 | O27: =SUM(O5:O26) -> 5619812.7 | P27: =SUM(P5:P26) -> 53785976
B29: TMB / VICTOIRE | C29: 2026/DA/01/32 | D29: 136/1-44/2026 | E29: ='FACTURES NORMALISEES'!E49 -> 225 | G29: 261 | J29: 36 | K29: 36 | N29: 80523.45 | O29: 583795.01
B30: MAJESTIC RIVER | C30: 2026/DT/01/9 | D30: 136/1-27/2026 | F30: ='FACTURES NORMALISEES'!E32 -> 178 | H30: ='FACTURES NORMALISEES'!#REF! -> #REF! | J30: =H30-F30 -> #REF! | K30: 28.48 | N30: 63703 | O30: 398143.72
B31: MAJESTIC RIVER | C31: 2026/DA/01/26 | D31: 136/1-38/2026 | E31: ='FACTURES NORMALISEES'!E43 -> 350 | G31: 406 | J31: =G31-E31 -> 56 | K31: 56 | N31: 125258.7 | O31: 782866.87
B32: MAJESTIC RIVER | C32: 2026/DA/01/27 | D32: 136/1-39/2026 | E32: ='FACTURES NORMALISEES'!E44 -> 350 | G32: 406 | J32: =G32-E32 -> 56 | K32: 56 | N32: 125258.7 | O32: 782866.87
B33: CONNEXAFRICA | C33: 2026/DT/01/11 | D33: 136/1-29/2026 | F33: ='FACTURES NORMALISEES'!E34 -> 2574 | H33: 2985.84 | J33: ='FACTURES NORMALISEES'!F34 -> 411.84 | K33: 411.84 | N33: 921188.27 | O33: 5757426.7
B34: DEVIMCO | C34: 2026/DA/01/24 | D34: 136/1-35/2026 | E34: ='FACTURES NORMALISEES'!E40 -> 130 | G34: 150.8 | J34: ='FACTURES NORMALISEES'!G40 -> 20.8 | K34: 20.8 | N34: 46524.66 | O34: 290779.12
B35: DEVIMCO | C35: 2026/DA/01/29 | D35: 136/1-40/2026 | E35: ='FACTURES NORMALISEES'!E45 -> 100 | G35: ='FACTURES NORMALISEES'!#REF! -> #REF! | J35: ='FACTURES NORMALISEES'!G45 -> 16 | K35: 16 | N35: 35788.2 | O35: 223676.25
B36: DEVIMCO | C36: 2026/DA/01/30 | D36: 136/1-42/2026 | E36: ='FACTURES NORMALISEES'!E47 -> 240 | G36: ='FACTURES NORMALISEES'!#REF! -> #REF! | J36: ='FACTURES NORMALISEES'!G47 -> 38.4 | K36: 38.4 | N36: 85891.68 | O36: 536823
B37: DEVIMCO | C37: 2026/DA/01/31 | D37: 136/1-43/2026 | E37: ='FACTURES NORMALISEES'!E48 -> 400 | G37: ='FACTURES NORMALISEES'!#REF! -> #REF! | J37: ='FACTURES NORMALISEES'!G48 -> 64 | K37: 64 | N37: 143152.8 | O37: 894705
B38: BELTEXCO | C38: 2026/DA/01/33 | D38: 136/1-45/2026 | E38: ='FACTURES NORMALISEES'!E50 -> 129.5 | G38: ='FACTURES NORMALISEES'!#REF! -> #REF! | J38: ='FACTURES NORMALISEES'!G50 -> 20.72 | K38: 20.72 | N38: 46345.72 | O38: 289660.74
B39: BELTEXCO | C39: 2026/DA/01/34 | D39: 136/1-46/2026 | E39: ='FACTURES NORMALISEES'!E51 -> 147 | G39: ='FACTURES NORMALISEES'!#REF! -> #REF! | J39: ='FACTURES NORMALISEES'!G51 -> 23.52 | K39: 23.52 | N39: 52608.65 | O39: 328804.09
B40: COMMUNAUTE HELLENIQUE | C40: 2026.01/DA/46 | D40: 136/1-63/2026 | E40: ='FACTURES NORMALISEES'!E71 -> 126 | G40: ='FACTURES NORMALISEES'!#REF! -> #REF! | J40: ='FACTURES NORMALISEES'!G71 -> 20.16 | K40: 20.16 | N40: 45260.13 | O40: 282875.82
B41: LFRD | C41: 2026.01/DA/50 | D41: 136/1-67/2026 | E41: =+H41/1.16 -> 0 | G41: 500 | I41: ='FACTURES NORMALISEES'!H75 -> 500 | P41: 1136451.1
B42: C.H. MONKOLE | C42: 2026.01/DA/51 | D42: 136/1-68/2026 | E42: =+H42/1.16 -> 0 | I42: ='FACTURES NORMALISEES'!H76 -> 700 | P42: 1591031.6
B43: US EMBASSY | C43: 2026.01/DA/52 | D43: 136/1-69/2026 | E43: =+H43/1.16 -> 0 | I43: ='FACTURES NORMALISEES'!H77 -> 250 | P43: 568225.57
B44: AMBABEL | C44: 2026.01/DA/53 | D44: 136/1-70/2026 | E44: =+H44/1.16 -> 0 | I44: ='FACTURES NORMALISEES'!H78 -> 750 | P44: 1704676.7
B45: MONUSCO | C45: 2026.01/DA/54 | D45: 136/1-71/2026 | E45: =+H45/1.16 -> 0 | I45: ='FACTURES NORMALISEES'!H79 -> 1200 | P45: 2727482.8
B46: BRITISH EMBASSY | C46: 2026.01/DA/55 | D46: 136/1-72/2026 | E46: =+H46/1.16 -> 0 | I46: ='FACTURES NORMALISEES'!H80 -> 157.5 | P46: 357982.11
B47: BANQUE MONDIALE | C47: 2026.01/DA/56 | D47: 136/1-73/2026 | E47: =+H47/1.16 -> 0 | I47: ='FACTURES NORMALISEES'!H81 -> 400 | P47: 909160.92
B48: BELTEXCO 1 | C48: 2026.01/DA/43 | D48: 136/1-60/2026 | E48: ='FACTURES NORMALISEES'!E68 -> 135.98276 | G48: ='FACTURES NORMALISEES'!#REF! -> #REF! | J48: ='FACTURES NORMALISEES'!G68 -> 21.757241 | K48: 21.76 | N48: 48846.01 | O48: 305287.57
B49: BELTEXCO 2 | C49: 2026.01/DA/44 | D49: 136/1-61/2026 | E49: ='FACTURES NORMALISEES'!E69 -> 154.35345 | G49: ='FACTURES NORMALISEES'!#REF! -> #REF! | J49: ='FACTURES NORMALISEES'!G69 -> 24.696552 | K49: 24.7 | N49: 55444.9 | O49: 346530.62
B50: TCK | C50: 2026/DT/01/5 | D50: 136/1-20/2026 | E50: ='FACTURES NORMALISEES'!E25 -> 384 | G50: ='FACTURES NORMALISEES'!#REF! -> #REF! | J50: ='FACTURES NORMALISEES'!F25 -> 61.44 | K50: 61.44 | N50: 135148.69 | O50: 844679.3
B51: DEVIMCO | C51: 2026.01/DA/35 | D51: 136/1-52/2026 | E51: ='FACTURES NORMALISEES'!E60 -> 136.5 | G51: 158.34 | J51: ='FACTURES NORMALISEES'!G60 -> 21.84 | K51: 21.84 | N51: 49031.81 | O51: 306448.8
B52: DEVIMCO | C52: 2026.01/DA/36 | D52: 136/1-53/2026 | E52: ='FACTURES NORMALISEES'!E61 -> 105 | G52: 121.8 | J52: ='FACTURES NORMALISEES'!G61 -> 16.8 | K52: 16.8 | N52: 37716.78 | O52: 235729.84
B53: DEVIMCO | C53: 2026.01/DA/37 | D53: 136/1-54/2026 | E53: ='FACTURES NORMALISEES'!E62 -> 252 | G53: 292.32 | J53: ='FACTURES NORMALISEES'!G62 -> 40.32 | K53: 40.32 | N53: 90520.26 | O53: 565751.64
B54: DEVIMCO | C54: 2026.01/DA/38 | D54: 136/1-55/2026 | E54: ='FACTURES NORMALISEES'!E63 -> 420 | G54: 487.2 | J54: ='FACTURES NORMALISEES'!G63 -> 67.2 | K54: 67.2 | N54: 150867.1 | O54: 942919.41
B55: MIDEMA (Facture 2025) | C55: 2025/DA/165 | E55: =+H55/1.16 -> 0 | G55: 319
B56: MIDEMA | C56: 2026/DA/01/25 | D56: 136/1-37/2026 | E56: =+H56/1.16 -> 0 | G56: ='FACTURES NORMALISEES'!#REF! -> #REF! | J56: ='FACTURES NORMALISEES'!G42 -> 44 | K56: 44 | N56: 98417.55 | O56: 615109.68
B57: MAJESTIC RIVER | C57: 2026.01/DA/63 | D57: 136/1-80/2026 | E57: ='FACTURES NORMALISEES'!E88 -> 350 | G57: ='FACTURES NORMALISEES'!#REF! -> #REF! | J57: ='FACTURES NORMALISEES'!G88 -> 56 | K57: 56 | N57: ='FACTURES NORMALISEES'!#REF! -> #REF! | O57: ='FACTURES NORMALISEES'!#REF! -> #REF!
B58: TALGARTH HOLDING INC | C58: 2026.01/DA/59 | D58: 136/1-76/2026 | E58: ='FACTURES NORMALISEES'!E84 -> 500 | G58: ='FACTURES NORMALISEES'!#REF! -> #REF! | J58: ='FACTURES NORMALISEES'!G84 -> 80 | K58: 80 | N58: ='FACTURES NORMALISEES'!#REF! -> #REF! | O58: ='FACTURES NORMALISEES'!#REF! -> #REF!
B59: TALGARTH HOLDING INC | C59: 2026.01/DA/60 | D59: 136/1-77/2026 | E59: ='FACTURES NORMALISEES'!E85 -> 250 | G59: ='FACTURES NORMALISEES'!#REF! -> #REF! | J59: ='FACTURES NORMALISEES'!G85 -> 40 | K59: 40 | N59: ='FACTURES NORMALISEES'!#REF! -> #REF! | O59: ='FACTURES NORMALISEES'!#REF! -> #REF!
B60: Immeuble SERKAS | C60: 2026.01/DA/65 | D60: 136/1-85/2026 | E60: ='FACTURES NORMALISEES'!E93 -> 181.43966 | G60: ='FACTURES NORMALISEES'!#REF! -> #REF! | J60: ='FACTURES NORMALISEES'!G93 -> 29.030345 | K60: 29.03 | N60: ='FACTURES NORMALISEES'!#REF! -> #REF! | O60: ='FACTURES NORMALISEES'!#REF! -> #REF!
B61: TMB | C61: 2026.01/DA/39 | D61: 136/1-56/2026 | E61: ='FACTURES NORMALISEES'!E64 -> 236.25 | G61: ='FACTURES NORMALISEES'!#REF! -> #REF! | J61: ='FACTURES NORMALISEES'!G64 -> 37.8 | K61: 37.8 | N61: ='FACTURES NORMALISEES'!#REF! -> #REF! | O61: ='FACTURES NORMALISEES'!#REF! -> #REF!
B62: TMB | C62: 2026.01/DA/40 | D62: 136/1-57/2026 | E62: ='FACTURES NORMALISEES'!E65 -> 1393.8793 | G62: ='FACTURES NORMALISEES'!#REF! -> #REF! | J62: ='FACTURES NORMALISEES'!G65 -> 223.02069 | K62: 223.02 | N62: ='FACTURES NORMALISEES'!#REF! -> #REF! | O62: ='FACTURES NORMALISEES'!#REF! -> #REF!
B63: AFRICANA PALACE | C63: 2026.01/DA/67 | D63: 136/1-86/2026 | E63: ='FACTURES NORMALISEES'!E94 -> 189 | G63: ='FACTURES NORMALISEES'!#REF! -> #REF! | J63: ='FACTURES NORMALISEES'!G94 -> 30.24 | K63: 30.24 | N63: ='FACTURES NORMALISEES'!#REF! -> #REF! | O63: ='FACTURES NORMALISEES'!#REF! -> #REF!
B64: RAWBANK | C64: 2026/DT/01/8 | D64: 136/1-25/2026 | E64: 0 | F64: ='FACTURES NORMALISEES'!E30 -> 12603.603 | H64: ='FACTURES NORMALISEES'!#REF! -> #REF! | J64: ='FACTURES NORMALISEES'!F30 -> 2016.5766 | K64: 2016.58 | N64: ='FACTURES NORMALISEES'!#REF! -> #REF! | O64: ='FACTURES NORMALISEES'!#REF! -> #REF!
B65: RAWBANK ( TVA NON PAYE) | C65: 2026/DT/01/16 | D65: 136/1-51/2026 | F65: =H65/1.16 -> #REF! | H65: ='FACTURES NORMALISEES'!#REF! -> #REF! | J65: =+F65*16% -> #REF! | K65: =+G65*16% -> 0 | N65: =155799275*16/100 -> 24927884 | O65: =155799275 -> 155799275
B66: EJCSDJ | C66: 2026/DT/01/18 | D66: 136/1-82/2026 | F66: ='FACTURES NORMALISEES'!E90 -> 8752.25 | H66: ='FACTURES NORMALISEES'!#REF! -> #REF! | J66: ='FACTURES NORMALISEES'!F90 -> 1400.36 | K66: 1400.36 | N66: ='FACTURES NORMALISEES'!#REF! -> #REF! | O66: ='FACTURES NORMALISEES'!#REF! -> #REF!
B67: EJCSDJ | C67: 2026/DT/01/19 | D67: 136/1-83/2026 | F67: ='FACTURES NORMALISEES'!E91 -> 4812.5 | H67: 5582.5 | J67: ='FACTURES NORMALISEES'!F91 -> 770 | K67: 770 | N67: ='FACTURES NORMALISEES'!#REF! -> #REF! | O67: ='FACTURES NORMALISEES'!#REF! -> #REF!
B68: LPL | C68: 2026/DT/01/7 | D68: 136/1-24/2026 | F68: ='FACTURES NORMALISEES'!E29 -> 2250 | H68: ='FACTURES NORMALISEES'!#REF! -> #REF! | J68: ='FACTURES NORMALISEES'!F29 -> 360 | K68: 360 | N68: ='FACTURES NORMALISEES'!#REF! -> #REF! | O68: ='FACTURES NORMALISEES'!#REF! -> #REF!
B69: IMMOKIN | C69: 2026.01/DA/61 | D69: 136/1-78/2026 | E69: ='FACTURES NORMALISEES'!E86 -> 250 | G69: ='FACTURES NORMALISEES'!#REF! -> #REF! | J69: ='FACTURES NORMALISEES'!G86 -> 40 | K69: 40 | N69: ='FACTURES NORMALISEES'!#REF! -> #REF! | O69: ='FACTURES NORMALISEES'!#REF! -> #REF!
B70: US EMBASSY | C70: 2026.01/DA/77 | D70: 136/1-103/2026 | P70: 523795.35
B71: BANQUE MONDIALE | C71: 2026.01/DA/78 | D71: 136/1-104/2026 | P71: 838072.56
N72: =-N65 -> -24927884 | O72: =-O65 -> -155799275
E73: =+H73/1.16 -> 0
B74: 46054 | E74: =SUM(E29:E73) -> 7135.9052 | F74: =SUM(F28:F73) -> #REF! | G74: =SUM(G28:G73) -> #REF! | H74: =SUM(H28:H73) -> #REF! | I74: =SUM(I28:I73) -> 3957.5 | J74: =SUM(J28:J73) -> #REF! | K74: =SUM(K28:K73) -> 6173.01 | N74: =SUM(N30:N73) -> #REF! | O74: =SUM(O30:O73) -> #REF! | P74: =SUM(P30:P73) -> 10356879
A76: 46085 | B76: JAPAN MOTORS | C76: 2026/DT/01/31 | D76: 136/1-118/2026 | F76: ='FACTURES NORMALISEES'!E129 -> 400 | H76: ='FACTURES NORMALISEES'!#REF! -> #REF! | J76: ='FACTURES NORMALISEES'!F129 -> 64 | K76: 64 | N76: =+O76*0.16 -> 143630.18 | O76: 897688.6
A77: 46085 | B77: SOGIC | C77: 2026.02/DA/72 | D77: 136/1-92/2026 | E77: ='FACTURES NORMALISEES'!E100 -> 192.14655 | G77: ='FACTURES NORMALISEES'!#REF! -> #REF! | J77: ='FACTURES NORMALISEES'!G100 -> 30.743448 | K77: 30.74 | N77: =+O77*16% -> 64910.734 | O77: 405692.09
A78: 46085 | B78: SOGIC | C78: 2026.02/DA/73 | D78: 136/1-93/2026 | E78: ='FACTURES NORMALISEES'!E101 -> 192.14655 | G78: ='FACTURES NORMALISEES'!#REF! -> #REF! | J78: ='FACTURES NORMALISEES'!G101 -> 30.743448 | K78: 30.74 | N78: =+O78*16% -> 64910.734 | O78: 405692.09
A79: 46086 | B79: COMMUNAUTE HELLENIQUE | C79: 2026.01/DA/85 | D79: 136/1-116/2026 | E79: ='FACTURES NORMALISEES'!E127 -> 126 | G79: ='FACTURES NORMALISEES'!#REF! -> #REF! | J79: ='FACTURES NORMALISEES'!G127 -> 20.16 | K79: 20.16 | N79: =+O79*16% -> 45243.506 | O79: 282771.91
A80: 46086 | B80: Immeuble DELPHIN (LA GRACE DE DIEU) | C80: 2026.01/DA/66 | D80: 136/1-87/2026 | E80: ='FACTURES NORMALISEES'!E95 -> 210 | G80: ='FACTURES NORMALISEES'!#REF! -> #REF! | J80: ='FACTURES NORMALISEES'!G95 -> 33.6 | K80: 33.6 | N80: =+O80*16% -> 76661.789 | O80: 479136.18
A81: 46087 | B81: TMB | C81: 2026/DT/01/26 | D81: 136/1-101/2026 | E81: 400 | H81: 464 | J81: 64 | K81: 64 | N81: =+O81*16% -> 134091.61 | O81: 838072.56
A82: 46087 | B82: TMB | C82: 2026.01/DA/76 | D82: 136/1-102/2026 | E82: 236.25 | G82: 275.05 | J82: 37.8 | K82: 37.8 | N82: =+O82*16% -> 79197.856 | O82: 494986.6
A83: 46094 | B83: PRIMMO | C83: 2026/DT/01/17 | D83: 136/1-109/2026 | F83: ='FACTURES NORMALISEES'!E120 -> 14967.991 | H83: 17362.87 | J83: 2394.88 | K83: 0 | N83: =+O83*16% -> #REF! | O83: ='FACTURES NORMALISEES'!#REF! -> #REF!
A84: 46108 | B84: TMB | C84: 2026.01/DA/102 | D84: 136/1-152/2026 | E84: ='FACTURES NORMALISEES'!E163 -> 1393.8793 | G84: 1582.56 | J84: 223.02 | K84: 223.02 | N84: =+O84*16% -> 507511.79 | O84: 3171948.7
A85: 46108 | B85: TMB | C85: 2026/DT/01/46 | D85: 136/1-143/2026 | E85: ='FACTURES NORMALISEES'!E154 -> 200 | G85: 227.07 | J85: 32 | K85: 32 | N85: =+O85*16% -> 72820.046 | O85: 455125.29
N86: =+O86*16% -> 0
A87: 46085 | B87: COMPAGNIE SUCRIERE | C87: 2026/DT/01/15 | D87: 136/1-50/2026 | H87: 2279.4 | J87: 314.4 | K87: 314.4 | N87: =+O87*16% -> 689191.46 | O87: 4307446.6
A88: 46087 | B88: TALGARTH HOLDING | C88: 2026.01/DA/79 | D88: 136/1-110/2026 | G88: 58 | J88: 8 | K88: 8 | N88: =+O88*16% -> 17953.771 | O88: 112211.07
A89: 46087 | B89: IAG | C89: 2026.01/DA/45 | D89: 136/1-62/2026 | G89: 1392 | J89: 192 | K89: 192 | N89: =+O89*16% -> 431048.87 | O89: 2694055.4
A90: 46088 | B90: MAJESTIC RIVER | C90: 2026/DT/01/30 | D90: 136/1-108/2026 | F90: 360 | H90: 417.6 | J90: 57.6 | K90: 57.6 | N90: =+O90*16% -> 127714.64 | O90: 798216.47
A91: 46090 | B91: UTEXAFRICA | D91: 136/1-15-74/2026 | G91: 1231.35 | J91: =84.38+85.46 -> 169.84 | K91: 169.84 | N91: =+O91*16% -> 376563.17 | O91: =1139476.5+1214043.34 -> 2353519.8
A92: 46090 | B92: COMPAGNIE SUCRIERE | C92: 2026/DT/01/14 | D92: 136/1-49/2026 | H92: 15387.4 | J92: 2122.4 | K92: 2122.4 | N92: =+O92*16% -> 4652480.8 | O92: 29078005
A93: 46091 | B93: LFRD | C93: 2026.01/DA/83 | D93: 136/1-114/2026 | I93: 500 | P93: 1122110.8
A94: 46091 | B94: MIDEMA | C94: 2026.01/DA/62 | D94: 136/1-79/2026 | G94: 319 | J94: 44 | K94: 44 | N94: =+O94*16% -> 100007.7 | O94: 625048.13
A95: 46093 | B95: IAG | C95: 2026.01/DA/84 | D95: 136/1-115/2026 | G95: 1392 | J95: 192 | K95: 192 | N95: =+O95*16% -> 430890.53 | O95: 2693065.8
A96: 46093 | B96: MAJESTIC RIVER | C96: 2026.01/DA/87 | D96: 136/1-123/2026 | G96: 406 | J96: 56 | K96: 56 | N96: =+O96*16% -> 120276.28 | O96: 751726.78
A97: 46094 | B97: TALGARTH HOLDING | C97: 2026.01/DA/88 | D97: 136/1-124/2026 | G97: 696 | J97: 96 | K97: 96 | N97: =+O97*16% -> 206187.92 | O97: 1288674.5
A98: 46100 | B98: EJCSDJ | C98: 2026/DT/01/40 | D98: 136/1-135/2026 | H98: 293.48 | J98: 40.48 | K98: 40.48 | N98: =+O98*16% -> 90706.061 | O98: 566912.88
A99: 46102 | B99: UTEXAFRICA | D99: 136/1-97-107-111/2026 | G99: 11626.73 | J99: =1293.6+226.56+83.53 -> 1603.69 | K99: 1603.69 | N99: =+O99*16% -> 3421062.9 | O99: =17070411.12+3139651.49+1171580.35 -> 21381643
A100: 46102 | B100: COTEX | C100: 2026/DT/01/23 | D100: 136/1-98/2026 | H100: 1745.8 | J100: ='FACTURES NORMALISEES'!F106 -> 240.8 | K100: 240.8 | N100: =+O100*16% -> 508417.44 | O100: 3177609
A102: 46084 | B102: RAWBANK | C102: 2026/DT/01/20 | D102: 136/1-84/2026 | H102: 1136 | J102: 156.8 | K102: 156.8 | N102: =+O102*16% -> 356252.12 | O102: 2226575.8
A103: 46085 | B103: COMPAGNIE SUCRIERE | C103: 2026/DT/01/25-35 | D103: 136/1-100-122/2026 | H103: 2876.4 | J103: ='FACTURES NORMALISEES'!F107+'FACTURES NORMALISEES'!G110 -> 315.4 | K103: 315.4 | N103: =+O103*16% -> 842647.43 | O103: =2388506.79+2878039.67 -> 5266546.5
A104: 46086 | B104: EXCELLERATE - Facture 2025/DT/104 | H104: =2894.2-2894.2 -> 0 | N104: =+O104*16% -> 0
A105: 46087 | B105: BELTEXCO | C105: 2026.01/DA/74-75 | D105: 136/1-94-95/2026 | H105: 336.79 | J105: =+'FACTURES NORMALISEES'!G102+'FACTURES NORMALISEES'!G103 -> 46.453793 | K105: 46.45 | N105: =+O105*16% -> 98081.056 | O105: =287109.66+325896.94 -> 613006.6
...

Sheet FACTURES NORMALISEES
A1: ELECTROCOOL SARL
A2: SUIVI FACTURES NORMALISEES - 2026
F3: TVA | H3: FACTURES
A4: DATE | B4: Clients | C4: N / Facture | D4: FACT.Normalisée | E4: PRODUITS | F4: CLIM | G4: ASC | H4: ASCENSEUR | I4: CLIM
A6: 46042 | B6: IMMEUBLE DELPHIN - Redevance 12/2025 | C6: 2026/DA/01/4 | D6: 136/1-1/2026 | E6: =+(H6+I6)/1.16 -> 200 | G6: =+H6-E6 -> 32 | H6: 232
A7: 46042 | B7: C.H.MONKOLE - Redevance 12/2025 | C7: 2026/DA/01/3 | D7: 136/1-2/2026 | E7: 700 | F7: 0 | G7: =+H7-E7 -> 0 | H7: 700
A8: 46042 | B8: AMBABEL - Redevance 12/2025 | C8: 2026/DA/01/1 | D8: 136/1-3/2026 | E8: 750 | F8: 0 | G8: =+H8-E8 -> 0 | H8: 750
A9: 46042 | B9: Ambassade BRITANNIQUE - Redevance 12/2025 | C9: 2026/DA/01/2 | D9: 136/1-4/2026 | E9: 150 | F9: 0 | G9: =+H9-E9 -> 0 | H9: 150
A10: 46042 | B10: BANQUE MONDIALE - Redevance 12/2025 | C10: 2026/DA/01/5 | D10: 136/1-5/2026 | E10: 400 | F10: 0 | G10: =+H10-E10 -> 0 | H10: 400
A11: 46042 | B11: IMMEUBLE SERKAS - Redevance 12/2025 | C11: 2026/DA/01/6 | D11: 136/1-6/2026 | E11: =+(H11+I11)/1.16 -> 172.80172 | G11: =+H11-E11 -> 27.648276 | H11: 200.45
A12: 46042 | B12: COMMUNAUTE HELENIQUE - Redevance 12/2025 | C12: 2026/DA/01/7 | D12: 136/1-7/2026 | E12: =+(H12+I12)/1.16 -> 120 | G12: =+H12-E12 -> 19.2 | H12: 139.2
A13: 46043 | B13: EBALE RESIDENCE - Redevance 12/2025 | C13: 2026/DA/01/8 | D13: 136/1-8/2026 | E13: =+(H13+I13)/1.16 -> 166.25 | G13: =+H13-E13 -> 26.6 | H13: 192.85
A14: 46043 | B14: SOGIC - Redevance BOULEVARD 12/2025 | C14: 2026/DA/01/9 | D14: 136/1-9/2026 | E14: =+(H14+I14)/1.16 -> 183 | G14: =+H14-E14 -> 29.28 | H14: 212.28
A15: 46043 | B15: AFRICANA PALACE - Redevance 12/2025 | C15: 2026/DA/01/10 | D15: 136/1-10/2026 | E15: =+(H15+I15)/1.16 -> 180 | G15: =+H15-E15 -> 28.8 | H15: 208.8
A16: 46043 | B16: LFRD - Redevance 12/2025 | C16: 2026/DA/01/11 | D16: 136/1-11/2026 | E16: 500 | F16: 0 | G16: =+H16-E16 -> 0 | H16: 500
A17: 46043 | B17: SOGIC - Redevance ROI BAUDOUIN 12/2025 | C17: 2026/DA/01/12 | D17: 136/1-12/2026 | E17: =+(H17+I17)/1.16 -> 183 | G17: =+H17-E17 -> 29.28 | H17: 212.28
A18: 46043 | B18: IMMEUBLE IMANI - Redevance 12/2025 | C18: 2026/DA/01/13 | D18: 136/1-13/2026 | E18: =+(H18+I18)/1.16 -> 200 | G18: =+H18-E18 -> 32 | H18: 232
A19: 46044 | B19: EBCDC - Revance escalators 12/2025 | C19: 2026/DA/01/14 | D19: 136/1-14/2026 | E19: =+(H19+I19)/1.16 -> 150 | G19: =+H19-E19 -> 24 | H19: 174
A20: 46044 | B20: UTEXAFRICA - Redevance BOIS NOBLES 2B 12/2025 (522€) | C20: 2026/DA/01/15 | D20: 136/1-15/2026 | E20: =+(H20+I20)/1.16 -> 527.37931 | G20: =+H20-E20 -> 84.38069 | H20: 611.76
A21: 46045 | B21: EXCELLERATE - Entretien 4eTRIM2025 - | C21: 2026/DT/01/1 | D21: 136/1-16/2026 | E21: =+(H21+I21)/1.16 -> 2575 | F21: =+I21-E21 -> 412 | I21: 2987
A22: 46045 | B22: AGL - Fo&po split 12000btu Bureau KINGABWA | C22: 2026/DT/01/3 | D22: 136/1-17/2026 | E22: =+(H22+I22)/1.16 -> 850 | F22: =+I22-E22 -> 136 | I22: 986
A23: 46045 | B23: AGL - Fo&po split 24000btu VILLA 150 UTEX (ANNULEE DUPPLICATA cfr 19/2026) | D23: 136/1-18/2026 | E23: =+(H23+I23)/1.16 -> 0 | F23: =+I23-E23 -> 0 | G23: =+H23-E23 -> 0
A24: 46045 | B24: AGL - Fo&po split 24000btu VILLA 150 UTEX | C24: 2026/DT/01/4 | D24: 136/1-19/2026 | E24: =+(H24+I24)/1.16 -> 1150 | F24: =+I24-E24 -> 184 | I24: 1334
A25: 46045 | B25: TCK - Entretien 12/2025 | C25: 2026/DT/01/5 | D25: 136/1-20/2026 | E25: =+(H25+I25)/1.16 -> 384 | F25: =+I25-E25 -> 61.44 | I25: 445.44
A26: 46045 | B26: SILIKIN VILLAGE - Entretien clim 12/2025 (ANNULEE cfr COTEX 138/2026 ) | C26: 2026/DT/01/6 | D26: 136/1-21/2026 | E26: =+(H26+I26)/1.16 -> 0 | F26: =+I26-E26 -> 0 | I26: =7609.6-7609.6 -> 0
A27: 46045 | B27: EBCDC/IAG - Redevance CONCESSION 12/2025 | C27: 2026/DA/01/17 | D27: 136/1-22/2026 | E27: =+(H27+I27)/1.16 -> 1200 | G27: =+H27-E27 -> 192 | H27: 1392
A28: 46045 | B28: TMB - Redevance SIEGE 12/2025 | C28: 2026/DA/01/18 | D28: 136/1-23/2026 | E28: =+(H28+I28)/1.16 -> 1327.5 | G28: =+H28-E28 -> 212.4 | H28: 1539.9
A29: 46050 | B29: LPL - Entretien clim 1erQUAD2026 | C29: 2026/DT/01/7 | D29: 136/1-24/2026 | E29: =+(H29+I29)/1.16 -> 2250 | F29: =+I29-E29 -> 360 | I29: 2610
A30: 46050 | B30: RAWBANK SARL - Entretien clim 1eTRIM.2026 (corrigé 4eTRIM.2025) | C30: 2026/DT/01/8 | D30: 136/1-25/2026 | E30: =+(H30+I30)/1.16 -> 12603.603 | F30: =+I30-E30 -> 2016.5766 | I30: 14620.18
A31: 46050 | B31: UNICEF - Maintenance HUB/KINKOLE 12/2025 | C31: 2026/DT/01/2 | D31: 136/1-26/2026 | E31: 13000 | F31: =+I31-E31 -> 0 | G31: 0 | I31: 13000
A32: 46050 | B32: MAJESTIC RIVER - Depannage CF 12/2025 | C32: 2026/DT/01/9 | D32: 136/1-27/2026 | E32: =+(H32+I32)/1.16 -> 178 | F32: =+I32-E32 -> 28.48 | I32: 206.48
A33: 46050 | B33: LFRD - Entretien clim 1erTRIM.2026 | C33: 2026/DT/01/10 | D33: 136/1-28/2026 | E33: 2940 | F33: =+I33-E33 -> 0 | G33: 0 | I33: 2940
A34: 46050 | B34: CONNEXAFRICA RDC - Entretien clim 1erTRIM.2026 | C34: 2026/DT/01/11 | D34: 136/1-29/2026 | E34: =+(H34+I34)/1.16 -> 2574 | F34: =+I34-E34 -> 411.84 | I34: 2985.84
A35: 46050 | B35: EBCDC - Redevance semestrielle ESCALATORS | C35: 2026/DA/01/16 | D35: 136/1-30/2026 | E35: =+(H35+I35)/1.16 -> 1600 | G35: =+H35-E35 -> 256 | H35: 1856
A36: 46050 | B36: C.H. MONKOLE - Fo&po 3 courroies de traction | C36: 2026/DA/01/20 | D36: 136/1-31/2026 | E36: 4000 | F36: 0 | G36: =+H36-E36 -> 0 | H36: 4000
A37: 46050 | B37: US EMBASSY - Fo&po 3 Remote ASC | C37: 2026/DA/01/21 | D37: 136/1-32/2026 | E37: 674.45 | F37: 0 | G37: =+H37-E37 -> 0 | H37: 674.45
A38: 46050 | B38: C.H. MONKOLE - Fo&po 4 Galets porte cabine | C38: 2026/DA/01/19 | D38: 136/1-33/2026 | E38: 780.32 | F38: 0 | G38: =+H38-E38 -> 0 | H38: 780.32
A39: 46050 | B39: US EMBASSY - Redevance 122025 - 2026.01/DA/22 | C39: 2026/DA/01/22 | D39: 136/1-34/2026 | E39: 250 | F39: 0 | G39: =+H39-E39 -> 0 | H39: 250
A40: 46050 | B40: DEVIMCO / PRESTIGE - Redevance 122025 - 2026.01/DA/24 | C40: 2026/DA/01/24 | D40: 136/1-35/2026 | E40: =+H40/1.16 -> 130 | G40: =+H40-E40 -> 20.8 | H40: 150.8
A41: 46050 | B41: WAGENIA - Redevance 122025 - 2026.01/DA/23 | C41: 2026/DA/01/23 | D41: 136/1-36/2026 | E41: =+H41/1.16 -> 250 | G41: =+H41-E41 -> 40 | H41: 290
A42: 46050 | B42: MIDEMA - Redevance 112025 - 2026.01/DA/25 | C42: 2026/DA/01/25 | D42: 136/1-37/2026 | E42: =+H42/1.16 -> 275 | G42: =+H42-E42 -> 44 | H42: 319
A43: 46050 | B43: MAJESTIC RIVER - Redevance 112025 - 2026.01/DA/26 | C43: 2026/DA/01/26 | D43: 136/1-38/2026 | E43: =+H43/1.16 -> 350 | G43: =+H43-E43 -> 56 | H43: 406
A44: 46050 | B44: MAJESTIC RIVER - Redevance 122025 - 2026.01/DA/27 | C44: 2026/DA/01/27 | D44: 136/1-39/2026 | E44: =+H44/1.16 -> 350 | G44: =+H44-E44 -> 56 | H44: 406
A45: 46050 | B45: DEVIMCO / AMBASSADEUR - Redevance 122025 - 2026.01/DA/29 | C45: 2026/DA/01/29 | D45: 136/1-40/2026 | E45: =+H45/1.16 -> 100 | G45: =+H45-E45 -> 16 | H45: 116
A46: 46050 | B46: MIDEMA - Redevance 122025 - 2026.01/DA/28 | C46: 2026/DA/01/28 | D46: 136/1-41/2026 | E46: =+H46/1.16 -> 275 | G46: =+H46-E46 -> 44 | H46: 319
A47: 46050 | B47: DEVIMCO / TRADITION - Redevance 122025 - 2026.01/DA/30 | C47: 2026/DA/01/30 | D47: 136/1-42/2026 | E47: =+H47/1.16 -> 240 | G47: =+H47-E47 -> 38.4 | H47: 278.4
A48: 46050 | B48: DEVIMCO / CONCORDE - Redevance 122025 - 2026.01/DA/31 | C48: 2026/DA/01/31 | D48: 136/1-43/2026 | E48: =+H48/1.16 -> 400 | G48: =+H48-E48 -> 64 | H48: 464
A49: 46050 | B49: TMB / VICTOIRE - Redevance 122025 - 2026.01/DA/32 | C49: 2026/DA/01/32 | D49: 136/1-44/2026 | E49: =+H49/1.16 -> 225 | G49: =+H49-E49 -> 36 | H49: 261
A50: 46050 | B50: BELTEXCO 1 - Redevance 122025 - 2026.01/DA/33 | C50: 2026/DA/01/33 | D50: 136/1-45/2026 | E50: =+H50/1.16 -> 129.5 | G50: =+H50-E50 -> 20.72 | H50: 150.22
A51: 46050 | B51: BELTEXCO 2 - Redevance 122025 - 2026.01/DA/34 | C51: 2026/DA/01/34 | D51: 136/1-46/2026 | E51: =+H51/1.16 -> 147 | G51: =+H51-E51 -> 23.52 | H51: 170.52
B53: 46023 | E53: =SUM(E5:E52) -> 55790.804 | F53: =SUM(F5:F52) -> 3610.3366 | G53: =SUM(G5:G52) -> 1453.029 | H53: =SUM(H5:H52) -> 18739.23 | I53: =SUM(I5:I52) -> 42114.94
A55: 46056 | B55: AGL - Entretien clim 4eTRIM.2025 - 2026.01/DT/12 | C55: 2026/DT/01/12 | D55: 136/1-47/2026 | E55: =+(H55+I55)/1.16 -> 9016 | F55: =+I55-E55 -> 1442.56 | G55: 0 | I55: 10458.56
A56: 46057 | B56: AGL - Dépannage clim 4eTRIM.2025 - 2026.01/DT/13 | C56: 2026/DT/01/13 | D56: 136/1-48/2026 | E56: =+(H56+I56)/1.16 -> 224 | F56: =+I56-E56 -> 35.84 | G56: 0 | I56: 259.84
A57: 46057 | B57: COMPAGNIE SUCRIERE - Entretien 4eTRIM.2025 | C57: 2026/DT/01/14 | D57: 136/1-49/2026 | E57: =+(H57+I57)/1.16 -> 13265 | F57: =+I57-E57 -> 2122.4 | G57: 0 | I57: 15387.4
A58: 46057 | B58: COMPAGNIE SUCRIERE - Dépannage 4eTRIM.2025 | C58: 2026/DT/01/15 | D58: 136/1-50/2026 | E58: =+(H58+I58)/1.16 -> 1965 | F58: =+I58-E58 -> 314.4 | G58: 0 | I58: 2279.4
A59: 46064 | B59: RAWBANK - 20% Travaux reamenagement 2026.01/DT/16 | C59: 2026/DT/01/16 | D59: 136/1-51/2026 | E59: =+(H59+I59)/1.16 -> 69800 | F59: =+I59-E59 -> 11168 | G59: 0 | I59: 80968
A60: 46065 | B60: DEVIMCO - Redevance PRESTIGE 01/2026 | C60: 2026.01/DA/35 | D60: 136/1-52/2026 | E60: =+H60/1.16 -> 136.5 | G60: =+H60-E60 -> 21.84 | H60: 158.34
A61: 46065 | B61: DEVIMCO - Redevance AMBASSADEUR 01/2026 | C61: 2026.01/DA/36 | D61: 136/1-53/2026 | E61: =+H61/1.16 -> 105 | G61: =+H61-E61 -> 16.8 | H61: 121.8
A62: 46065 | B62: DEVIMCO - Redevance TRADITION 01/2026 | C62: 2026.01/DA/37 | D62: 136/1-54/2026 | E62: =+H62/1.16 -> 252 | G62: =+H62-E62 -> 40.32 | H62: 292.32
A63: 46065 | B63: DEVIMCO - Redevance CONCORDE 01/2026 | C63: 2026.01/DA/38 | D63: 136/1-55/2026 | E63: =+H63/1.16 -> 420 | G63: =+H63-E63 -> 67.2 | H63: 487.2
A64: 46065 | B64: TMB - Redevance VICTOIRE 01/2026 | C64: 2026.01/DA/39 | D64: 136/1-56/2026 | E64: =+H64/1.16 -> 236.25 | G64: =+H64-E64 -> 37.8 | H64: 274.05
A65: 46065 | B65: TMB - Redevance DG 01/2026 | C65: 2026.01/DA/40 | D65: 136/1-57/2026 | E65: =+H65/1.16 -> 1393.8793 | G65: =+H65-E65 -> 223.02069 | H65: 1616.9
A66: 46065 | B66: IMANI - Redevance 01/2026 | C66: 2026.01/DA/41 | D66: 136/1-58/2026 | E66: =+H66/1.16 -> 210 | G66: =+H66-E66 -> 33.6 | H66: 243.6
A67: 46065 | B67: SOGIC - Redevance ROI BAUDOUIN 01/2026 | C67: 2026.01/DA/42 | D67: 136/1-59/2026 | E67: =+H67/1.16 -> 192.14655 | G67: =+H67-E67 -> 30.743448 | H67: 222.89
A68: 46065 | B68: BELTEXCO 1 - Redevance 01/2026 | C68: 2026.01/DA/43 | D68: 136/1-60/2026 | E68: =+H68/1.16 -> 135.98276 | G68: =+H68-E68 -> 21.757241 | H68: 157.74
A69: 46065 | B69: BELTEXCO 2 - Redevance 01/2026 | C69: 2026.01/DA/44 | D69: 136/1-61/2026 | E69: =+H69/1.16 -> 154.35345 | G69: =+H69-E69 -> 24.696552 | H69: 179.05
A70: 46065 | B70: IAG - Redevance CONCESSION 01/2026 | C70: 2026.01/DA/45 | D70: 136/1-62/2026 | E70: =+H70/1.16 -> 1200 | G70: =+H70-E70 -> 192 | H70: 1392
A71: 46065 | B71: COMMUNAUTE HELLENIQUE - Redevance 01/2026 | C71: 2026.01/DA/46 | D71: 136/1-63/2026 | E71: =+H71/1.16 -> 126 | G71: =+H71-E71 -> 20.16 | H71: 146.16
... A74: 46070 | B74: EBALE RESIDENCE - Redevance mensuelle 01/2026 | C74: 2026.01/DA/49 | D74: 136/1-66/2026 | E74: =+H74/1.16 -> 174.56034 | G74: =+H74-E74 -> 27.929655 | H74: 202.49
A75: 46070 | B75: LFRD - Redevance mensuelle 01/2026 | C75: 2026.01/DA/50 | D75: 136/1-67/2026 | E75: 500 | F75: 0 | G75: 0 | H75: 500
A76: 46070 | B76: C.H. MONKOLE - Redevance 01/2026 | C76: 2026.01/DA/51 | D76: 136/1-68/2026 | E76: 700 | F76: 0 | G76: 0 | H76: 700
A77: 46070 | B77: US EMBASSY - Redevance PANORAMA 01/2026 | C77: 2026.01/DA/52 | D77: 136/1-69/2026 | E77: 250 | F77: 0 | G77: 0 | H77: 250
A78: 46070 | B78: AMBABEL - Redevance mensuelle 01/2025 | C78: 2026.01/DA/53 | D78: 136/1-70/2026 | E78: 750 | F78: 0 | G78: 0 | H78: 750
A79: 46070 | B79: MONUSCO - Redevance 1er TRIM.2026 | C79: 2026.01/DA/54 | D79: 136/1-71/2026 | E79: 1200 | F79: 0 | G79: 0 | H79: 1200
A80: 46070 | B80: BRITISH EMBASSY - Redevance mensuelle 01/2026 | C80: 2026.01/DA/55 | D80: 136/1-72/2026 | E80: 157.5 | F80: 0 | G80: 0 | H80: 157.5
A81: 46070 | B81: BANQUE MONDIALE - Redevance mensuelle 01/2026 | C81: 2026.01/DA/56 | D81: 136/1-73/2026 | E81: 400 | F81: 0 | G81: 0 | H81: 400
A82: 46070 | B82: UTEXAFRICA - Redevance BOIS NOBLES 2B 01/2026 | C82: 2026.01/DA/57 | D82: 136/1-74/2026 | E82: =+H82/1.16 -> 534.13793 | G82: =+H82-E82 -> 85.462069 | H82: 619.6
A83: 46070 | B83: EBCDC - Redevance & surveillance escalators 01/2026 | C83: 2026.01/DA/58 | D83: 136/1-75/2026 | E83: =+H83/1.16 -> 600 | G83: =+H83-E83 -> 96 | H83: 696
A84: 46070 | B84: TALGARTH HOLDING INC - Redevance BAMBOU 01-02/2026 | C84: 2026.01/DA/59 | D84: 136/1-76/2026 | E84: =+H84/1.16 -> 500 | G84: =+H84-E84 -> 80 | H84: 580
A85: 46070 | B85: TALGARTH HOLDING INC - Redevance EQUATEUR 01-02/2026 | C85: 2026.01/DA/60 | D85: 136/1-77/2026 | E85: =+H85/1.16 -> 250 | G85: =+H85-E85 -> 40 | H85: 290
A86: 46070 | B86: IMMOKIN - Redevance TILAPIA 01-02/2026 | C86: 2026.01/DA/61 | D86: 136/1-78/2026 | E86: =+H86/1.16 -> 250 | G86: =+H86-E86 -> 40 | H86: 290
A87: 46070 | B87: MIDEMA - Redevance mensuelle 01/2026 | C87: 2026.01/DA/62 | D87: 136/1-79/2026 | E87: =+H87/1.16 -> 275 | G87: =+H87-E87 -> 44 | H87: 319
A88: 46070 | B88: MAJESTIC RIVER - Redevance mensuelle 01/2026 | C88: 2026.01/DA/63 | D88: 136/1-80/2026 | E88: =+H88/1.16 -> 350 | G88: =+H88-E88 -> 56 | H88: 406
A89: 46070 | B89: SOGIC - Redevance ROI BOULEVARD 01/2026 | C89: 2026.01/DA/64 | D89: 136/1-81/2026 | E89: =+H89/1.16 -> 192.14655 | G89: =+H89-E89 -> 30.743448 | H89: 222.89
A90: 46071 | B90: EJCSDJ - Fo&po 2 fans moteur chiller 2026.01/DT/18 | C90: 2026/DT/01/18 | D90: 136/1-82/2026 | E90: =+(H90+I90)/1.16 -> 8752.25 | F90: =+I90-E90 -> 1400.36 | G90: 0 | I90: 10152.61
A91: 46071 | B91: EJCSDJ - Entretien clim 1er TRIM. 2026.01/DT/19 | C91: 2026/DT/01/19 | D91: 136/1-83/2026 | E91: =+(H91+I91)/1.16 -> 4812.5 | F91: =+I91-E91 -> 770 | G91: 0 | I91: 5582.5
A92: 46071 | B92: RAWBANK - Entretien clim 1erTOUR 2026.01/DT/16 | C92: 2026/DT/01/20 | D92: 136/1-84/2026 | E92: =+(H92+I92)/1.16 -> 980 | F92: =+I92-E92 -> 156.8 | G92: 0 | I92: 1136.8
A93: 46073 | B93: Immeuble SERKAS - Redevance 01/2026 | C93: 2026.01/DA/65 | D93: 136/1-85/2026 | E93: =+H93/1.16 -> 181.43966 | G93: =+H93-E93 -> 29.030345 | H93: 210.47
A94: 46073 | B94: AFRICANA PALACE - Redevance 01/2026 | C94: 2026.01/DA/67 | D94: 136/1-86/2026 | E94: =+H94/1.16 -> 189 | G94: =+H94-E94 -> 30.24 | H94: 219.24
A95: 46073 | B95: Immeuble DELPHIN (LA GRACE DE DIEU) - Redevance 01/2026 | C95: 2026.01/DA/66 | D95: 136/1-87/2026 | E95: =+H95/1.16 -> 210 | G95: =+H95-E95 -> 33.6 | H95: 243.6
A96: 46077 | B96: DEVIMCO - Redevance AMBASSADEUR 02/2026 | C96: 2026.01/DA/68 | D96: 136/1-88/2026 | E96: =+H96/1.16 -> 105 | G96: =+H96-E96 -> 16.8 | H96: 121.8
A97: 46077 | B97: DEVIMCO - Redevance TRADITION 02/2026 | C97: 2026.01/DA/69 | D97: 136/1-89/2026 | E97: =+H97/1.16 -> 252 | G97: =+H97-E97 -> 40.32 | H97: 292.32
A98: 46077 | B98: DEVIMCO - Redevance CONCORDE 02/2026 | C98: 2026.01/DA/70 | D98: 136/1-90/2026 | E98: =+H98/1.16 -> 420 | G98: =+H98-E98 -> 67.2 | H98: 487.2
A99: 46077 | B99: TMB - Redevance DG 02/2026 | C99: 2026.01/DA/71 | D99: 136/1-91/2026 | E99: =+H99/1.16 -> 1393.8793 | G99: =+H99-E99 -> 223.02069 | H99: 1616.9
A100: 46077 | B100: SOGIC - Redevance BOULEVARD 02/2026 | C100: 2026.02/DA/72 | D100: 136/1-92/2026 | E100: =+H100/1.16 -> 192.14655 | G100: =+H100-E100 -> 30.743448 | H100: 222.89
A101: 46077 | B101: SOGIC - Redevance ROI BAUDOUIN 02/2026 | C101: 2026.02/DA/73 | D101: 136/1-93/2026 | E101: =+H101/1.16 -> 192.14655 | G101: =+H101-E101 -> 30.743448 | H101: 222.89
A102: 46077 | B102: BELTEXCO 1 - Redevance 02/2026 | C102: 2026.01/DA/74 | D102: 136/1-94/2026 | E102: =+H102/1.16 -> 135.98276 | G102: =+H102-E102 -> 21.757241 | H102: 157.74
A103: 46077 | B103: BELTEXCO 2 - Redevance 02/2026 | C103: 2026.01/DA/75 | D103: 136/1-95/2026 | E103: =+H103/1.16 -> 154.35345 | G103: =+H103-E103 -> 24.696552 | H103: 179.05
A104: 46077 | B104: COMPAGNIE SUCRIERE - Supplment Dépannage 4eTRIM.2025 | C104: 2026/DT/01/21 | D104: 136/1-96/2026 | E104: =+(H104+I104)/1.16 -> 637.60345 | F104: =+I104-E104 -> 102.01655 | G104: 0 | I104: 739.62
A105: 46077 | B105: UTEXAFRICA - Entretien clim 3eTRIM.2025 | C105: 2026/DT/01/22 | D105: 136/1-97/2026 | E105: =+(H105+I105)/1.16 -> 8085 | F105: =+I105-E105 -> 1293.6 | G105: 0 | I105: 9378.6
...

Sheet FACTURES SN
A1: ELECTROCOOL SARL
A2: FACTURATION SN 2026
A4: DATE | B4: Clients | C4: N° Facture | D4: PRODUITS | E4: TVA | G4: SN | I4: Total | J4: Encaissement | K4: Solde
F5: Plomberie | G5: CLIM | H5: ASC
A7: 46018 | B7: SHEHENAJ L.M. - Fo&po 2 garnitures cabine IMM. MBUJI MAYI (ANNULEE cfr 2025/SN12/1 | C7: 2026.01/SN/1 | D7: =+I7-E7 -> 0 | I7: 0 | K7: =I7-J7 -> 0 | BG7: =AX7+AW7+AV7+AU7+AT7+AS7+AR7+AQ7+AP7+AN7+AM7+AL7+AK7+AJ7+AI7+AH7+AG7+AF7+AE7+AD7+AC7+AB7+AA7+Z7+Y7+X7+W7+V7+U7+T7+S7+R7+Q7+P7+O7+N7+M7 -> 0
A8: 46018 | B8: SHEHENAJ L.M. - Fo&po 1 bouton appel cabine IMM. COMMERCE (ANNULEE cfr 2025/SN12/2 | C8: 2026.01/SN/2 | D8: =+I8-E8 -> 0 | I8: 0 | K8: =I8-J8 -> 0 | BG8: =AX8+AW8+AV8+AU8+AT8+AS8+AR8+AQ8+AP8+AN8+AM8+AL8+AK8+AJ8+AI8+AH8+AG8+AF8+AE8+AD8+AC8+AB8+AA8+Z8+Y8+X8+W8+V8+U8+T8+S8+R8+Q8+P8+O8+N8+M8 -> 0
A9: 46018 | B9: SHEHENAJ L.M. - Redevance IMMEUBLE COMMERCE 12/2025 (ANNULEE cfr 2025/SN12/3) | C9: 2026.01/SN/3 | D9: =+I9-E9 -> 0 | I9: 0 | K9: =I9-J9 -> 0 | BG9: =AX9+AW9+AV9+AU9+AT9+AS9+AR9+AQ9+AP9+AN9+AM9+AL9+AK9+AJ9+AI9+AH9+AG9+AF9+AE9+AD9+AC9+AB9+AA9+Z9+Y9+X9+W9+V9+U9+T9+S9+R9+Q9+P9+O9+N9+M9 -> 0
A10: 46018 | B10: SHEHENAJ L.M. - Redevance IMMEUBLE PACIFIQUE 12/2025 (ANNULEE cfr 2025/SN12/4) | C10: 2026.01/SN/4 | D10: =+I10-E10 -> 0 | I10: 0 | K10: =I10-J10 -> 0 | BG10: =AX10+AW10+AV10+AU10+AT10+AS10+AR10+AQ10+AP10+AN10+AM10+AL10+AK10+AJ10+AI10+AH10+AG10+AF10+AE10+AD10+AC10+AB10+AA10+Z10+Y10+X10+W10+V10+U10+T10+S10+R10+Q10+P10+O10+N10+M10 -> 0
C11: 2026.01/SN/5 | D11: =+I11-E11 -> 0 | I11: 0 | K11: =I11-J11 -> 0
C12: 2026.01/SN/6 | D12: =+I12-E12 -> 0 | I12: 0 | K12: =I12-J12 -> 0
A14: 46036 | B14: RESIDENCE EMERAUDE - Réinstallation liaisons frigo APT 2 cfr 2eNIVEAU | C14: 2026.01/SN/1 | D14: =+I14-E14 -> 296 | G14: 296 | I14: 296 | K14: =I14-J14 -> 296
A15: 46036 | B15: RESIDENCE EMERAUDE - Depannage clim APT 2-4 cfr 2eNIVEAU | C15: 2026.01/SN/2 | D15: =+I15-E15 -> 220 | G15: 220 | I15: 220 | J15: 220 | K15: =I15-J15 -> 0
A16: 46036 | B16: SN ZHENDRE - Frais dédouanement colis AERO/LUANO | C16: 2026.01/SN/3 | D16: =+I16-E16 -> 3800 | H16: 3800 | I16: 3800 | K16: =I16-J16 -> 3800
A17: 46036 | B17: A ONE CONSTRUCTION - Redevance mensuelle PANORAMIQUE 12/2025 | C17: 2026.01/SN/4 | D17: =+I17-E17 -> 400 | H17: 400 | I17: 400 | J17: 400 | K17: =I17-J17 -> 0
A18: 46036 | B18: Monsieur KETELEER PRINCE - Entretien clim 12/202 | C18: 2026.01/SN/5 | D18: =+I18-E18 -> 175 | G18: 175 | I18: 175 | J18: 175 | K18: =I18-J18 -> 0
A19: 46036 | B19: LYS SARL - Redevance LYS TOWER 12/2025 | C19: 2026.01/SN/6 | D19: =+I19-E19 -> 200 | H19: 200 | I19: 200 | J19: 200 | K19: =I19-J19 -> 0
A20: 46036 | B20: IMMEUBLE MARIE YVETTE - Redevance mensuelle 12/2025 | C20: 2026.01/SN/7 | D20: =+I20-E20 -> 174 | H20: 174 | I20: 174 | J20: 174 | K20: =I20-J20 -> 0 | BG20: =AX20+AW20+AV20+AU20+AT20+AS20+AR20+AQ20+AP20+AN20+AM20+AL20+AK20+AJ20+AI20+AH20+AG20+AF20+AE20+AD20+AC20+AB20+AA20+Z20+Y20+X20+W20+V20+U20+T20+S20+R20+Q20+P20+O20+N20+M20 -> 0
A21: 46036 | B21: LYS SARL - Redevance LYS CENTER 11/2025 | C21: 2026.01/SN/8 | D21: =+I21-E21 -> 600 | H21: 600 | I21: 600 | J21: 600 | K21: =I21-J21 -> 0 | BG21: =AX21+AW21+AV21+AU21+AT21+AS21+AR21+AQ21+AP21+AN21+AM21+AL21+AK21+AJ21+AI21+AH21+AG21+AF21+AE21+AD21+AC21+AB21+AA21+Z21+Y21+X21+W21+V21+U21+T21+S21+R21+Q21+P21+O21+N21+M21 -> 0
A22: 46036 | B22: IMMEUBLE LEGREY - Redevance mensuelle 12/2025 | C22: 2026.01/SN/9 | D22: =+I22-E22 -> 400 | H22: 400 | I22: 400 | J22: 400 | K22: =I22-J22 -> 0 | BG22: =AX22+AW22+AV22+AU22+AT22+AS22+AR22+AQ22+AP22+AN22+AM22+AL22+AK22+AJ22+AI22+AH22+AG22+AF22+AE22+AD22+AC22+AB22+AA22+Z22+Y22+X22+W22+V22+U22+T22+S22+R22+Q22+P22+O22+N22+M22 -> 0
A23: 46036 | B23: ESPACE SHADARY - Redevance CITE VERTE 12/2025 | C23: 2026.01/SN/10 | D23: =+I23-E23 -> 200 | H23: 200 | I23: 200 | J23: 200 | K23: =I23-J23 -> 0 | BG23: =AX23+AW23+AV23+AU23+AT23+AS23+AR23+AQ23+AP23+AN23+AM23+AL23+AK23+AJ23+AI23+AH23+AG23+AF23+AE23+AD23+AC23+AB23+AA23+Z23+Y23+X23+W23+V23+U23+T23+S23+R23+Q23+P23+O23+N23+M23 -> 0
A24: 46047 | B24: LIBERTY - Redevance mensuelle LUBUMBASHI 01/2026 | C24: 2026.01/SN/11 | D24: =+I24-E24 -> 577.5 | H24: 577.5 | I24: 577.5 | K24: =I24-J24 -> 577.5
A25: 46047 | B25: DEV GROUP - Redevance mensuelle DEV SOLAIRE LUSHI 01/2026 | C25: 2026.01/SN/12 | D25: =+I25-E25 -> 288.75 | H25: 288.75 | I25: 288.75 | J25: 14 | K25: =I25-J25 -> 274.75
A26: 46047 | B26: IMMEUBLE MALAIKA - Redevance 1er TRIM.2026 | C26: 2026.01/SN/13 | D26: =+I26-E26 -> 450 | H26: 450 | I26: 450 | J26: 450 | K26: =I26-J26 -> 0
A27: 46047 | B27: IMMEUBLE MARIE YVETTE - Redevance mensuelle 01/2026 | C27: 2026.01/SN/14 | D27: =+I27-E27 -> 182.7 | H27: 182.7 | I27: 182.7 | J27: 182.7 | K27: =I27-J27 -> 0
A28: 46050 | B28: ESPACE SHADARY - Redevance CITE VERTE 01/2026 | C28: 2026.01/SN/15 | D28: =+I28-E28 -> 210 | H28: 210 | I28: 210 | J28: 210 | K28: =I28-J28 -> 0
A29: 46050 | B29: ESPACE SHADARY - Redevance LUBEFU 01/2026 | C29: 2026.01/SN/16 | D29: =+I29-E29 -> 210 | H29: 210 | I29: 210 | J29: 210 | K29: =I29-J29 -> 0
A30: 46050 | B30: SHEHENAJ L.M. - Redevance COMMERCE (HARMONIE) 01/2026 | C30: 2026.01/SN/17 | D30: =+I30-E30 -> 183.75 | H30: 183.75 | I30: 183.75 | J30: 175 | K30: =I30-J30 -> 8.75
A31: 46050 | B31: SHEHENAJ L.M. - Redevance PACIFIQUE 01/2026 | C31: 2026.01/SN/18 | D31: =+I31-E31 -> 367.5 | H31: 367.5 | I31: 367.5 | J31: 350 | K31: =I31-J31 -> 17.5
A32: 46050 | B32: A ONE CONSTRUCTION - Redevance mensuelle PANORAMIQUE 01/2026 | C32: 2026.01/SN/19 | D32: =+I32-E32 -> 210 | H32: 210 | I32: 210 | J32: 210 | K32: =I32-J32 -> 0
A33: 46050 | B33: IMMEUBLE LEGREY - Redevance mensuelle 01/2026 | C33: 2026.01/SN/20 | D33: =+I33-E33 -> 420 | H33: 420 | I33: 420 | J33: 420 | K33: =I33-J33 -> 0
A34: 46053 | B34: LYS SARL - Redevance LYS CENTER 12/2025 | C34: 2026.01/SN/21 | D34: =+I34-E34 -> 600 | H34: 600 | I34: 600 | J34: 600 | K34: =I34-J34 -> 0
A35: 46053 | B35: LYS SARL - Redevance LYS TOWER 01/2026 | C35: 2026.01/SN/22 | D35: =+I35-E35 -> 400 | H35: 400 | I35: 400 | K35: =I35-J35 -> 400
A36: 46053 | B36: LYS SARL - Redevance LYS CENTER 01/2026 | C36: 2026.01/SN/23 | D36: =+I36-E36 -> 600 | H36: 600 | I36: 600 | J36: 156.4 | K36: =I36-J36 -> 443.6
A37: 46053 | B37: ESPACE SHADARY - Redevance NYEMBO 01/2026 | C37: 2026.01/SN/24 | D37: =+I37-E37 -> 210 | H37: 210 | I37: 210 | K37: =I37-J37 -> 210
BG38: =+AQ38+AP38+AN38+AM38+AL38+AK38+AJ38+AI38+AH38+AG38+AF38+AE38+AD38+AC38+AB38+AA38+Z38+Y38+X38+W38+V38+U38+T38+S38+R38+Q38+P38+O38+N38+M38 -> 0
B39: FACTURATION SN - JANVIER 2026 | D39: =SUM(D7:D38) -> 11375.2 | E39: =SUM(E7:E38) -> 0 | F39: =SUM(F7:F38) -> 0 | G39: =SUM(G7:G38) -> 691 | H39: =SUM(H7:H38) -> 10684.2 | I39: =SUM(I7:I38) -> 11375.2 | J39: =SUM(J7:J38) -> 5347.1 | K39: =I39-J39 -> 6028.1 | M39: =SUM(M7:M38) -> 0 | N39: =SUM(N7:N38) -> 0 | O39: =SUM(O7:O38) -> 0 | P39: =SUM(P7:P38) -> 0 | Q39: =SUM(Q7:Q38) -> 0 | R39: =SUM(R7:R38) -> 0 | S39: =SUM(S7:S38) -> 0 | T39: =SUM(T7:T38) -> 0 | ... AN39: =SUM(AN7:AN38) -> 0 | AP39: =SUM(AP7:AP38) -> 0 | AQ39: =SUM(AQ7:AQ38) -> 0 | AR39: =SUM(AR7:AR38) -> 0 | AS39: =SUM(AS7:AS38) -> 0 | AT39: =SUM(AT7:AT38) -> 0 | AU39: =SUM(AU7:AU38) -> 0 | AV39: =SUM(AV7:AV38) -> 0 | AW39: =SUM(AW7:AW38) -> 0 | ... AY39: =SUM(AY7:AY38) -> 0 | BG39: =SUM(BG7:BG38) -> 0
A41: 46069 | B41: SHEHENAJ L.M. - Redevance PACIFIQUE 02/2026 | C41: 2026.01/SN/25 | D41: =+I41-E41 -> 367.5 | H41: 367.5 | I41: 367.5 | J41: 367.5 | K41: =I41-J41 -> 0
A42: 46069 | B42: A ONE CONSTRUCTION - Redevance PANORAMIQUE (ESTORIL) 02/2026 | C42: 2026.01/SN/26 | D42: =+I42-E42 -> 420 | H42: 420 | I42: 420 | J42: 420 | K42: =I42-J42 -> 0
A43: 46069 | B43: LYS SARL - Redevance LYS TOWER 02/2026 | C43: 2026.01/SN/27 | D43: =+I43-E43 -> 400 | H43: 400 | I43: 400 | K43: =I43-J43 -> 400
A44: 46069 | B44: IMMEUBLE TATELIE - Redevance mensuelle 01/2026 - DECEMBRE ??? | C44: 2026.01/SN/28 | D44: =+I44-E44 -> 174 | H44: 157.5 | I44: 174 | J44: 174 | K44: =I44-J44 -> 0
A45: 46069 | B45: LYS SARL - Entretien condenseur VRV+8 Evapo EUNICE/VILLA 5 | C45: 2026.02/SN/29 | D45: =+I45-E45 -> 225 | G45: 225 | I45: 225 | K45: =I45-J45 -> 225
A46: 46069 | B46: IMMEUBLE IMANI - Redevance mensuelle 02/2026 | C46: 2026.01/SN/30 | D46: =+I46-E46 -> 243.6 | H46: 243.6 | I46: 243.6 | J46: 243.6 | K46: =I46-J46 -> 0
A47: 46069 | B47: RESIDENCE EMERAUDE - Entretien general clim 1er TOUR 2026 | C47: 2026.01/SN/31 | D47: =+I47-E47 -> 700 | G47: 700 | I47: 700 | J47: 700 | K47: =I47-J47 -> 0
A48: 46069 | B48: LYS SARL - Dépannage clim BOUTIQUE COULOIR LYS CENTER | C48: 2026.01/SN/32 | D48: =+I48-E48 -> 846 | G48: 846 | I48: 846 | K48: =I48-J48 -> 846
A49: 46069 | B49: LYS SARL - Dépannage machines VRV 2é&3é Etage LYS CENTER | C49: 2026.01/SN/33 | D49: =+I49-E49 -> 194.6 | H49: 194.6 | I49: 194.6 | K49: =I49-J49 -> 194.6
A50: 46078 | B50: Monsieur THOMAS - Entretien clim 12/2025 | C50: 2026.01/SN/34 | D50: =+I50-E50 -> 210 | H50: 210 | I50: 210 | J50: 210 | K50: =I50-J50 -> 0
A51: 46078 | B51: SHEHENAJ L.M. - Redevance COMMERCE (HARMONIE) 02/2026 | C51: 2026.01/SN/35 | D51: =+I51-E51 -> 183.75 | H51: 183.75 | I51: 183.75 | J51: 183.75 | K51: =I51-J51 -> 0
A52: 46078 | B52: LYS SARL - Fo&po 4 garnitures de PRS / LYS CENTER | C52: 2026.01/SN/36 | D52: =+I52-E52 -> 100 | H52: 100 | I52: 100 | K52: =I52-J52 -> 100
A53: 46078 | B53: RESIDENCE KAWELE - Redevance mensuelle 02/2026 | C53: 2026.01/SN/37 | D53: =+I53-E53 -> 250 | H53: 250 | I53: 250 | J53: 250 | K53: =I53-J53 -> 0
A54: 46080 | B54: IMMEUBLE MARIE YVETTE - Redevance mensuelle 02/2026 | C54: 2026.01/SN/38 | D54: =+I54-E54 -> 182.7 | H54: 182.7 | I54: 182.7 | J54: 182.7 | K54: =I54-J54 -> 0
A55: 46080 | B55: ESPACE SHADARY - Redevance CITE VERTE 02/2026 | C55: 2026.01/SN/39 | D55: =+I55-E55 -> 210 | H55: 210 | I55: 210 | K55: =I55-J55 -> 210
A56: 46081 | B56: LIBERTY - Redevance 02/2026 | C56: 2026.01/SN/40 | D56: =+I56-E56 -> 577.5 | H56: 577.5 | I56: 577.5 | K56: =I56-J56 -> 577.5
A57: 46081 | B57: DEV GROUP - Redevance DEV SOLAIRE 02/2026 | C57: 2026.01/SN/41 | D57: =+I57-E57 -> 288.75 | H57: 288.75 | I57: 288.75 | K57: =I57-J57 -> 288.75
A58: 46081 | B58: IMMEUBLE TATELIE - Redevance mensuelle 01/2026 | C58: 2026.01/SN/42 | D58: =+I58-E58 -> 174 | H58: 174 | I58: 174 | J58: 174 | K58: =I58-J58 -> 0
A59: 46081 | B59: IMMEUBLE LEGREY - Redevance 02/2026 | C59: 2026.01/SN/43 | D59: =+I59-E59 -> 420 | H59: 420 | I59: 420 | J59: 420 | K59: =I59-J59 -> 0
A60: 46081 | B60: ESPACE SHADARY - Redevance LUBEFU 02/2026 | C60: 2026.01/SN/44 | D60: =+I60-E60 -> 210 | H60: 210 | I60: 210 | K60: =I60-J60 -> 210
A61: 46081 | B61: ESPACE SHADARY - Redevance NYEMBO 02/2026 | C61: 2026.01/SN/45 | D61: =+I61-E61 -> 210 | H61: 210 | I61: 210 | K61: =I61-J61 -> 210
K62: =I62-J62 -> 0 | BG62: =+AR62+AQ62+AP62+AN62+AM62+AL62+AK62+AJ62+AI62+AH62+AG62+AF62+AE62+AD62+AC62+AB62+AA62+Z62+Y62+X62+W62+V62+U62+T62+S62+R62+Q62+P62+O62+N62+M62 -> 0
B63: FACTURATION SN - FEVRIER 2026 | D63: =SUM(D40:D62) -> 6587.4 | E63: =SUM(E40:E62) -> 0 | F63: =SUM(F40:F62) -> 0 | G63: =SUM(G40:G62) -> 1771 | H63: =SUM(H40:H62) -> 4799.9 | I63: =SUM(I40:I62) -> 6587.4 | J63: =SUM(J40:J62) -> 3325.55 | K63: =I63-J63 -> 3261.85 | M63: =SUM(M40:M62) -> 0 | N63: =SUM(N40:N62) -> 0 | O63: =SUM(O40:O62) -> 0 | P63: =SUM(P40:P62) -> 0 | Q63: =SUM(Q40:Q62) -> 0 | R63: =SUM(R40:R62) -> 0 | S63: =SUM(S40:S62) -> 0 | T63: =SUM(T40:T62) -> 0 | ... AN63: =SUM(AN40:AN62) -> 0 | AP63: =SUM(AP40:AP62) -> 0 | AQ63: =SUM(AQ40:AQ62) -> 0 | AR63: =SUM(AR40:AR62) -> 0 | AS63: =SUM(AS40:AS62) -> 0 | AT63: =SUM(AT40:AT62) -> 0 | AU63: =SUM(AU40:AU62) -> 0 | AV63: =SUM(AV40:AV62) -> 0 | AW63: =SUM(AW40:AW62) -> 0 | ... BA63: =SUM(BA40:BA62) -> 0 | BG63: =SUM(BG40:BG62) -> 0
A65: 46093 | B65: PROJET KIMPEVILLE - Installation & mise en service ASC/KIMPEVILLE | C65: 2026.01/SN/46 | D65: =+I65-E65 -> 7640 | H65: 7640 | I65: 7640 | K65: =I65-J65 -> 7640
A66: 46093 | B66: SHEHENAJ L.M. - Redevance PACIFIQUE 03/2026 | C66: 2026.01/SN/47 | D66: =+I66-E66 -> 367.5 | H66: 367.5 | I66: 367.5 | J66: 367.5 | K66: =I66-J66 -> 0
A67: 46093 | B67: A ONE CONSTRUCTION - Redevance PANORAMIQUE (ESTORIL) 03/2026 | C67: 2026.01/SN/48 | D67: =+I67-E67 -> 420 | H67: 420 | I67: 420 | J67: 420 | K67: =I67-J67 -> 0
A68: 46093 | B68: LIBERTY - Redevance SUPER MARCHE LUSHI 03/2026 | C68: 2026.01/SN/49 | D68: =+I68-E68 -> 577.5 | I68: 577.5 | K68: =I68-J68 -> 577.5
A69: 46093 | B69: DEV GROUP - Redevance mensuelle 03/2026 | C69: 2026.01/SN/50 | D69: =+I69-E69 -> 288.75 | H69: 288.75 | I69: 288.75 | K69: =I69-J69 -> 288.75
A70: 46093 | B70: A ONE CONSTRUCTION - Fo&po 1 Crate GECB-AP / PANORAMIQUE | C70: 2026.01/SN/51 | D70: =+I70-E70 -> 3418.08 | H70: 3418.08 | I70: 3418.08 | K70: =I70-J70 -> 3418.08
A71: 46094 | B71: MR THOMAS - Chargement freon R22 split DAIKIN/BUREAU | C71: 2026.01/SN/52 | D71: =+I71-E71 -> 140 | G71: 140 | I71: 140 | J71: 140 | K71: =I71-J71 -> 0
A72: 46101 | B72: SHEHENAJ L.M. - Redevance COMMERCE (HARMONIE) 03/2026 | C72: 2026.01/SN/53 | D72: =+I72-E72 -> 183.75 | H72: 183.75 | I72: 183.75 | J72: 183.75 | K72: =I72-J72 -> 0
A73: 46104 | B73: IMMEUBLE LEGREY - Fo&po 4 galets porte cabine & 4 glissieres ASC | C73: 2026.01/SN/54 | D73: =+I73-E73 -> 553 | H73: 553 | I73: 553 | J73: 553 | K73: =I73-J73 -> 0
A74: 46104 | B74: SHEHENAJ L.M. - Fo&po support detecteur ASC/PACIFIQUE | C74: 2026.01/SN/55 | D74: =+I74-E74 -> 100 | H74: 100 | I74: 100 | J74: 100 | K74: =I74-J74 -> 0
A75: 46107 | B75: IMMEUBLE LEGREY - Redevance 03/2026 | C75: 2026.01/SN/56 | D75: =+I75-E75 -> 420 | H75: 420 | I75: 420 | J75: 420 | K75: =I75-J75 -> 0
A76: 46110 | B76: RESIDENCE KAWELE - Redevance 03/2026 | C76: 2026.01/SN/57 | D76: =+I76-E76 -> 250 | H76: 250 | I76: 250 | J76: 250 | K76: =I76-J76 -> 0
A77: 46110 | B77: LYS SARL - Redevance LYS CENTER 02/2026 | C77: 2026.01/SN/58 | D77: =+I77-E77 -> 600 | H77: 182.7 | I77: 600 | K77: =I77-J77 -> 600
A78: 46110 | B78: IMMEUBLE MARIE YVETTE - Redevance mensuelle 03/2026 | C78: 2026.01/SN/59 | D78: =+I78-E78 -> 182.7 | H78: 210 | I78: 182.7 | J78: 182.7 | K78: =I78-J78 -> 0
A79: 46110 | B79: ESPACE SHADARY - Redevance NYEMBO 03/2026 | C79: 2026.01/SN/60 | D79: =+I79-E79 -> 210 | H79: 210 | I79: 210 | K79: =I79-J79 -> 210
A80: 46112 | B80: LYS SARL - Fo&po 12 garnitures cabine ASC / LYS TOWER | C80: 2026.01/SN/61 | D80: =+I80-E80 -> 1308 | H80: 1308 | I80: 1308 | J80: 1300 | K80: =I80-J80 -> 8
A81: 46112 | B81: COMIMMO - Entretien 95 cassettes VRV avec 8 condenseurs & 19 splits | C81: 2026.01/SN/62 | D81: =+I81-E81 -> 6281.4 | G81: 6281.4 | I81: 6281.4 | K81: =I81-J81 -> 6281.4
A82: 46112 | B82: ESPACE SHADARY - Redevance CITE VERTE 03/2026 | C82: 2026.01/SN/63 | D82: =+I82-E82 -> 210 | H82: 210 | I82: 210 | K82: =I82-J82 -> 210
A83: 46112 | B83: IMMEUBLE TATELIE - Redevance mensuelle 03/2026 | C83: 2026.01/SN/64 | D83: =+I83-E83 -> 174 | H83: 174 | I83: 174 | J83: 174 | K83: =I83-J83 -> 0
A84: 46112 | B84: IMMEUBLE IMANI - Redevance mensuelle 03/2026 | C84: 2026.01/SN/65 | D84: =+I84-E84 -> 243.6 | H84: 243.6 | I84: 243.6 | J84: 243.6 | K84: =I84-J84 -> 0
A85: 46112 | B85: SHEHENAJ L.M. - Fo&po 1 garniture cabine IMM.PACIFIQUE | C85: 2026.01/SN/66 | D85: =+I85-E85 -> 109 | H85: 109 | I85: 109 | J85: 109 | K85: =I85-J85 -> 0
A86: 46112 | B86: DFSN - Entretien general clim 1erTRIM.2026 | C86: 2026.01/SN/67 | D86: =+I86-E86 -> 245 | G86: 245 | I86: 245 | J86: 245 | K86: =I86-J86 -> 0
A87: 46112 | B87: MAGASIN DIPLOMATIQUE - Entretien general clim 1erTRIM.2026 | C87: 2026.01/SN/68 | D87: =+I87-E87 -> 525 | G87: 525 | I87: 525 | J87: 525 | K87: =I87-J87 -> 0
BG88: =+AP88+AN88+AM88+AL88+AK88+AJ88+AI88+AH88+AG88+AF88+AE88+AD88+AC88+AB88+AA88+Z88+Y88+X88+W88+V88+U88+T88+S88+R88+Q88+P88+O88+N88+M88 -> 0
B89: FACTURATION SN - MARS 2026 | D89: =SUM(D64:D88) -> 24447.28 | E89: =SUM(E64:E88) -> 0 | F89: =SUM(F64:F88) -> 0 | G89: =SUM(G64:G88) -> 7191.4 | H89: =SUM(H64:H88) -> 16288.38 | I89: =SUM(I64:I88) -> 24447.28 | J89: =SUM(J64:J88) -> 5213.55 | K89: =I89-J89 -> 19233.73 | M89: =SUM(M64:M88) -> 0 | N89: =SUM(N64:N88) -> 0 | O89: =SUM(O64:O88) -> 0 | P89: =SUM(P64:P88) -> 0 | Q89: =SUM(Q64:Q88) -> 0 | R89: =SUM(R64:R88) -> 0 | S89: =SUM(S64:S88) -> 0 | T89: =SUM(T64:T88) -> 0 | ... AD89: =SUM(AD64:AD88) -> 0 | AI89: =SUM(AI64:AI88) -> 0 | AJ89: =SUM(AJ64:AJ88) -> 0 | AK89: =SUM(AK64:AK88) -> 0 | AL89: =SUM(AL64:AL88) -> 0 | AM89: =SUM(AM64:AM88) -> 0 | AN89: =SUM(AN64:AN88) -> 0 | AP89: =SUM(AP64:AP88) -> 0 | AQ89: =SUM(AQ64:AQ88) -> 0 | AR89: =SUM(AR64:AR88) -> 0 | AS89: =SUM(AS64:AS88) -> 0 | AT89: =SUM(AT64:AT88) -> 0 | AU89: =SUM(AU64:AU88) -> 0 | AV89: =SUM(AV64:AV88) -> 0 | AW89: =SUM(AW64:AW88) -> 0 | ... BA89: =SUM(BA64:BA88) -> 0 | BG89: =SUM(BG64:BG88) -> 0
A91: 46122 | B91: Mr PETER DEBOTTER - Entretien general clim AVRIL 2026 | C91: 2026.01/SN/69 | D91: =+I91-E91 -> 405 | G91: 405 | I91: 405 | J91: 405 | K91: =I91-J91 -> 0
A92: 46141 | B92: RS HOLDING - Restitution retenue reception definitive | C92: 2026.01/SN/70 | D92: =+I92-E92 -> 56900 | G92: 56900 | I92: 56900 | K92: =I92-J92 -> 56900
A93: 46141 | B93: SHEHENAJ L.M. - Redevance PACIFIQUE 04/2026 | C93: 2026.01/SN/71 | D93: =+I93-E93 -> 367.5 | H93: 367.5 | I93: 367.5 | J93: 367.5 | K93: =I93-J93 -> 0
A94: 46141 | B94: SHEHENAJ L.M. - Redevance COMMERCE (HARMONIE) 04/2026 | C94: 2026.01/SN/72 | D94: =+I94-E94 -> 183.75 | H94: 183.75 | I94: 183.75 | J94: 183.75 | K94: =I94-J94 -> 0
A95: 46142 | B95: LIBERTY - Redevance SUPER MARCHE LUSHI 04/2026 | C95: 2026.01/SN/73 | D95: =+I95-E95 -> 577.5 | H95: 577.5 | I95: 577.5 | K95: =I95-J95 -> 577.5
A96: 46142 | B96: DEV GROUP - Redevance mensuelle 04/2026 | C96: 2026.01/SN/74 | D96: =+I96-E96 -> 288.75 | H96: 288.75 | I96: 288.75 | K96: =I96-J96 -> 288.75
A97: 46142 | B97: A ONE CONSTRUCTION - Redevance PANORAMIQUE (ESTORIL) 04/2026 | C97: 2026.01/SN/75 | D97: =+I97-E97 -> 420 | H97: 420 | I97: 420 | J97: 420 | K97: =I97-J97 -> 0
A98: 46142 | B98: IMMEUBLE LEGREY - Redevance mensuelle 04/2026 | C98: 2026.01/SN/76 | D98: =+I98-E98 -> 420 | H98: 420 | I98: 420 | J98: 420 | K98: =I98-J98 -> 0
A99: 46142 | B99: LYS SARL - Entretien general clim LYS CENTER 1erTRIM.2026 | C99: 2026.01/SN/77 | D99: =+I99-E99 -> 6562.5 | G99: 6562.5 | I99: 6562.5 | K99: =I99-J99 -> 6562.5
A100: 46142 | B100: LYS SARL - Redevance LYS TOWER 03/2026 | C100: 2026.01/SN/78 | D100: =+I100-E100 -> 400 | H100: 400 | I100: 400 | K100: =I100-J100 -> 400
A101: 46142 | B101: LYS SARL - Redevance LYS TOWER 04/2026 | C101: 2026.01/SN/79 | D101: =+I101-E101 -> 400 | H101: 400 | I101: 400 | K101: =I101-J101 -> 400
A102: 46142 | B102: LYS SARL - Redevance LYS CENTER 03/2026 | C102: 2026.01/SN/80 | D102: =+I102-E102 -> 600 | H102: 600 | I102: 600 | K102: =I102-J102 -> 600
A103: 46142 | B103: LYS SARL - Redevance LYS CENTER 04/2026 | C103: 2026.01/SN/81 | D103: =+I103-E103 -> 600 | H103: 600 | I103: 600 | K103: =I103-J103 -> 600
A104: 46142 | B104: IMMEUBLE MALAIKA - Redevance trimestrielle 1erTRIM.2026 | C104: 2026.01/SN/82 | D104: =+I104-E104 -> 450 | H104: 450 | I104: 450 | J104: 450 | K104: =I104-J104 -> 0
A105: 46142 | B105: RESIDENCE KAWELE - Redevance 04/2026 | C105: 2026.01/SN/83 | D105: =+I105-E105 -> 250 | H105: 250 | I105: 250 | J105: 250 | K105: =I105-J105 -> 0
A106: 46142 | B106: IMMEUBLE TATELIE - Redevance mensuelle 04/2026 | C106: 2026.01/SN/84 | D106: =+I106-E106 -> 174 | H106: 174 | I106: 174 | K106: =I106-J106 -> 174
...

Sheet Feuil1
