Workbook

Sheet 062026
A1: ELECTROCOOL
A2: RAPPORT DE CAISSE | L2: 46174
B3: LIBELLES | D3: USD | H3: EUROS | J3: Francs
C4: ENC CLIENT | D4: ENTREE ($) | E4: SORTIE ($) | F4: SOLDE ($) | G4: ENTREE (Euro) | H4: SORTIE (Euro) | I4: SOLDE (Euro) | J4: ENTREE (Francs) | K4: SORTIE (Francs) | L4: SOLDE (francs)
B5: REPORT | D5: ='052026'!F378 -> 982 | F5: =D5 -> 982 | G5: 0 | I5: 0 | J5: ='052026'!L378 -> 206690 | L5: =J5 -> 206690
F6: =+F5+C6+D6-E6 -> 982 | H6: 0 | I6: =I5++G6-H6 -> 0 | L6: =L5++J6-K6 -> 206690
F7: =+F6+C7+D7-E7 -> 982 | I7: =I6++G7-H7 -> 0 | L7: =L6++J7-K7 -> 206690
F8: =+F7+C8+D8-E8 -> 982 | I8: =I7++G8-H8 -> 0 | L8: =L7++J8-K8 -> 206690
F9: =+F8+C9+D9-E9 -> 982 | I9: =I8++G9-H9 -> 0 | L9: =L8++J9-K9 -> 206690
F10: =+F9+C10+D10-E10 -> 982 | I10: =I9++G10-H10 -> 0 | L10: =L9++J10-K10 -> 206690
F11: =+F10+C11+D11-E11 -> 982 | I11: =I10++G11-H11 -> 0 | L11: =L10++J11-K11 -> 206690
F12: =+F11+C12+D12-E12 -> 982 | I12: =I11++G12-H12 -> 0 | L12: =L11++J12-K12 -> 206690
F13: =+F12+C13+D13-E13 -> 982 | I13: =I12++G13-H13 -> 0 | L13: =L12++J13-K13 -> 206690
F14: =+F13+C14+D14-E14 -> 982 | I14: =I13++G14-H14 -> 0 | L14: =L13++J14-K14 -> 206690
F15: =+F14+C15+D15-E15 -> 982 | I15: =I14++G15-H15 -> 0 | L15: =L14++J15-K15 -> 206690
F16: =+F15+C16+D16-E16 -> 982 | I16: =I15++G16-H16 -> 0 | L16: =L15++J16-K16 -> 206690
F17: =+F16+C17+D17-E17 -> 982 | I17: =I16++G17-H17 -> 0 | L17: =L16++J17-K17 -> 206690
F18: =+F17+C18+D18-E18 -> 982 | I18: =I17++G18-H18 -> 0 | L18: =L17++J18-K18 -> 206690
... F28: =+F27+C28+D28-E28 -> 982 | I28: =I27++G28-H28 -> 0 | L28: =L27++J28-K28 -> 206690
F29: =+F28+C29+D29-E29 -> 982 | H29: 0 | I29: =I28++G29-H29 -> 0 | L29: =L28++J29-K29 -> 206690
F30: =+F29+C30+D30-E30 -> 982 | I30: =I29++G30-H30 -> 0 | L30: =L29++J30-K30 -> 206690
F31: =+F30+C31+D31-E31 -> 982 | I31: =I30++G31-H31 -> 0 | L31: =L30++J31-K31 -> 206690
F32: =+F31+C32+D32-E32 -> 982 | I32: =I31++G32-H32 -> 0 | L32: =L31++J32-K32 -> 206690
F33: =+F32+C33+D33-E33 -> 982 | I33: =I32++G33-H33 -> 0 | L33: =L32++J33-K33 -> 206690
F34: =+F33+C34+D34-E34 -> 982 | I34: =I33++G34-H34 -> 0 | L34: =L33++J34-K34 -> 206690
F35: =+F34+C35+D35-E35 -> 982 | I35: =I34++G35-H35 -> 0 | L35: =L34++J35-K35 -> 206690
F36: =+F35+C36+D36-E36 -> 982 | H36: 0 | I36: =I35++G36-H36 -> 0 | L36: =L35++J36-K36 -> 206690
F37: =+F36+C37+D37-E37 -> 982 | I37: =I36++G37-H37 -> 0 | L37: =L36++J37-K37 -> 206690
F38: =+F37+C38+D38-E38 -> 982 | I38: =I37++G38-H38 -> 0 | L38: =L37++J38-K38 -> 206690
F39: =+F38+C39+D39-E39 -> 982 | I39: =I38++G39-H39 -> 0 | L39: =L38++J39-K39 -> 206690
F40: =+F39+C40+D40-E40 -> 982 | H40: 0 | I40: =I39++G40-H40 -> 0 | L40: =L39++J40-K40 -> 206690
F41: =+F40+C41+D41-E41 -> 982 | I41: =I40++G41-H41 -> 0 | L41: =L40++J41-K41 -> 206690
F42: =+F41+C42+D42-E42 -> 982 | I42: =I41++G42-H42 -> 0 | L42: =L41++J42-K42 -> 206690
F43: =+F42+C43+D43-E43 -> 982 | I43: =I42++G43-H43 -> 0 | L43: =L42++J43-K43 -> 206690
F44: =+F43+C44+D44-E44 -> 982 | I44: =I43++G44-H44 -> 0 | L44: =L43++J44-K44 -> 206690
F45: =+F44+C45+D45-E45 -> 982 | I45: =I44++G45-H45 -> 0 | L45: =L44++J45-K45 -> 206690
F46: =+F45+C46+D46-E46 -> 982 | I46: =I45++G46-H46 -> 0 | L46: =L45++J46-K46 -> 206690
F47: =+F46+C47+D47-E47 -> 982 | H47: 0 | I47: =I46++G47-H47 -> 0 | L47: =L46++J47-K47 -> 206690
F48: =+F47+C48+D48-E48 -> 982 | I48: =I47++G48-H48 -> 0 | L48: =L47++J48-K48 -> 206690
F49: =+F48+C49+D49-E49 -> 982 | I49: =I48++G49-H49 -> 0 | L49: =L48++J49-K49 -> 206690
F50: =+F49+C50+D50-E50 -> 982 | I50: =I49++G50-H50 -> 0 | L50: =L49++J50-K50 -> 206690
F51: =+F50+C51+D51-E51 -> 982 | I51: =I50++G51-H51 -> 0 | L51: =L50++J51-K51 -> 206690
F52: =+F51+C52+D52-E52 -> 982 | I52: =I51++G52-H52 -> 0 | L52: =L51++J52-K52 -> 206690
F53: =+F52+C53+D53-E53 -> 982 | I53: =I52++G53-H53 -> 0 | L53: =L52++J53-K53 -> 206690
F54: =+F53+C54+D54-E54 -> 982 | I54: =I53++G54-H54 -> 0 | L54: =L53++J54-K54 -> 206690
F55: =+F54+C55+D55-E55 -> 982 | I55: =I54++G55-H55 -> 0 | L55: =L54++J55-K55 -> 206690
F56: =+F55+C56+D56-E56 -> 982 | I56: =I55++G56-H56 -> 0 | L56: =L55++J56-K56 -> 206690
F57: =+F56+C57+D57-E57 -> 982 | I57: =I56++G57-H57 -> 0 | L57: =L56++J57-K57 -> 206690
F58: =+F57+C58+D58-E58 -> 982 | I58: =I57++G58-H58 -> 0 | L58: =L57++J58-K58 -> 206690
F59: =+F58+C59+D59-E59 -> 982 | I59: =I58++G59-H59 -> 0 | L59: =L58++J59-K59 -> 206690
... F65: =+F64+C65+D65-E65 -> 982 | I65: =I64++G65-H65 -> 0 | L65: =L64++J65-K65 -> 206690
F66: =+F65+C66+D66-E66 -> 982 | H66: 0 | I66: =I65++G66-H66 -> 0 | L66: =L65++J66-K66 -> 206690
F67: =+F66+C67+D67-E67 -> 982 | I67: =I66++G67-H67 -> 0 | L67: =L66++J67-K67 -> 206690
F68: =+F67+C68+D68-E68 -> 982 | I68: =I67++G68-H68 -> 0 | L68: =L67++J68-K68 -> 206690
F69: =+F68+C69+D69-E69 -> 982 | I69: =I68++G69-H69 -> 0 | L69: =L68++J69-K69 -> 206690
F70: =+F69+C70+D70-E70 -> 982 | I70: =I69++G70-H70 -> 0 | L70: =L69++J70-K70 -> 206690
F71: =+F70+C71+D71-E71 -> 982 | I71: =I70++G71-H71 -> 0 | L71: =L70++J71-K71 -> 206690
F72: =+F71+C72+D72-E72 -> 982 | I72: =I71++G72-H72 -> 0 | L72: =L71++J72-K72 -> 206690
F73: =+F72+C73+D73-E73 -> 982 | I73: =I72++G73-H73 -> 0 | L73: =L72++J73-K73 -> 206690
F74: =+F73+C74+D74-E74 -> 982 | I74: =I73++G74-H74 -> 0 | L74: =L73++J74-K74 -> 206690
F75: =+F74+C75+D75-E75 -> 982 | I75: =I74++G75-H75 -> 0 | L75: =L74++J75-K75 -> 206690
F76: =+F75+C76+D76-E76 -> 982 | I76: =I75++G76-H76 -> 0 | L76: =L75++J76-K76 -> 206690
F77: =+F76+C77+D77-E77 -> 982 | I77: =I76++G77-H77 -> 0 | L77: =L76++J77-K77 -> 206690
F78: =+F77+C78+D78-E78 -> 982 | I78: =I77++G78-H78 -> 0 | L78: =L77++J78-K78 -> 206690
... F96: =+F95+C96+D96-E96 -> 982 | I96: =I95++G96-H96 -> 0 | L96: =L95++J96-K96 -> 206690
F97: =+F96+C97+D97-E97 -> 982 | H97: 0 | I97: =I96++G97-H97 -> 0 | L97: =L96++J97-K97 -> 206690
F98: =+F97+C98+D98-E98 -> 982 | I98: =I97++G98-H98 -> 0 | L98: =L97++J98-K98 -> 206690
F99: =+F98+C99+D99-E99 -> 982 | I99: =I98++G99-H99 -> 0 | L99: =L98++J99-K99 -> 206690
F100: =+F99+C100+D100-E100 -> 982 | I100: =I99++G100-H100 -> 0 | L100: =L99++J100-K100 -> 206690
F101: =+F100+C101+D101-E101 -> 982 | I101: =I100++G101-H101 -> 0 | L101: =L100++J101-K101 -> 206690
F102: =+F101+C102+D102-E102 -> 982 | I102: =I101++G102-H102 -> 0 | L102: =L101++J102-K102 -> 206690
F103: =+F102+C103+D103-E103 -> 982 | I103: =I102++G103-H103 -> 0 | L103: =L102++J103-K103 -> 206690
F104: =+F103+C104+D104-E104 -> 982 | H104: 0 | I104: =I103++G104-H104 -> 0 | L104: =L103++J104-K104 -> 206690
F105: =+F104+C105+D105-E105 -> 982 | I105: =I104++G105-H105 -> 0 | L105: =L104++J105-K105 -> 206690
F106: =+F105+C106+D106-E106 -> 982 | I106: =I105++G106-H106 -> 0 | L106: =L105++J106-K106 -> 206690
F107: =+F106+C107+D107-E107 -> 982 | I107: =I106++G107-H107 -> 0 | L107: =L106++J107-K107 -> 206690
F108: =+F107+C108+D108-E108 -> 982 | I108: =I107++G108-H108 -> 0 | L108: =L107++J108-K108 -> 206690
F109: =+F108+C109+D109-E109 -> 982 | I109: =I108++G109-H109 -> 0 | L109: =L108++J109-K109 -> 206690
F110: =+F109+C110+D110-E110 -> 982 | I110: =I109++G110-H110 -> 0 | L110: =L109++J110-K110 -> 206690
F111: =+F110+C111+D111-E111 -> 982 | I111: =I110++G111-H111 -> 0 | L111: =L110++J111-K111 -> 206690
F112: =+F111+C112+D112-E112 -> 982 | I112: =I111++G112-H112 -> 0 | L112: =L111++J112-K112 -> 206690
F113: =+F112+C113+D113-E113 -> 982 | I113: =I112++G113-H113 -> 0 | L113: =L112++J113-K113 -> 206690
F114: =+F113+C114+D114-E114 -> 982 | I114: =I113++G114-H114 -> 0 | L114: =L113++J114-K114 -> 206690
F115: =+F114+C115+D115-E115 -> 982 | I115: =I114++G115-H115 -> 0 | L115: =L114++J115-K115 -> 206690
F116: =+F115+C116+D116-E116 -> 982 | H116: 0 | I116: =I115++G116-H116 -> 0 | L116: =L115++J116-K116 -> 206690
F117: =+F116+C117+D117-E117 -> 982 | I117: =I116++G117-H117 -> 0 | L117: =L116++J117-K117 -> 206690
F118: =+F117+C118+D118-E118 -> 982 | I118: =I117++G118-H118 -> 0 | L118: =L117++J118-K118 -> 206690
F119: =+F118+C119+D119-E119 -> 982 | I119: =I118++G119-H119 -> 0 | L119: =L118++J119-K119 -> 206690
F120: =+F119+C120+D120-E120 -> 982 | I120: =I119++G120-H120 -> 0 | L120: =L119++J120-K120 -> 206690
F121: =+F120+C121+D121-E121 -> 982 | I121: =I120++G121-H121 -> 0 | L121: =L120++J121-K121 -> 206690
F122: =+F121+C122+D122-E122 -> 982 | I122: =I121++G122-H122 -> 0 | L122: =L121++J122-K122 -> 206690
F123: =+F122+C123+D123-E123 -> 982 | I123: =I122++G123-H123 -> 0 | L123: =L122++J123-K123 -> 206690
F124: =+F123+C124+D124-E124 -> 982 | I124: =I123++G124-H124 -> 0 | L124: =L123++J124-K124 -> 206690
F125: =+F124+C125+D125-E125 -> 982 | I125: =I124++G125-H125 -> 0 | L125: =L124++J125-K125 -> 206690
F126: =+F125+C126+D126-E126 -> 982 | I126: =I125++G126-H126 -> 0 | L126: =L125++J126-K126 -> 206690
F127: =+F126+C127+D127-E127 -> 982 | I127: =I126++G127-H127 -> 0 | L127: =L126++J127-K127 -> 206690
F128: =+F127+C128+D128-E128 -> 982 | I128: =I127++G128-H128 -> 0 | L128: =L127++J128-K128 -> 206690
F129: =+F128+C129+D129-E129 -> 982 | I129: =I128++G129-H129 -> 0 | L129: =L128++J129-K129 -> 206690
F130: =+F129+C130+D130-E130 -> 982 | H130: 0 | I130: =I129++G130-H130 -> 0 | L130: =L129++J130-K130 -> 206690
F131: =+F130+C131+D131-E131 -> 982 | I131: =I130++G131-H131 -> 0 | L131: =L130++J131-K131 -> 206690
...

Sheet 052026
A1: ELECTROCOOL
A2: RAPPORT DE CAISSE | L2: 46143
B3: LIBELLES | D3: USD | H3: EUROS | J3: Francs
C4: ENC CLIENT | D4: ENTREE ($) | E4: SORTIE ($) | F4: SOLDE ($) | G4: ENTREE (Euro) | H4: SORTIE (Euro) | I4: SOLDE (Euro) | J4: ENTREE (Francs) | K4: SORTIE (Francs) | L4: SOLDE (francs)
B5: REPORT | D5: ='042026'!F331 -> 1184 | F5: =D5 -> 1184 | G5: 0 | I5: 0 | J5: 294216 | L5: =J5 -> 294216
A6: 46144 | B6: ALVARO - Evacuation poubelle NDOLO | F6: =+F5+C6+D6-E6 -> 1184 | H6: 0 | I6: =+I5+G6-H6 -> 0 | K6: 10000 | L6: =+L5+J6-K6 -> 284216
A7: 46146 | B7: DIDIER - Carburant TATA DELUXE | E7: 50 | F7: =+F6+C7+D7-E7 -> 1134 | H7: 0 | I7: =+I6+G7-H7 -> 0 | L7: =+L6+J7-K7 -> 284216
A8: 46146 | B8: LEKO - Carburant IST | E8: 40 | F8: =+F7+C8+D8-E8 -> 1094 | I8: =+I7+G8-H8 -> 0 | L8: =+L7+J8-K8 -> 284216
A9: 46146 | B9: CLAUDE - Carburant PICKUP L200 | E9: 50 | F9: =+F8+C9+D9-E9 -> 1044 | I9: =+I8+G9-H9 -> 0 | L9: =+L8+J9-K9 -> 284216
A10: 46146 | B10: PROSPERE - Carburant NISSAN/DG | E10: 70 | F10: =+F9+C10+D10-E10 -> 974 | I10: =+I9+G10-H10 -> 0 | L10: =+L9+J10-K10 -> 284216
A11: 46146 | B11: PROSPERE - Communications | E11: 10 | F11: =+F10+C11+D11-E11 -> 964 | I11: =+I10+G11-H11 -> 0 | L11: =+L10+J11-K11 -> 284216
A12: 46146 | B12: IMMEUBLE EBATA - Acpte Factures | C12: 20000 | F12: =+F11+C12+D12-E12 -> 20964 | I12: =+I11+G12-H12 -> 0 | L12: =+L11+J12-K12 -> 284216
A13: 46146 | B13: BAT CONGO - Acpte travaux encastrement & condensat | E13: 19000 | F13: =+F12+C13+D13-E13 -> 1964 | I13: =+I12+G13-H13 -> 0 | L13: =+L12+J13-K13 -> 284216
A14: 46146 | B14: MIESSI - Legalisation A.G.O. 2026/2025 | E14: 250 | F14: =+F13+C14+D14-E14 -> 1714 | I14: =+I13+G14-H14 -> 0 | L14: =+L13+J14-K14 -> 284216
A15: 46146 | B15: WAPETWA/MAMBINI/LUBAKI - Transport chantiers | F15: =+F14+C15+D15-E15 -> 1714 | I15: =+I14+G15-H15 -> 0 | K15: 15000 | L15: =+L14+J15-K15 -> 269216
A16: 46146 | B16: Emile KABASELE - IRL RESIDENCE IVAN | E16: 300 | F16: =+F15+C16+D16-E16 -> 1414 | I16: =+I15+G16-H16 -> 0 | L16: =+L15+J16-K16 -> 269216
A17: 46146 | B17: COMMUNICATIONS willy, georges, nancy, urbain | E17: 80 | F17: =+F16+C17+D17-E17 -> 1334 | I17: =+I16+G17-H17 -> 0 | L17: =+L16+J17-K17 -> 269216
A18: 46146 | B18: MNAOUER - Communications | E18: 20 | F18: =+F17+C18+D18-E18 -> 1314 | I18: =+I17+G18-H18 -> 0 | L18: =+L17+J18-K18 -> 269216
A19: 46146 | B19: COMMUNICATIONS franck, kusiekita, bangamo, ndona | E19: 40 | F19: =+F18+C19+D19-E19 -> 1274 | I19: =+I18+G19-H19 -> 0 | L19: =+L18+J19-K19 -> 269216
A20: 46146 | B20: BLAISE/DGM - Collation cfr visas volant (VERRVE-BOSSUT) | E20: 100 | F20: =+F19+C20+D20-E20 -> 1174 | I20: =+I19+G20-H20 -> 0 | L20: =+L19+J20-K20 -> 269216
A21: 46146 | B21: PRIMMO - 1 Bouteille azote | E21: 105 | F21: =+F20+C21+D21-E21 -> 1069 | I21: =+I20+G21-H21 -> 0 | L21: =+L20+J21-K21 -> 269216
A22: 46146 | B22: losembe 1 - Reparation fenetre cuisine BUREAU/NDOLO | F22: =+F21+C22+D22-E22 -> 1069 | I22: =+I21+G22-H22 -> 0 | K22: 20000 | L22: =+L21+J22-K22 -> 249216
A23: 46146 | B23: MNOUER - 1 SIM de pointage avec recharge | E23: 10 | F23: =+F22+C23+D23-E23 -> 1059 | I23: =+I22+G23-H23 -> 0 | L23: =+L22+J23-K23 -> 249216
A24: 46146 | B24: SHEHENAJ L.M. - Facture 2026.03/SN/66 | F24: =+F23+C24+D24-E24 -> 1059 | I24: =+I23+G24-H24 -> 0 | J24: 250500 | L24: =+L23+J24-K24 -> 499716
A25: 46147 | B25: EBCDC USD - RETRAIT | D25: 2000 | F25: =+F24+C25+D25-E25 -> 3059 | H25: 0 | I25: =+I24+G25-H25 -> 0 | L25: =+L24+J25-K25 -> 499716
A26: 46147 | B26: IY - APPRO CAISSE | D26: 9000 | F26: =+F25+C26+D26-E26 -> 12059 | I26: =+I25+G26-H26 -> 0 | L26: =+L25+J26-K26 -> 499716
A27: 46147 | B27: MBENKIE - Carburant groupe NDOLO | F27: =+F26+C27+D27-E27 -> 12059 | I27: =+I26+G27-H27 -> 0 | K27: 210000 | L27: =+L26+J27-K27 -> 289716
A28: 46147 | B28: MUPEPE - Solde honoraies comptables EX.2026/2025 | E28: 2500 | F28: =+F27+C28+D28-E28 -> 9559 | I28: =+I27+G28-H28 -> 0 | L28: =+L27+J28-K28 -> 289716
A29: 46147 | B29: MUTORO - Frais RAPPORT CONTRÔLE de 2024 à 2026 | E29: 2400 | F29: =+F28+C29+D29-E29 -> 7159 | I29: =+I28+G29-H29 -> 0 | L29: =+L28+J29-K29 -> 289716
A30: 46147 | B30: MNAOUER - Prestations 04/2026 | E30: 3000 | F30: =+F29+C30+D30-E30 -> 4159 | I30: =+I29+G30-H30 -> 0 | L30: =+L29+J30-K30 -> 289716
A31: 46147 | B31: MOATAZ - Communications 02-03/2026 | E31: 160 | F31: =+F30+C31+D31-E31 -> 3999 | I31: =+I30+G31-H31 -> 0 | L31: =+L30+J31-K31 -> 289716
A32: 46147 | B32: MOATAZ - Divers achats | E32: 299 | F32: =+F31+C32+D32-E32 -> 3700 | I32: =+I31+G32-H32 -> 0 | L32: =+L31+J32-K32 -> 289716
A33: 46147 | B33: KINKOLE - Frais maintenanciers HUB 04/2026 | E33: 500 | F33: =+F32+C33+D33-E33 -> 3200 | I33: =+I32+G33-H33 -> 0 | L33: =+L32+J33-K33 -> 289716
A34: 46147 | B34: ATRIUM - Accessoires divers cfr bon 3670 | E34: 1239 | F34: =+F33+C34+D34-E34 -> 1961 | I34: =+I33+G34-H34 -> 0 | L34: =+L33+J34-K34 -> 289716
A35: 46147 | B35: ATRIUM - 60Lg armaflex 32 | E35: 420 | F35: =+F34+C35+D35-E35 -> 1541 | I35: =+I34+G35-H35 -> 0 | L35: =+L34+J35-K35 -> 289716
A36: 46147 | B36: MAGASIN - 50Toiles iso, 5pqt baguette ag, 5gaz butane GF | E36: 225 | F36: =+F35+C36+D36-E36 -> 1316 | I36: =+I35+G36-H36 -> 0 | L36: =+L35+J36-K36 -> 289716
A37: 46147 | B37: MAGASIN - 10 Capas 50µf, 40&45µf, 35+5µf & 20 de 1,5µf | E37: 310 | F37: =+F36+C37+D37-E37 -> 1006 | I37: =+I36+G37-H37 -> 0 | L37: =+L36+J37-K37 -> 289716
A38: 46147 | B38: MAGASIN - 2 Crts savon liquide | E38: 60 | F38: =+F37+C38+D38-E38 -> 946 | I38: =+I37+G38-H38 -> 0 | L38: =+L37+J38-K38 -> 289716
A39: 46147 | B39: MAGASIN - 1Bouteille freon 410 & 1R22 | E39: 225 | F39: =+F38+C39+D39-E39 -> 721 | I39: =+I38+G39-H39 -> 0 | L39: =+L38+J39-K39 -> 289716
A40: 46147 | B40: MAGASIN - 1 Sac locks pour entretien | E40: 100 | F40: =+F39+C40+D40-E40 -> 621 | I40: =+I39+G40-H40 -> 0 | L40: =+L39+J40-K40 -> 289716
A41: 46147 | B41: CHANGE | E41: 50 | F41: =+F40+C41+D41-E41 -> 571 | I41: =+I40+G41-H41 -> 0 | J41: 112500 | L41: =+L40+J41-K41 -> 402216
A42: 46147 | B42: MAGASIN - 2Rlx sachets bleu pour entretien | F42: =+F41+C42+D42-E42 -> 571 | I42: =+I41+G42-H42 -> 0 | K42: 180000 | L42: =+L41+J42-K42 -> 222216
A43: 46147 | B43: LEKO - Achat bons de sortie caisse | F43: =+F42+C43+D43-E43 -> 571 | I43: =+I42+G43-H43 -> 0 | K43: 35000 | L43: =+L42+J43-K43 -> 187216
A44: 46147 | B44: Complement transport agents RESIDENCE IY & DG | E44: 75 | F44: =+F43+C44+D44-E44 -> 496 | I44: =+I43+G44-H44 -> 0 | L44: =+L43+J44-K44 -> 187216
A45: 46147 | B45: CHICK - Communications | E45: 10 | F45: =+F44+C45+D45-E45 -> 486 | I45: =+I44+G45-H45 -> 0 | L45: =+L44+J45-K45 -> 187216
A46: 46148 | B46: DIDIER - Reparation pneu TATA DELUXE | F46: =+F45+C46+D46-E46 -> 486 | H46: 0 | I46: =+I45+G46-H46 -> 0 | K46: 4000 | L46: =+L45+J46-K46 -> 183216
A47: 46148 | B47: PGHK - Accessoires divers cfr bon 3934 | E47: 300 | F47: =+F46+C47+D47-E47 -> 186 | I47: =+I46+G47-H47 -> 0 | L47: =+L46+J47-K47 -> 183216
A48: 46148 | B48: PRIMMO - 10 Disques c125, 2Gaz propane GF | E48: 45 | F48: =+F47+C48+D48-E48 -> 141 | I48: =+I47+G48-H48 -> 0 | L48: =+L47+J48-K48 -> 183216
A49: 46148 | B49: Osée KAMBU - Course de service A/R PEV | E49: 20 | F49: =+F48+C49+D49-E49 -> 121 | I49: =+I48+G49-H49 -> 0 | L49: =+L48+J49-K49 -> 183216
A50: 46148 | B50: GEORGES - Carburant NISSAN PATROL | E50: 60 | F50: =+F49+C50+D50-E50 -> 61 | I50: =+I49+G50-H50 -> 0 | L50: =+L49+J50-K50 -> 183216
A51: 46148 | B51: LOSEMBE 1 - Transport RESIDENCE IVAN | F51: =+F50+C51+D51-E51 -> 61 | I51: =+I50+G51-H51 -> 0 | K51: 20000 | L51: =+L50+J51-K51 -> 163216
A52: 46149 | B52: TMB USD - RETRAIT | D52: 2000 | F52: =+F51+C52+D52-E52 -> 2061 | H52: 0 | I52: =+I51+G52-H52 -> 0 | L52: =+L51+J52-K52 -> 163216
A53: 46149 | B53: SALAMA RDC - Abonnement mensuelle 05/2026 | E53: 250 | F53: =+F52+C53+D53-E53 -> 1811 | I53: =+I52+G53-H53 -> 0 | L53: =+L52+J53-K53 -> 163216
A54: 46149 | B54: PRIMMO - 5 Crts colle contact | E54: 300 | F54: =+F53+C54+D54-E54 -> 1511 | I54: =+I53+G54-H54 -> 0 | L54: =+L53+J54-K54 -> 163216
A55: 46149 | B55: ATRIUM - 1Rlx tube cu 1/4, 8Lg armaflex 1/4 | E55: 56 | F55: =+F54+C55+D55-E55 -> 1455 | I55: =+I54+G55-H55 -> 0 | L55: =+L54+J55-K55 -> 163216
A56: 46149 | B56: SUCRIERE - 2 Bouteilles freon 410 1 R22 | E56: 395 | F56: =+F55+C56+D56-E56 -> 1060 | I56: =+I55+G56-H56 -> 0 | L56: =+L55+J56-K56 -> 163216
A57: 46149 | B57: IY - APPRO. CAISSE | D57: 1500 | F57: =+F56+C57+D57-E57 -> 2560 | I57: =+I56+G57-H57 -> 0 | L57: =+L56+J57-K57 -> 163216
A58: 46149 | B58: MAMBINI MOMPATA - Avance pension de retraite | E58: 500 | F58: =+F57+C58+D58-E58 -> 2060 | I58: =+I57+G58-H58 -> 0 | L58: =+L57+J58-K58 -> 163216
A59: 46149 | B59: WAPETWA - Avance pension de retraite | E59: 500 | F59: =+F58+C59+D59-E59 -> 1560 | I59: =+I58+G59-H59 -> 0 | L59: =+L58+J59-K59 -> 163216
A60: 46149 | B60: LUBAKI - Avance pension de retraite | E60: 500 | F60: =+F59+C60+D60-E60 -> 1060 | I60: =+I59+G60-H60 -> 0 | L60: =+L59+J60-K60 -> 163216
A61: 46149 | B61: CHANGE | E61: 100 | F61: =+F60+C61+D61-E61 -> 960 | I61: =+I60+G61-H61 -> 0 | J61: 225000 | L61: =+L60+J61-K61 -> 388216
A62: 46149 | B62: URBAIN - Transport Bureau/CITIBANK | F62: =+F61+C62+D62-E62 -> 960 | I62: =+I61+G62-H62 -> 0 | K62: 17000 | L62: =+L61+J62-K62 -> 371216
A63: 46149 | B63: RESIDENCE IVAN - Reparation toiture | E63: 79 | F63: =+F62+C63+D63-E63 -> 881 | I63: =+I62+G63-H63 -> 0 | L63: =+L62+J63-K63 -> 371216
A64: 46149 | B64: LYS HEAVEN - Impression 24 plans A1 | E64: 240 | F64: =+F63+C64+D64-E64 -> 641 | I64: =+I63+G64-H64 -> 0 | L64: =+L63+J64-K64 -> 371216
A65: 46149 | B65: MNAOUER - Frais visa entrée/sortie | E65: 350 | F65: =+F64+C65+D65-E65 -> 291 | I65: =+I64+G65-H65 -> 0 | L65: =+L64+J65-K65 -> 371216
A66: 46149 | B66: DIDIER - 10L huile moteur & 1L huile frein / STOCK | F66: =+F65+C66+D66-E66 -> 291 | I66: =+I65+G66-H66 -> 0 | K66: 203000 | L66: =+L65+J66-K66 -> 168216
A67: 46149 | B67: LOSEMBE 1 - Transport de contrôle de NACELLE | F67: =+F66+C67+D67-E67 -> 291 | I67: =+I66+G67-H67 -> 0 | K67: 10000 | L67: =+L66+J67-K67 -> 158216
A68: 46149 | B68: A ONE CONSTRUCT - Facture 2026.04./SN/75 | C68: 420 | F68: =+F67+C68+D68-E68 -> 711 | I68: =+I67+G68-H68 -> 0 | L68: =+L67+J68-K68 -> 158216
A69: 46149 | B69: IMMEUBLE SERKAS - Facture 2026.04/DA/141 | C69: 210 | F69: =+F68+C69+D69-E69 -> 921 | I69: =+I68+G69-H69 -> 0 | J69: 1000 | L69: =+L68+J69-K69 -> 159216
A70: 46150 | B70: IY - APPRO. CAISSE | D70: 1500 | F70: =+F69+C70+D70-E70 -> 2421 | H70: 0 | I70: =+I69+G70-H70 -> 0 | L70: =+L69+J70-K70 -> 159216
A71: 46150 | B71: MBENKIE - Carburant JAC/CONTAINER | E71: 50 | F71: =+F70+C71+D71-E71 -> 2371 | I71: =+I70+G71-H71 -> 0 | L71: =+L70+J71-K71 -> 159216
A72: 46150 | B72: CHANGE | E72: 50 | F72: =+F71+C72+D72-E72 -> 2321 | I72: =+I71+G72-H72 -> 0 | J72: 112500 | L72: =+L71+J72-K72 -> 271716
A73: 46150 | B73: CHICK - Carburant PRADO/DG | E73: 70 | F73: =+F72+C73+D73-E73 -> 2251 | I73: =+I72+G73-H73 -> 0 | K73: 5000 | L73: =+L72+J73-K73 -> 266716
A74: 46150 | B74: HANS KISOLA - Avance frais de mission LUSHI (72jrs) | E74: 500 | F74: =+F73+C74+D74-E74 -> 1751 | I74: =+I73+G74-H74 -> 0 | L74: =+L73+J74-K74 -> 266716
A75: 46150 | B75: LEKO - Carburant IST | E75: 40 | F75: =+F74+C75+D75-E75 -> 1711 | I75: =+I74+G75-H75 -> 0 | L75: =+L74+J75-K75 -> 266716
A76: 46150 | B76: LOSEMBE 1 - 1G4 de 63A / Inverteur STS-ELC | E76: 95 | F76: =+F75+C76+D76-E76 -> 1616 | I76: =+I75+G76-H76 -> 0 | L76: =+L75+J76-K76 -> 266716
A77: 46150 | B77: PRIMMO - 2 Meches carottes HILTI 63 | E77: 380 | F77: =+F76+C77+D77-E77 -> 1236 | I77: =+I76+G77-H77 -> 0 | L77: =+L76+J77-K77 -> 266716
A78: 46150 | B78: SUCRIERE - Disjoncteurs GV2 9à14A & 6à10A | E78: 350 | F78: =+F77+C78+D78-E78 -> 886 | I78: =+I77+G78-H78 -> 0 | L78: =+L77+J78-K78 -> 266716
A79: 46150 | B79: SUCRIERE - Accessoires divers / Fabrication supports | E79: 230 | F79: =+F78+C79+D79-E79 -> 656 | I79: =+I78+G79-H79 -> 0 | L79: =+L78+J79-K79 -> 266716
A80: 46150 | B80: PRIMMO - Papiers colliers resiliant, plastics, collant GF | E80: 240 | F80: =+F79+C80+D80-E80 -> 416 | I80: =+I79+G80-H80 -> 0 | L80: =+L79+J80-K80 -> 266716
A81: 46150 | B81: SUCRIERE - Accessoires montage cfr bon 3689 | E81: 291 | F81: =+F80+C81+D81-E81 -> 125 | I81: =+I80+G81-H81 -> 0 | L81: =+L80+J81-K81 -> 266716
A82: 46150 | B82: ALVARO - Evacuation poubelle NDOLO | F82: =+F81+C82+D82-E82 -> 125 | I82: =+I81+G82-H82 -> 0 | K82: 10000 | L82: =+L81+J82-K82 -> 256716
A83: 46151 | B83: COMMUNAUTE HELLENIQUE - Fact.2026.04/DA/142 | C83: 146 | F83: =+F82+C83+D83-E83 -> 271 | H83: 0 | I83: =+I82+G83-H83 -> 0 | J83: 400 | L83: =+L82+J83-K83 -> 257116
A84: 46151 | B84: IMMEUBLE TATELIE - Fact.2026.02/SN/42 | C84: 174 | F84: =+F83+C84+D84-E84 -> 445 | I84: =+I83+G84-H84 -> 0 | J84: 10000 | L84: =+L83+J84-K84 -> 267116
A85: 46153 | B85: LOSEMBE 1 - Carburant groupe NDOLO | E85: 100 | F85: =+F84+C85+D85-E85 -> 345 | H85: 0 | I85: =+I84+G85-H85 -> 0 | L85: =+L84+J85-K85 -> 267116
A86: 46153 | B86: DIDIER - Carburant TATA DELUXE | E86: 50 | F86: =+F85+C86+D86-E86 -> 295 | I86: =+I85+G86-H86 -> 0 | L86: =+L85+J86-K86 -> 267116
A87: 46153 | B87: PROSPERE LIHOZA - Carburant NISSAN/DG | E87: 70 | F87: =+F86+C87+D87-E87 -> 225 | I87: =+I86+G87-H87 -> 0 | L87: =+L86+J87-K87 -> 267116
A88: 46153 | B88: PROSPERE LIHOZA - Communications | E88: 10 | F88: =+F87+C88+D88-E88 -> 215 | I88: =+I87+G88-H88 -> 0 | L88: =+L87+J88-K88 -> 267116
A89: 46153 | B89: LOSEMBE 1 - Transport RESIDENCE EBATA | F89: =+F88+C89+D89-E89 -> 215 | I89: =+I88+G89-H89 -> 0 | K89: 10000 | L89: =+L88+J89-K89 -> 257116
A90: 46153 | B90: EBCDC USD - RETRAIT | D90: 5000 | F90: =+F89+C90+D90-E90 -> 5215 | I90: =+I89+G90-H90 -> 0 | L90: =+L89+J90-K90 -> 257116
A91: 46153 | B91: CHANGE | E91: 4700 | F91: =+F90+C91+D91-E91 -> 515 | I91: =+I90+G91-H91 -> 0 | J91: 10716000 | L91: =+L90+J91-K91 -> 10973116
A92: 46153 | B92: ELECTROCOOL - Quinzaine 05/2026 | F92: =+F91+C92+D92-E92 -> 515 | I92: =+I91+G92-H92 -> 0 | K92: 2720000 | L92: =+L91+J92-K92 -> 8253116
A93: 46153 | B93: EGSC - Quinzaine 05/2026 | F93: =+F92+C93+D93-E93 -> 515 | I93: =+I92+G93-H93 -> 0 | K93: 2440000 | L93: =+L92+J93-K93 -> 5813116
A94: 46153 | B94: TEMPORAIRES 05/2026 | F94: =+F93+C94+D94-E94 -> 515 | I94: =+I93+G94-H94 -> 0 | K94: 5015000 | L94: =+L93+J94-K94 -> 798116
A95: 46153 | B95: TEMPLE - 1 Bouteille azote, 1 acetylene, 1 oxygene | E95: 302 | F95: =+F94+C95+D95-E95 -> 213 | I95: =+I94+G95-H95 -> 0 | L95: =+L94+J95-K95 -> 798116
A96: 46153 | B96: COMMUNICATIONS willy, nancy, urbain, georges | E96: 80 | F96: =+F95+C96+D96-E96 -> 133 | I96: =+I95+G96-H96 -> 0 | L96: =+L95+J96-K96 -> 798116
A97: 46153 | B97: MNAOUER - Communications | E97: 20 | F97: =+F96+C97+D97-E97 -> 113 | I97: =+I96+G97-H97 -> 0 | L97: =+L96+J97-K97 -> 798116
A98: 46153 | B98: COMMUNICATIONS franck, kusiekita, bangamo & ndona | E98: 40 | F98: =+F97+C98+D98-E98 -> 73 | I98: =+I97+G98-H98 -> 0 | L98: =+L97+J98-K98 -> 798116
A99: 46153 | B99: ATRIUM - 4 Journaliers du 30/04 au | F99: =+F98+C99+D99-E99 -> 73 | I99: =+I98+G99-H99 -> 0 | K99: 640000 | L99: =+L98+J99-K99 -> 158116
A100: 46153 | B100: IMMEUBLE DELPHIN - Facture 2026.04/DA/140 | C100: 243 | F100: =+F99+C100+D100-E100 -> 316 | I100: =+I99+G100-H100 -> 0 | L100: =+L99+J100-K100 -> 158116
...

Sheet 042026
A1: ELECTROCOOL
A2: RAPPORT DE CAISSE | L2: 46113
B3: LIBELLES | D3: USD | H3: EUROS | J3: Francs
C4: ENC CLIENT | D4: ENTREE ($) | E4: SORTIE ($) | F4: SOLDE ($) | G4: ENTREE (Euro) | H4: SORTIE (Euro) | I4: SOLDE (Euro) | J4: ENTREE (Francs) | K4: SORTIE (Francs) | L4: SOLDE (francs)
B5: REPORT | D5: =+'032026'!F268 -> 9019 | F5: =D5 -> 9019 | G5: 0 | I5: 0 | J5: ='032026'!L268 -> 1081313 | L5: =J5 -> 1081313
A6: 46114 | B6: MBENKIE - Carburant groupe NDOLO | E6: 100 | F6: =+F5+C6+D6-E6 -> 8919 | H6: 0 | I6: =+I5+G6-H6 -> 0 | L6: =+L5+J6-K6 -> 1081313
A7: 46114 | B7: LEKO - Carburant IST | E7: 40 | F7: =+F6+C7+D7-E7 -> 8879 | I7: =+I6+G7-H7 -> 0 | L7: =+L6+J7-K7 -> 1081313
A8: 46114 | B8: KWAMI - Travaux local machine COMIMMO & acpte M.O. | E8: 824 | F8: =+F7+C8+D8-E8 -> 8055 | I8: =+I7+G8-H8 -> 0 | L8: =+L7+J8-K8 -> 1081313
A9: 46114 | B9: MAIEL - Prestations SUCRIERE 03/2026 | E9: 2250 | F9: =+F8+C9+D9-E9 -> 5805 | I9: =+I8+G9-H9 -> 0 | L9: =+L8+J9-K9 -> 1081313
A10: 46114 | B10: IY - Cotisation Famille YSEBOOT/Mariage NANCY | E10: 500 | F10: =+F9+C10+D10-E10 -> 5305 | I10: =+I9+G10-H10 -> 0 | L10: =+L9+J10-K10 -> 1081313
A11: 46114 | B11: COTISATION ELC / Mariage NANCY | E11: 100 | F11: =+F10+C11+D11-E11 -> 5205 | I11: =+I10+G11-H11 -> 0 | L11: =+L10+J11-K11 -> 1081313
A12: 46114 | B12: CHARLES - Reparation electrique MITHUBISHI&PATROL | E12: 50 | F12: =+F11+C12+D12-E12 -> 5155 | I12: =+I11+G12-H12 -> 0 | L12: =+L11+J12-K12 -> 1081313
A13: 46114 | B13: PGHK - 1 Tenue complet, chaussure+decoration NDAKUZU | E13: 70 | F13: =+F12+C13+D13-E13 -> 5085 | I13: =+I12+G13-H13 -> 0 | L13: =+L12+J13-K13 -> 1081313
A14: 46114 | B14: PRIMMO - 2 Bouteilles azote, 1 acetylene, 1 oxygene | E14: 406 | F14: =+F13+C14+D14-E14 -> 4679 | I14: =+I13+G14-H14 -> 0 | L14: =+L13+J14-K14 -> 1081313
A15: 46114 | B15: PRIMMO - 100m cable 4x2,5mm² & 10 lames scie | E15: 265 | F15: =+F14+C15+D15-E15 -> 4414 | I15: =+I14+G15-H15 -> 0 | L15: =+L14+J15-K15 -> 1081313
A16: 46114 | B16: MANGA FLORE - Desinsectisation jardin 12/2025 | E16: 134 | F16: =+F15+C16+D16-E16 -> 4280 | I16: =+I15+G16-H16 -> 0 | L16: =+L15+J16-K16 -> 1081313
A17: 46114 | B17: MAMBA SECURITY - Facture NDOLO&RESIDENCE 01/2026 | E17: 750 | F17: =+F16+C17+D17-E17 -> 3530 | I17: =+I16+G17-H17 -> 0 | L17: =+L16+J17-K17 -> 1081313
A18: 46114 | B18: KIABA JEAN - Prêt société | E18: 500 | F18: =+F17+C18+D18-E18 -> 3030 | I18: =+I17+G18-H18 -> 0 | L18: =+L17+J18-K18 -> 1081313
... A20: 46114 | B20: MUPEPE - Divers ONEC | E20: 2000 | F20: =+F19+C20+D20-E20 -> 780 | I20: =+I19+G20-H20 -> 0 | L20: =+L19+J20-K20 -> 1081313
A21: 46114 | B21: GEORGES - RETOUR CAISSE | F21: =+F20+C21+D21-E21 -> 780 | I21: =+I20+G21-H21 -> 0 | J21: 22500 | L21: =+L20+J21-K21 -> 1103813
A22: 46114 | B22: DIDIER - 1L huile frein, 2L huile hydrau, 10L moteur STOCK | F22: =+F21+C22+D22-E22 -> 780 | I22: =+I21+G22-H22 -> 0 | K22: 203500 | L22: =+L21+J22-K22 -> 900313
F23: =+F22+C23+D23-E23 -> 780 | I23: =I22++G23-H23 -> 0 | L23: =L22++J23-K23 -> 900313
A24: 46115 | B24: LOSEMBE1&DIDIER - Transport PRIMMO | F24: =+F23+C24+D24-E24 -> 780 | H24: 0 | I24: =+I23+G24-H24 -> 0 | K24: 20000 | L24: =+L23+J24-K24 -> 880313
A25: 46115 | B25: Serge KABULO - TRFT MPESA/ Prestations 03/2026 | E25: 250 | F25: =+F24+C25+D25-E25 -> 530 | I25: =+I24+G25-H25 -> 0 | L25: =+L24+J25-K25 -> 880313
A26: 46115 | B26: UTEXAFRICA - 30Disques c230, 1bte antirouille, thinner--- | E26: 45 | F26: =+F25+C26+D26-E26 -> 485 | I26: =+I25+G26-H26 -> 0 | L26: =+L25+J26-K26 -> 880313
A27: 46115 | B27: PGHK - 1crt colle contact, 100chevilles+vis--- | E27: 135 | F27: =+F26+C27+D27-E27 -> 350 | I27: =+I26+G27-H27 -> 0 | L27: =+L26+J27-K27 -> 880313
A28: 46115 | B28: ETS NEW CEPRONAC - Passage immondices RESIDENCE IY | E28: 125 | F28: =+F27+C28+D28-E28 -> 225 | I28: =+I27+G28-H28 -> 0 | L28: =+L27+J28-K28 -> 880313
A29: 46115 | B29: ALVARO - Evacuation poubelle NDOLO | F29: =+F28+C29+D29-E29 -> 225 | I29: =+I28+G29-H29 -> 0 | K29: 10000 | L29: =+L28+J29-K29 -> 870313
A30: 46115 | B30: LYS HEAVEN - 1Rlx flexible 50 | E30: 125 | F30: =+F29+C30+D30-E30 -> 100 | I30: =+I29+G30-H30 -> 0 | L30: =+L29+J30-K30 -> 870313
A31: 46115 | B31: UTEX/SILIKIN - 1 Bte colle tangit 500gr | E31: 15 | F31: =+F30+C31+D31-E31 -> 85 | I31: =+I30+G31-H31 -> 0 | L31: =+L30+J31-K31 -> 870313
F32: =+F31+C32+D32-E32 -> 85 | I32: =I31++G32-H32 -> 0 | L32: =L31++J32-K32 -> 870313
A33: 46119 | B33: TMB USD - RETRAIT | D33: 1500 | F33: =+F32+C33+D33-E33 -> 1585 | H33: 0 | I33: =+I32+G33-H33 -> 0 | L33: =+L32+J33-K33 -> 870313
A34: 46119 | B34: IMMEUBLE MARIE YVETTE - Redevance 02/2026 | C34: 183 | F34: =+F33+C34+D34-E34 -> 1768 | I34: =+I33+G34-H34 -> 0 | L34: =+L33+J34-K34 -> 870313
A35: 46119 | B35: LOSEMBE 1 - Transport / Reparation flexible NACELLE | F35: =+F34+C35+D35-E35 -> 1768 | I35: =+I34+G35-H35 -> 0 | K35: 10000 | L35: =+L34+J35-K35 -> 860313
A36: 46119 | B36: IY - Appro caisse | D36: 100 | F36: =+F35+C36+D36-E36 -> 1868 | I36: =+I35+G36-H36 -> 0 | L36: =+L35+J36-K36 -> 860313
A37: 46119 | B37: DG - Appro caisse | D37: 100 | F37: =+F36+C37+D37-E37 -> 1968 | I37: =+I36+G37-H37 -> 0 | L37: =+L36+J37-K37 -> 860313
A38: 46119 | B38: JETONS DE PRESENCE CDT/WILLY | E38: 200 | F38: =+F37+C38+D38-E38 -> 1768 | I38: =+I37+G38-H38 -> 0 | L38: =+L37+J38-K38 -> 860313
A39: 46119 | B39: DIDIER - Course de service | F39: =+F38+C39+D39-E39 -> 1768 | I39: =+I38+G39-H39 -> 0 | K39: 10000 | L39: =+L38+J39-K39 -> 850313
A40: 46119 | B40: DIDIER - Carburant TATA DELUXE | E40: 50 | F40: =+F39+C40+D40-E40 -> 1718 | I40: =+I39+G40-H40 -> 0 | L40: =+L39+J40-K40 -> 850313
A41: 46119 | B41: MALEWU Pirins - Prestations 13 jours | F41: =+F40+C41+D41-E41 -> 1718 | I41: =+I40+G41-H41 -> 0 | K41: 372604 | L41: =+L40+J41-K41 -> 477709
A42: 46119 | B42: UK Embassy - HS mardi au jeudi 19/03/2026 | F42: =+F41+C42+D42-E42 -> 1718 | I42: =+I41+G42-H42 -> 0 | K42: 16500 | L42: =+L41+J42-K42 -> 461209
F43: =+F42+C43+D43-E43 -> 1718 | I43: =I42++G43-H43 -> 0 | L43: =L42++J43-K43 -> 461209
A44: 46120 | B44: LEKO - Carburant IST | E44: 40 | F44: =+F43+C44+D44-E44 -> 1678 | H44: 0 | I44: =+I43+G44-H44 -> 0 | L44: =+L43+J44-K44 -> 461209
A45: 46120 | B45: Prospere LIHOZA - Carburant NISSAN PATROL | E45: 70 | F45: =+F44+C45+D45-E45 -> 1608 | I45: =+I44+G45-H45 -> 0 | L45: =+L44+J45-K45 -> 461209
A46: 46120 | B46: Prospere LIHOZA - COMMUNICATIONS | E46: 10 | F46: =+F45+C46+D46-E46 -> 1598 | I46: =+I45+G46-H46 -> 0 | L46: =+L45+J46-K46 -> 461209
A47: 46120 | B47: LOSEMBE 1 - Carburant groupe NDOLO | E47: 100 | F47: =+F46+C47+D47-E47 -> 1498 | I47: =+I46+G47-H47 -> 0 | L47: =+L46+J47-K47 -> 461209
A48: 46120 | B48: CLAUDE - Carburant PICKUP L200 | E48: 50 | F48: =+F47+C48+D48-E48 -> 1448 | I48: =+I47+G48-H48 -> 0 | L48: =+L47+J48-K48 -> 461209
A49: 46120 | B49: CHICK - Carburant PRADO/DG | E49: 70 | F49: =+F48+C49+D49-E49 -> 1378 | I49: =+I48+G49-H49 -> 0 | L49: =+L48+J49-K49 -> 461209
A50: 46120 | B50: CHICK - Achat eau DG&BUREAU | E50: 20 | F50: =+F49+C50+D50-E50 -> 1358 | I50: =+I49+G50-H50 -> 0 | L50: =+L49+J50-K50 -> 461209
A51: 46120 | B51: MALEWU Pirens - HS /MONKOLE samedi 04/04/2026 | F51: =+F50+C51+D51-E51 -> 1358 | I51: =+I50+G51-H51 -> 0 | K51: 25704 | L51: =+L50+J51-K51 -> 435505
A52: 46120 | B52: UTEXAFRICA - 10Lg cornieres 30; 10paires pomelle 16 | E52: 290 | F52: =+F51+C52+D52-E52 -> 1068 | I52: =+I51+G52-H52 -> 0 | L52: =+L51+J52-K52 -> 435505
A53: 46120 | B53: LYS HEAVEN - 1Rlx flexible 50 | E53: 125 | F53: =+F52+C53+D53-E53 -> 943 | I53: =+I52+G53-H53 -> 0 | L53: =+L52+J53-K53 -> 435505
A54: 46120 | B54: PRIMMO - 3Gaz propane & 20disques c125 | E54: 71 | F54: =+F53+C54+D54-E54 -> 872 | I54: =+I53+G54-H54 -> 0 | L54: =+L53+J54-K54 -> 435505
A55: 46120 | B55: COMMUNICATIONS willy, nancy, georges, urbain | E55: 80 | F55: =+F54+C55+D55-E55 -> 792 | I55: =+I54+G55-H55 -> 0 | L55: =+L54+J55-K55 -> 435505
A56: 46120 | B56: MNAOUER - Communications | E56: 20 | F56: =+F55+C56+D56-E56 -> 772 | I56: =+I55+G56-H56 -> 0 | L56: =+L55+J56-K56 -> 435505
A57: 46120 | B57: COMMUNICATIONS franck, kusiekita, bangamo, ndona | E57: 40 | F57: =+F56+C57+D57-E57 -> 732 | I57: =+I56+G57-H57 -> 0 | L57: =+L56+J57-K57 -> 435505
A58: 46120 | B58: A ONE CONSTRUCTION - Facture 2026.03/SN/48 | C58: 420 | F58: =+F57+C58+D58-E58 -> 1152 | I58: =+I57+G58-H58 -> 0 | L58: =+L57+J58-K58 -> 435505
A59: 46120 | B59: Mr THOMAS - Facture 2026.03/SN/52 | F59: =+F58+C59+D59-E59 -> 1152 | I59: =+I58+G59-H59 -> 0 | J59: 322000 | L59: =+L58+J59-K59 -> 757505
A60: 46120 | B60: DIVERS | E60: 100 | F60: =+F59+C60+D60-E60 -> 1052 | H60: 0 | I60: =I59++G60-H60 -> 0 | L60: =L59++J60-K60 -> 757505
A61: 46121 | B61: GEORGES - Carburant NISSAN PATROL | E61: 60 | F61: =+F60+C61+D61-E61 -> 992 | H61: 0 | I61: =+I60+G61-H61 -> 0 | L61: =+L60+J61-K61 -> 757505
A62: 46121 | B62: MBENKIE - Carburant jac:container | E62: 50 | F62: =+F61+C62+D62-E62 -> 942 | I62: =+I61+G62-H62 -> 0 | L62: =+L61+J62-K62 -> 757505
A63: 46121 | B63: LOSEMBE 1 - Carburant groupe NDOLO | E63: 100 | F63: =+F62+C63+D63-E63 -> 842 | I63: =+I62+G63-H63 -> 0 | L63: =+L62+J63-K63 -> 757505
A64: 46121 | B64: LYS HEAVEN - Impression 1 plan | E64: 15 | F64: =+F63+C64+D64-E64 -> 827 | I64: =+I63+G64-H64 -> 0 | L64: =+L63+J64-K64 -> 757505
A65: 46121 | B65: LEKO - Frais parking aero NDOLO | E65: 10 | F65: =+F64+C65+D65-E65 -> 817 | I65: =+I64+G65-H65 -> 0 | L65: =+L64+J65-K65 -> 757505
A66: 46121 | B66: PRIMMO&MAGASIN - 2 Pinceaux | E66: 37 | F66: =+F65+C66+D66-E66 -> 780 | I66: =+I65+G66-H66 -> 0 | L66: =+L65+J66-K66 -> 757505
A67: 46121 | B67: PRIMMO - 5Pqts nylon colson GF | E67: 50 | F67: =+F66+C67+D67-E67 -> 730 | I67: =+I66+G67-H67 -> 0 | L67: =+L66+J67-K67 -> 757505
A68: 46121 | B68: DIDIER - Filtres, plaquettes, bandes ARR, 10l hydrau | E68: 345 | F68: =+F67+C68+D68-E68 -> 385 | I68: =+I67+G68-H68 -> 0 | L68: =+L67+J68-K68 -> 757505
A69: 46121 | B69: ATRIUM - HS lundi au samedi 28/03/2026 | F69: =+F68+C69+D69-E69 -> 385 | I69: =+I68+G69-H69 -> 0 | K69: 469500 | L69: =+L68+J69-K69 -> 288005
A70: 46121 | B70: PGHK - 4 Petits galons degraissant CTA/SALON | F70: =+F69+C70+D70-E70 -> 385 | I70: =+I69+G70-H70 -> 0 | K70: 72000 | L70: =+L69+J70-K70 -> 216005
A71: 46121 | B71: MAKIESE PIERRE - Divers 03/2026 | F71: =+F70+C71+D71-E71 -> 385 | I71: =+I70+G71-H71 -> 0 | K71: 75000 | L71: =+L70+J71-K71 -> 141005
A72: 46121 | B72: POSPERE LIHOZA - Divers 03/2026 | F72: =+F71+C72+D72-E72 -> 385 | I72: =+I71+G72-H72 -> 0 | K72: 50000 | L72: =+L71+J72-K72 -> 91005
F73: =+F72+C73+D73-E73 -> 385 | I73: =I72++G73-H73 -> 0 | L73: =L72++J73-K73 -> 91005
A74: 46122 | B74: CHICK - Liquide de refroissement PRADO | E74: 20 | F74: =+F73+C74+D74-E74 -> 365 | H74: 0 | I74: =+I73+G74-H74 -> 0 | L74: =+L73+J74-K74 -> 91005
A75: 46122 | B75: LOSEMBE 1 - Transport RESIDENCE DG | F75: =+F74+C75+D75-E75 -> 365 | I75: =+I74+G75-H75 -> 0 | K75: 10000 | L75: =+L74+J75-K75 -> 81005
A76: 46122 | B76: KWAMI - Acpte M.O. Travaux COIMIMMO | E76: 50 | F76: =+F75+C76+D76-E76 -> 315 | I76: =+I75+G76-H76 -> 0 | L76: =+L75+J76-K76 -> 81005
A77: 46122 | B77: ATRIUM - 5Pqts colliers colson MF | E77: 50 | F77: =+F76+C77+D77-E77 -> 265 | I77: =+I76+G77-H77 -> 0 | L77: =+L76+J77-K77 -> 81005
A78: 46122 | B78: ALVARO - Evacuation poubelle NDOLO | F78: =+F77+C78+D78-E78 -> 265 | I78: =+I77+G78-H78 -> 0 | K78: 10000 | L78: =+L77+J78-K78 -> 71005
A79: 46122 | B79: NTUMBA - Impression QRCODE / SUCRIERE | F79: =+F78+C79+D79-E79 -> 265 | I79: =+I78+G79-H79 -> 0 | K79: 15000 | L79: =+L78+J79-K79 -> 56005
A80: 46122 | B80: EBCDC USD - RETRAIT | D80: 1800 | F80: =+F79+C80+D80-E80 -> 2065 | I80: =+I79+G80-H80 -> 0 | L80: =+L79+J80-K80 -> 56005
A81: 46122 | B81: CHANGE | E81: 1800 | F81: =+F80+C81+D81-E81 -> 265 | I81: =+I80+G81-H81 -> 0 | J81: 4158000 | L81: =+L80+J81-K81 -> 4214005
A82: 46122 | B82: EGSC - CNSS 03/2026 | F82: =+F81+C82+D82-E82 -> 265 | I82: =+I81+G82-H82 -> 0 | K82: 2248499.7 | L82: =+L81+J82-K82 -> 1965505.3
A83: 46122 | B83: EGSC - IPR 03/2026 | F83: =+F82+C83+D83-E83 -> 265 | I83: =+I82+G83-H83 -> 0 | K83: 1780062 | L83: =+L82+J83-K83 -> 185443.3
F84: =+F83+C84+D84-E84 -> 265 | I84: =I83++G84-H84 -> 0 | L84: =L83++J84-K84 -> 185443.3
A85: 46123 | B85: CDT - Transport AGO / CDT-Agents | E85: 50 | F85: =+F84+C85+D85-E85 -> 215 | H85: 0 | I85: =+I84+G85-H85 -> 0 | L85: =+L84+J85-K85 -> 185443.3
A86: 46123 | B86: LOSEMBE 1 - Transport PRIMMO | F86: =+F85+C86+D86-E86 -> 215 | I86: =+I85+G86-H86 -> 0 | K86: 10000 | L86: =+L85+J86-K86 -> 175443.3
F87: =+F86+C87+D87-E87 -> 215 | I87: =I86++G87-H87 -> 0 | L87: =L86++J87-K87 -> 175443.3
A88: 46125 | B88: EBCDC USD - RETRAIT | D88: 5000 | F88: =+F87+C88+D88-E88 -> 5215 | H88: 0 | I88: =+I87+G88-H88 -> 0 | L88: =+L87+J88-K88 -> 175443.3
A89: 46125 | B89: Prospere LIHOZA - Achat telephone de service | E89: 100 | F89: =+F88+C89+D89-E89 -> 5115 | I89: =+I88+G89-H89 -> 0 | L89: =+L88+J89-K89 -> 175443.3
A90: 46125 | B90: FRANCK - Abonnement ORANGE du 13/04 au 12/05/2026 | E90: 200 | F90: =+F89+C90+D90-E90 -> 4915 | I90: =+I89+G90-H90 -> 0 | L90: =+L89+J90-K90 -> 175443.3
A91: 46125 | B91: LEKO - Carburant IST | E91: 40 | F91: =+F90+C91+D91-E91 -> 4875 | I91: =+I90+G91-H91 -> 0 | L91: =+L90+J91-K91 -> 175443.3
A92: 46125 | B92: CHANGE | E92: 4300 | F92: =+F91+C92+D92-E92 -> 575 | I92: =+I91+G92-H92 -> 0 | J92: 9890000 | L92: =+L91+J92-K92 -> 10065443
A93: 46125 | B93: ELECTROCOOL - Quinzaine 04/2026 | F93: =+F92+C93+D93-E93 -> 575 | I93: =+I92+G93-H93 -> 0 | K93: 2720000 | L93: =+L92+J93-K93 -> 7345443.3
A94: 46125 | B94: EGSC - Quinzaine 04/2026 | F94: =+F93+C94+D94-E94 -> 575 | I94: =+I93+G94-H94 -> 0 | K94: 2090000 | L94: =+L93+J94-K94 -> 5255443.3
A95: 46125 | B95: TEMPORAIRES - Quinzaine 04/2026 | F95: =+F94+C95+D95-E95 -> 575 | I95: =+I94+G95-H95 -> 0 | K95: 5015000 | L95: =+L94+J95-K95 -> 240443.3
A96: 46125 | B96: immeuble SERKAS - Facture 2026.03/DA/123 | C96: 210 | F96: =+F95+C96+D96-E96 -> 785 | I96: =+I95+G96-H96 -> 0 | J96: 1000 | L96: =+L95+J96-K96 -> 241443.3
A97: 46125 | B97: RESIDENCE KAWELE - Facture AVRIL 2026 | C97: 250 | F97: =+F96+C97+D97-E97 -> 1035 | I97: =+I96+G97-H97 -> 0 | L97: =+L96+J97-K97 -> 241443.3
F98: =+F97+C98+D98-E98 -> 1035 | I98: =I97++G98-H98 -> 0 | L98: =L97++J98-K98 -> 241443.3
A99: 46126 | B99: RS HOLDING - VENTE 2 Bouteilles nettoyage INOX | C99: 60 | F99: =+F98+C99+D99-E99 -> 1095 | H99: 0 | I99: =+I98+G99-H99 -> 0 | L99: =+L98+J99-K99 -> 241443.3
A100: 46126 | B100: MBENKIE - Carburant groupe NDOLO | E100: 100 | F100: =+F99+C100+D100-E100 -> 995 | I100: =+I99+G100-H100 -> 0 | L100: =+L99+J100-K100 -> 241443.3
A101: 46126 | B101: Prospere LIHOZA - Carburant NISSAN PATROL | E101: 70 | F101: =+F100+C101+D101-E101 -> 925 | I101: =+I100+G101-H101 -> 0 | L101: =+L100+J101-K101 -> 241443.3
...

Sheet 032026
A1: ELECTROCOOL
A2: RAPPORT DE CAISSE | L2: 46082
B3: LIBELLES | D3: USD | H3: EUROS | J3: Francs
C4: ENC CLIENT | D4: ENTREE ($) | E4: SORTIE ($) | F4: SOLDE ($) | G4: ENTREE (Euro) | H4: SORTIE (Euro) | I4: SOLDE (Euro) | J4: ENTREE (Francs) | K4: SORTIE (Francs) | L4: SOLDE (francs)
B5: REPORT | D5: 47 | F5: =D5 -> 47 | G5: 0 | I5: 0 | J5: 87187 | L5: =J5 -> 87187
A6: 46083 | B6: RAWBANK USD - RETRAIT | D6: 2000 | F6: =+F5+C6+D6-E6 -> 2047 | H6: 0 | I6: =+I5+G6-H6 -> 0 | L6: =+L5+J6-K6 -> 87187
A7: 46083 | B7: MUMBIMBI - Reparation pneu NISSAN PATROL | F7: =+F6+C7+D7-E7 -> 2047 | I7: =+I6+G7-H7 -> 0 | K7: 20000 | L7: =+L6+J7-K7 -> 67187
A8: 46083 | B8: MUMBIMBI - Reparation pneu JAC/CONTAINER | F8: =+F7+C8+D8-E8 -> 2047 | I8: =+I7+G8-H8 -> 0 | K8: 10000 | L8: =+L7+J8-K8 -> 57187
A9: 46083 | B9: RESIDENCE IVAN - M.O. Reparation toiture | E9: 50 | F9: =+F8+C9+D9-E9 -> 1997 | I9: =+I8+G9-H9 -> 0 | L9: =+L8+J9-K9 -> 57187
A10: 46083 | B10: COMMUNICATIONS willy, georges, urbain, nancy | E10: 80 | F10: =+F9+C10+D10-E10 -> 1917 | I10: =+I9+G10-H10 -> 0 | L10: =+L9+J10-K10 -> 57187
A11: 46083 | B11: MNAOUER - Communications | E11: 20 | F11: =+F10+C11+D11-E11 -> 1897 | I11: =+I10+G11-H11 -> 0 | L11: =+L10+J11-K11 -> 57187
A12: 46083 | B12: COMMUNICATIONS franck, kusiekita, bangamo, ndona | E12: 40 | F12: =+F11+C12+D12-E12 -> 1857 | I12: =+I11+G12-H12 -> 0 | L12: =+L11+J12-K12 -> 57187
A13: 46083 | B13: Immeuble IMANI - Facture 2026.01/DA/58 | C13: 243 | F13: =+F12+C13+D13-E13 -> 2100 | I13: =+I12+G13-H13 -> 0 | L13: =+L12+J13-K13 -> 57187
A14: 46083 | B14: CHANGE | E14: 50 | F14: =+F13+C14+D14-E14 -> 2050 | I14: =+I13+G14-H14 -> 0 | J14: 112500 | L14: =+L13+J14-K14 -> 169687
A15: 46083 | B15: KINKOLE - Frais maintenanciers+supplement transport | E15: 500 | F15: =+F14+C15+D15-E15 -> 1550 | I15: =+I14+G15-H15 -> 0 | K15: 150000 | L15: =+L14+J15-K15 -> 19687
A16: 46084 | B16: MALEWU - Carburant TATA/DELUXE | E16: 50 | F16: =+F15+C16+D16-E16 -> 1500 | H16: 0 | I16: =+I15+G16-H16 -> 0 | L16: =+L15+J16-K16 -> 19687
A17: 46084 | B17: MBENKIE - Carburant JAC/CONTAINER | E17: 50 | F17: =+F16+C17+D17-E17 -> 1450 | I17: =+I16+G17-H17 -> 0 | L17: =+L16+J17-K17 -> 19687
A18: 46084 | B18: UTEX - 18 Piles touches cfr GEORGES | F18: =+F17+C18+D18-E18 -> 1450 | I18: =+I17+G18-H18 -> 0 | K18: 20000 | L18: =+L17+J18-K18 -> -313
A19: 46084 | B19: PROSPERE LIHOZA - Carburant NISSAN / DG | E19: 70 | F19: =+F18+C19+D19-E19 -> 1380 | I19: =+I18+G19-H19 -> 0 | L19: =+L18+J19-K19 -> -313
A20: 46084 | B20: PROSPERE LIHOZA - Communications | E20: 10 | F20: =+F19+C20+D20-E20 -> 1370 | I20: =+I19+G20-H20 -> 0 | L20: =+L19+J20-K20 -> -313
A21: 46084 | B21: CLAUDE - Carburant PICKUP L200 | E21: 50 | F21: =+F20+C21+D21-E21 -> 1320 | I21: =+I20+G21-H21 -> 0 | L21: =+L20+J21-K21 -> -313
A22: 46084 | B22: LOSEMBE 1 - Carburant groupe NDOLO | E22: 100 | F22: =+F21+C22+D22-E22 -> 1220 | I22: =+I21+G22-H22 -> 0 | L22: =+L21+J22-K22 -> -313
A23: 46084 | B23: CHICK - Carburant PRADO/DG | E23: 70 | F23: =+F22+C23+D23-E23 -> 1150 | I23: =+I22+G23-H23 -> 0 | L23: =+L22+J23-K23 -> -313
A24: 46084 | B24: Poupon IKELE - Bache bateau IY | E24: 320 | F24: =+F23+C24+D24-E24 -> 830 | I24: =+I23+G24-H24 -> 0 | L24: =+L23+J24-K24 -> -313
A25: 46084 | B25: MAJESTIC - 1 Bouteille freon R404 | E25: 140 | F25: =+F24+C25+D25-E25 -> 690 | I25: =+I24+G25-H25 -> 0 | L25: =+L24+J25-K25 -> -313
A26: 46084 | B26: PRIMMO - 5 Crts colle contact | E26: 300 | F26: =+F25+C26+D26-E26 -> 390 | I26: =+I25+G26-H26 -> 0 | L26: =+L25+J26-K26 -> -313
A27: 46084 | B27: ATRIUM - Crts colle contact | E27: 300 | F27: =+F26+C27+D27-E27 -> 90 | I27: =+I26+G27-H27 -> 0 | L27: =+L26+J27-K27 -> -313
A28: 46084 | B28: LIOKO - Transport MONKOLE | F28: =+F27+C28+D28-E28 -> 90 | I28: =+I27+G28-H28 -> 0 | K28: 12000 | L28: =+L27+J28-K28 -> -12313
A29: 46084 | B29: GEORGES - 1 Chambre à air NISSAN PATROL | E29: 10 | F29: =+F28+C29+D29-E29 -> 80 | I29: =+I28+G29-H29 -> 0 | L29: =+L28+J29-K29 -> -12313
A30: 46084 | B30: CHANGE | E30: 50 | F30: =+F29+C30+D30-E30 -> 30 | I30: =+I29+G30-H30 -> 0 | J30: 112500 | L30: =+L29+J30-K30 -> 100187
A31: 46084 | B31: ATRIUM - Evacuation poubelle 4e Etage | F31: =+F30+C31+D31-E31 -> 30 | I31: =+I30+G31-H31 -> 0 | K31: 20000 | L31: =+L30+J31-K31 -> 80187
A32: 46084 | B32: DEV GROUP-Fact.2025/SN/129-149-164-174 & 2026.01/SN/12 | C32: 1114 | F32: =+F31+C32+D32-E32 -> 1144 | I32: =+I31+G32-H32 -> 0 | L32: =+L31+J32-K32 -> 80187
A33: 46085 | B33: LOSEMBE 1 - Transport RESIDENCE IVAN | F33: =+F32+C33+D33-E33 -> 1144 | H33: 0 | I33: =+I32+G33-H33 -> 0 | K33: 10000 | L33: =+L32+J33-K33 -> 70187
A34: 46085 | B34: PRIMMO - 5Pqts electrodes 2,25 & 10pqts baguettes ag | E34: 235 | F34: =+F33+C34+D34-E34 -> 909 | I34: =+I33+G34-H34 -> 0 | L34: =+L33+J34-K34 -> 70187
A35: 46085 | B35: ATRIUM - 3L miel & 1bte lait | E35: 74 | F35: =+F34+C35+D35-E35 -> 835 | I35: =+I34+G35-H35 -> 0 | L35: =+L34+J35-K35 -> 70187
A36: 46085 | B36: PRIMMO - 3L miel & 1 bte lait | E36: 74 | F36: =+F35+C36+D36-E36 -> 761 | I36: =+I35+G36-H36 -> 0 | L36: =+L35+J36-K36 -> 70187
A37: 46085 | B37: COMIMMO 2 - 2 Bouteille acetylene, 2 oxygene | E37: 392 | F37: =+F36+C37+D37-E37 -> 369 | I37: =+I36+G37-H37 -> 0 | L37: =+L36+J37-K37 -> 70187
A38: 46085 | B38: LOSEMBE 1 - Entretien groupe NDOLO | E38: 120 | F38: =+F37+C38+D38-E38 -> 249 | I38: =+I37+G38-H38 -> 0 | L38: =+L37+J38-K38 -> 70187
A39: 46085 | B39: LOSEMBE 1 - Eclairage entrepot NDOLO | E39: 70 | F39: =+F38+C39+D39-E39 -> 179 | I39: =+I38+G39-H39 -> 0 | L39: =+L38+J39-K39 -> 70187
A40: 46085 | B40: COMIMMO 2 - Acpte Facture 2025/DA/114 | C40: 9500 | F40: =+F39+C40+D40-E40 -> 9679 | I40: =+I39+G40-H40 -> 0 | L40: =+L39+J40-K40 -> 70187
A41: 46085 | B41: JAPAN MOTORS - Facture 2026.02/DT/31 | C41: 464 | F41: =+F40+C41+D41-E41 -> 10143 | I41: =+I40+G41-H41 -> 0 | J41: 2000 | L41: =+L40+J41-K41 -> 72187
A42: 46085 | B42: SOGIC - Facture 2026.02/DA/72-73 | C42: 445 | F42: =+F41+C42+D42-E42 -> 10588 | I42: =+I41+G42-H42 -> 0 | L42: =+L41+J42-K42 -> 72187
A43: 46085 | B43: LYS SARL-Fact.2025/SN/161-166-102-111-126-144-162-167 | C43: 11000 | F43: =+F42+C43+D43-E43 -> 21588 | I43: =+I42+G43-H43 -> 0 | L43: =+L42+J43-K43 -> 72187
A44: 46085 | B44: &2026.01/SN/6-8-21-23 | F44: =+F43+C44+D44-E44 -> 21588 | I44: =+I43+G44-H44 -> 0 | L44: =+L43+J44-K44 -> 72187
A45: 46085 | B45: IY - RETRAIT cfr CAISSE | E45: 11000 | F45: =+F44+C45+D45-E45 -> 10588 | I45: =+I44+G45-H45 -> 0 | L45: =+L44+J45-K45 -> 72187
A46: 46086 | B46: leko - Carburant IST | E46: 40 | F46: =+F45+C46+D46-E46 -> 10548 | H46: 0 | I46: =+I45+G46-H46 -> 0 | L46: =+L45+J46-K46 -> 72187
A47: 46086 | B47: KNTC - Acpte fournit. Système detect°, extincteurs, devidoirs | E47: 3010 | F47: =+F46+C47+D47-E47 -> 7538 | I47: =+I46+G47-H47 -> 0 | L47: =+L46+J47-K47 -> 72187
A48: 46086 | B48: MAMBA SECURITY - Facture NDOLO 11-12/2025 | E48: 500 | F48: =+F47+C48+D48-E48 -> 7038 | I48: =+I47+G48-H48 -> 0 | L48: =+L47+J48-K48 -> 72187
A49: 46086 | B49: MAMBA SECURITY - Facture RESIDENCE IY 11-12/2025 | E49: 1000 | F49: =+F48+C49+D49-E49 -> 6038 | I49: =+I48+G49-H49 -> 0 | L49: =+L48+J49-K49 -> 72187
A50: 46086 | B50: MOATEZ MAIEL - Rbrst depenses & communication 01/2026 | E50: 579 | F50: =+F49+C50+D50-E50 -> 5459 | I50: =+I49+G50-H50 -> 0 | L50: =+L49+J50-K50 -> 72187
A51: 46086 | B51: URBAIN - 4 Cartouches toner cfr USCT | E51: 530 | F51: =+F50+C51+D51-E51 -> 4929 | I51: =+I50+G51-H51 -> 0 | L51: =+L50+J51-K51 -> 72187
A52: 46086 | B52: ETS NEW CEPRONAC - Passage immondices residence 02/2026 | E52: 100 | F52: =+F51+C52+D52-E52 -> 4829 | I52: =+I51+G52-H52 -> 0 | L52: =+L51+J52-K52 -> 72187
A53: 46086 | B53: CHANGE | E53: 200 | F53: =+F52+C53+D53-E53 -> 4629 | I53: =+I52+G53-H53 -> 0 | J53: 450000 | L53: =+L52+J53-K53 -> 522187
A54: 46086 | B54: PGHK - HS wapetwa, imbana, menga, matondo, steve, prospere | F54: =+F53+C54+D54-E54 -> 4629 | I54: =+I53+G54-H54 -> 0 | K54: 108000 | L54: =+L53+J54-K54 -> 414187
A55: 46086 | B55: PGHK - HS samedi 06-07/12/2025 matondo | F55: =+F54+C55+D55-E55 -> 4629 | I55: =+I54+G55-H55 -> 0 | K55: 135000 | L55: =+L54+J55-K55 -> 279187
A56: 46086 | B56: PROSPERE - Divers 02/2026 | F56: =+F55+C56+D56-E56 -> 4629 | I56: =+I55+G56-H56 -> 0 | K56: 75000 | L56: =+L55+J56-K56 -> 204187
A57: 46086 | B57: MAKIESE Pierre - Divers 02/2026 | F57: =+F56+C57+D57-E57 -> 4629 | I57: =+I56+G57-H57 -> 0 | K57: 50000 | L57: =+L56+J57-K57 -> 154187
A58: 46086 | B58: Poupon IKELE - Solde mecano CHICO/Bateau IY | E58: 100 | F58: =+F57+C58+D58-E58 -> 4529 | I58: =+I57+G58-H58 -> 0 | L58: =+L57+J58-K58 -> 154187
A59: 46086 | B59: SALAMA CONGO - Abonnement mensuel sécurité 03/2026 | E59: 250 | F59: =+F58+C59+D59-E59 -> 4279 | I59: =+I58+G59-H59 -> 0 | L59: =+L58+J59-K59 -> 154187
A60: 46086 | B60: MOATEZ MAIEL - Prestations 02/2026 | E60: 2250 | F60: =+F59+C60+D60-E60 -> 2029 | I60: =+I59+G60-H60 -> 0 | L60: =+L59+J60-K60 -> 154187
A61: 46086 | B61: Monsieur THOMAS - Facture 2026.02/SN/34 | C61: 210 | F61: =+F60+C61+D61-E61 -> 2239 | I61: =+I60+G61-H61 -> 0 | L61: =+L60+J61-K61 -> 154187
A62: 46086 | B62: SHEHENAJ L.M. - Facture 2026.02/SN/25-35 | C62: 551 | F62: =+F61+C62+D62-E62 -> 2790 | I62: =+I61+G62-H62 -> 0 | J62: 500 | L62: =+L61+J62-K62 -> 154687
A63: 46086 | B63: Immeuble DELPHIN - Facture 2026.01/DA/66 | C63: 240 | F63: =+F62+C63+D63-E63 -> 3030 | I63: =+I62+G63-H63 -> 0 | J63: 8100 | L63: =+L62+J63-K63 -> 162787
A64: 46086 | B64: COMMUNAUTE HELLENIQUE - Facture 2026.02/DA/85 | C64: 146 | F64: =+F63+C64+D64-E64 -> 3176 | I64: =+I63+G64-H64 -> 0 | L64: =+L63+J64-K64 -> 162787
A65: 46086 | B65: RS HOLDING - 1 Bouteille freon R410A | E65: 140 | F65: =+F64+C65+D65-E65 -> 3036 | I65: =+I64+G65-H65 -> 0 | L65: =+L64+J65-K65 -> 162787
A66: 46087 | B66: FRANCK - Course de service cfr MIESSI/Dos. Montassar | E66: 10 | F66: =+F65+C66+D66-E66 -> 3026 | H66: 0 | I66: =+I65+G66-H66 -> 0 | L66: =+L65+J66-K66 -> 162787
A67: 46087 | B67: AGL - Frais accès tarmac aero | E67: 129 | F67: =+F66+C67+D67-E67 -> 2897 | I67: =+I66+G67-H67 -> 0 | L67: =+L66+J67-K67 -> 162787
A68: 46087 | B68: GEORGES - Prime trimestrielle | E68: 2000 | F68: =+F67+C68+D68-E68 -> 897 | I68: =+I67+G68-H68 -> 0 | L68: =+L67+J68-K68 -> 162787
A69: 46087 | B69: DIDIER - Entretien TATA SUPER | E69: 667 | F69: =+F68+C69+D69-E69 -> 230 | I69: =+I68+G69-H69 -> 0 | L69: =+L68+J69-K69 -> 162787
A70: 46087 | B70: CHANGE | E70: 200 | F70: =+F69+C70+D70-E70 -> 30 | I70: =+I69+G70-H70 -> 0 | J70: 450000 | L70: =+L69+J70-K70 -> 612787
A71: 46087 | B71: LPL - HS samedi 03 & 05/01/2026 13 agents | F71: =+F70+C71+D71-E71 -> 30 | I71: =+I70+G71-H71 -> 0 | K71: 380500 | L71: =+L70+J71-K71 -> 232287
A72: 46087 | B72: RAWBANK USD - RETRAIT | D72: 5000 | F72: =+F71+C72+D72-E72 -> 5030 | I72: =+I71+G72-H72 -> 0 | L72: =+L71+J72-K72 -> 232287
A73: 46087 | B73: CDI - Mise à dispo / REGUL TVA 2025 | E73: 5000 | F73: =+F72+C73+D73-E73 -> 30 | I73: =+I72+G73-H73 -> 0 | L73: =+L72+J73-K73 -> 232287
A74: 46087 | B74: DIDIER - Carburant groupe NDOLO | E74: 50 | F74: =+F73+C74+D74-E74 -> -20 | I74: =+I73+G74-H74 -> 0 | L74: =+L73+J74-K74 -> 232287
A75: 46087 | B75: ALVARO - Evacuation poubelle NDOLO | F75: =+F74+C75+D75-E75 -> -20 | I75: =+I74+G75-H75 -> 0 | K75: 10000 | L75: =+L74+J75-K75 -> 222287
A76: 46087 | B76: IMMEUBLE MALAIKA - Facture 2026.01/SN/13 | C76: 450 | F76: =+F75+C76+D76-E76 -> 430 | I76: =+I75+G76-H76 -> 0 | L76: =+L75+J76-K76 -> 222287
A77: 46087 | B77: A ONE CONSTRUCTION - Facture 2026.02/SN/26 | C77: 420 | F77: =+F76+C77+D77-E77 -> 850 | I77: =+I76+G77-H77 -> 0 | L77: =+L76+J77-K77 -> 222287
A78: 46087 | B78: IMMEUBLE MARIE YVETTE - Facture 2026.01/SN/14 | C78: 180 | F78: =+F77+C78+D78-E78 -> 1030 | I78: =+I77+G78-H78 -> 0 | J78: 7000 | L78: =+L77+J78-K78 -> 229287
A79: 46087 | B79: ESPACE SHADARY - Facture 2025/SN/138-139 | C79: 400 | F79: =+F78+C79+D79-E79 -> 1430 | I79: =+I78+G79-H79 -> 0 | L79: =+L78+J79-K79 -> 229287
A80: 46087 | B80: COMIMMO 2 - 5 Bidons vides 25L | F80: =+F79+C80+D80-E80 -> 1430 | I80: =+I79+G80-H80 -> 0 | K80: 75000 | L80: =+L79+J80-K80 -> 154287
A81: 46087 | B81: GEORGES - Retour s/achat sonde MAJESTIC | D81: 55 | F81: =+F80+C81+D81-E81 -> 1485 | I81: =+I80+G81-H81 -> 0 | L81: =+L80+J81-K81 -> 154287
A82: 46087 | B82: ATRIUM/COMIMMO - Pt journaliers cfr FRANCK | F82: =+F81+C82+D82-E82 -> 1485 | I82: =+I81+G82-H82 -> 0 | K82: 140000 | L82: =+L81+J82-K82 -> 14287
A83: 46090 | B83: MALEWU - Carburant TATA DELUXE | E83: 50 | F83: =+F82+C83+D83-E83 -> 1435 | H83: 0 | I83: =+I82+G83-H83 -> 0 | L83: =+L82+J83-K83 -> 14287
A84: 46090 | B84: MBENKIE - Carburant JAC/CONTAINER | E84: 50 | F84: =+F83+C84+D84-E84 -> 1385 | I84: =+I83+G84-H84 -> 0 | L84: =+L83+J84-K84 -> 14287
A85: 46090 | B85: CLAUDE - Carburant PICKUP L200 | E85: 50 | F85: =+F84+C85+D85-E85 -> 1335 | I85: =+I84+G85-H85 -> 0 | L85: =+L84+J85-K85 -> 14287
A86: 46090 | B86: PROSPERE - Carburant NISSAN/DG | E86: 70 | F86: =+F85+C86+D86-E86 -> 1265 | I86: =+I85+G86-H86 -> 0 | L86: =+L85+J86-K86 -> 14287
A87: 46090 | B87: CHICK - Carburant PRADO/DG | E87: 70 | F87: =+F86+C87+D87-E87 -> 1195 | I87: =+I86+G87-H87 -> 0 | L87: =+L86+J87-K87 -> 14287
A88: 46090 | B88: LOSEMBE 1 - Carburant groupe NDOLO | E88: 50 | F88: =+F87+C88+D88-E88 -> 1145 | I88: =+I87+G88-H88 -> 0 | L88: =+L87+J88-K88 -> 14287
A89: 46090 | B89: GEORGES - Carburant NISSAN PATROL | E89: 60 | F89: =+F88+C89+D89-E89 -> 1085 | I89: =+I88+G89-H89 -> 0 | L89: =+L88+J89-K89 -> 14287
A90: 46090 | B90: NANCY - Achat bons de sortie caisse | E90: 20 | F90: =+F89+C90+D90-E90 -> 1065 | I90: =+I89+G90-H90 -> 0 | L90: =+L89+J90-K90 -> 14287
A91: 46090 | B91: BANGAMO - 6 jetons de presence cfr REUNION | E91: 120 | F91: =+F90+C91+D91-E91 -> 945 | I91: =+I90+G91-H91 -> 0 | L91: =+L90+J91-K91 -> 14287
A92: 46090 | B92: ZHENDRE - Amende frais douane & manutention | E92: 268 | F92: =+F91+C92+D92-E92 -> 677 | I92: =+I91+G92-H92 -> 0 | L92: =+L91+J92-K92 -> 14287
A93: 46090 | B93: MR KETELEER PRINCE - Facture 2026.01/SN/5 | C93: 170 | F93: =+F92+C93+D93-E93 -> 847 | I93: =+I92+G93-H93 -> 0 | J93: 11000 | L93: =+L92+J93-K93 -> 25287
A94: 46090 | B94: ATRIUM - 5 Meches à beton 5&10 | E94: 75 | F94: =+F93+C94+D94-E94 -> 772 | I94: =+I93+G94-H94 -> 0 | L94: =+L93+J94-K94 -> 25287
A95: 46090 | B95: COMIMMO2 - Meches à diamant 10-12, disque c230--- | E95: 92 | F95: =+F94+C95+D95-E95 -> 680 | I95: =+I94+G95-H95 -> 0 | L95: =+L94+J95-K95 -> 25287
A96: 46090 | B96: ATRIUM - 15Tès Y pvc 40& 20Tès pvc 32 | E96: 120 | F96: =+F95+C96+D96-E96 -> 560 | I96: =+I95+G96-H96 -> 0 | L96: =+L95+J96-K96 -> 25287
A97: 46090 | B97: COMMUNICATIONS willy, georges, urbain, nancy | E97: 80 | F97: =+F96+C97+D97-E97 -> 480 | I97: =+I96+G97-H97 -> 0 | L97: =+L96+J97-K97 -> 25287
A98: 46090 | B98: MNAOUER - Communications | E98: 20 | F98: =+F97+C98+D98-E98 -> 460 | I98: =+I97+G98-H98 -> 0 | L98: =+L97+J98-K98 -> 25287
A99: 46090 | B99: COMMUNICATIONS franck, kusiekita, bangamo, ndona | E99: 40 | F99: =+F98+C99+D99-E99 -> 420 | I99: =+I98+G99-H99 -> 0 | L99: =+L98+J99-K99 -> 25287
A100: 46091 | B100: IMMEUBLE SERKAS - Facture 2026.02/DA/92 | C100: 210 | F100: =+F99+C100+D100-E100 -> 630 | H100: 0 | I100: =+I99+G100-H100 -> 0 | J100: 1000 | L100: =+L99+J100-K100 -> 26287
...

Sheet 022026
A1: ELECTROCOOL
A2: JOURNAL MENSUEL DE CAISSE | L2: 46054
B3: LIBELLES | D3: USD | H3: EUROS | J3: Francs
C4: ENC CLIENT | D4: ENTREE ($) | E4: SORTIE ($) | F4: SOLDE ($) | G4: ENTREE (Euro) | H4: SORTIE (Euro) | I4: SOLDE (Euro) | J4: ENTREE (Francs) | K4: SORTIE (Francs) | L4: SOLDE (francs)
B5: REPORT | D5: 662 | F5: =D5 -> 662 | G5: 0 | I5: 0 | J5: 26967 | L5: =J5 -> 26967
A6: 46055 | B6: RAWBANK USD - RETRAIT | D6: 1500 | F6: =+F5+C6+D6-E6 -> 2162 | H6: 0 | I6: =+I5+G6-H6 -> 0 | L6: =+L5+J6-K6 -> 26967
A7: 46055 | B7: CLAUDE - Carburant PICKUP L200 | E7: 50 | F7: =+F6+C7+D7-E7 -> 2112 | I7: =+I6+G7-H7 -> 0 | L7: =+L6+J7-K7 -> 26967
A8: 46055 | B8: PROSPERE - Carburant NISSAN/DG | E8: 70 | F8: =+F7+C8+D8-E8 -> 2042 | I8: =+I7+G8-H8 -> 0 | L8: =+L7+J8-K8 -> 26967
A9: 46055 | B9: PROSPERE - Communications | E9: 10 | F9: =+F8+C9+D9-E9 -> 2032 | I9: =+I8+G9-H9 -> 0 | L9: =+L8+J9-K9 -> 26967
A10: 46055 | B10: MBENKIE - Carburant JAC/CONTAINER | E10: 50 | F10: =+F9+C10+D10-E10 -> 1982 | I10: =+I9+G10-H10 -> 0 | L10: =+L9+J10-K10 -> 26967
A11: 46055 | B11: CHICK - Carburant PRADO | E11: 70 | F11: =+F10+C11+D11-E11 -> 1912 | I11: =+I10+G11-H11 -> 0 | L11: =+L10+J11-K11 -> 26967
A12: 46055 | B12: LOSEMBE 1 - Carburant groupe NDOLO | E12: 100 | F12: =+F11+C12+D12-E12 -> 1812 | I12: =+I11+G12-H12 -> 0 | L12: =+L11+J12-K12 -> 26967
A13: 46055 | B13: KINKOLE - 4 Rlmnts 6201 | E13: 50 | F13: =+F12+C13+D13-E13 -> 1762 | I13: =+I12+G13-H13 -> 0 | L13: =+L12+J13-K13 -> 26967
A14: 46055 | B14: PRIMMO - Journaliers dechargement container 4 | E14: 100 | F14: =+F13+C14+D14-E14 -> 1662 | I14: =+I13+G14-H14 -> 0 | L14: =+L13+J14-K14 -> 26967
A15: 46055 | B15: COMMUNICATIONS willy, georges, urbain, nancy | E15: 80 | F15: =+F14+C15+D15-E15 -> 1582 | I15: =+I14+G15-H15 -> 0 | L15: =+L14+J15-K15 -> 26967
A16: 46055 | B16: COMMUNCATIONS franck, kusiekita, bangamo | E16: 30 | F16: =+F15+C16+D16-E16 -> 1552 | I16: =+I15+G16-H16 -> 0 | L16: =+L15+J16-K16 -> 26967
A17: 46055 | B17: MNAOUER - Communications | E17: 20 | F17: =+F16+C17+D17-E17 -> 1532 | I17: =+I16+G17-H17 -> 0 | L17: =+L16+J17-K17 -> 26967
A18: 46055 | B18: LUBAKI - Avance pension de retraite | E18: 500 | F18: =+F17+C18+D18-E18 -> 1032 | I18: =+I17+G18-H18 -> 0 | L18: =+L17+J18-K18 -> 26967
... A20: 46055 | B20: ATRIUM - Impression 6plans A0 | E20: 90 | F20: =+F19+C20+D20-E20 -> 742 | I20: =+I19+G20-H20 -> 0 | L20: =+L19+J20-K20 -> 26967
A21: 46056 | B21: RAWBANK USD - RETRAIT | D21: 2000 | F21: =+F20+C21+D21-E21 -> 2742 | H21: 0 | I21: =+I20+G21-H21 -> 0 | L21: =+L20+J21-K21 -> 26967
A22: 46056 | B22: SOFIBANK USD - RETRAIT | D22: 2000 | F22: =+F21+C22+D22-E22 -> 4742 | I22: =+I21+G22-H22 -> 0 | L22: =+L21+J22-K22 -> 26967
A23: 46056 | B23: RESIDENCE IVAN - IF & IRL 4eTRIM.2025+Frais Mpesa | E23: 900 | F23: =+F22+C23+D23-E23 -> 3842 | I23: =+I22+G23-H23 -> 0 | K23: 10000 | L23: =+L22+J23-K23 -> 16967
A24: 46056 | B24: VENUS/MERVEILLE - 20Baguettes, 3gaz butane, 3disques D | E24: 220 | F24: =+F23+C24+D24-E24 -> 3622 | I24: =+I23+G24-H24 -> 0 | L24: =+L23+J24-K24 -> 16967
A25: 46056 | B25: KINKOLE - Frais journaliers entretien CF/HUB | E25: 120 | F25: =+F24+C25+D25-E25 -> 3502 | I25: =+I24+G25-H25 -> 0 | L25: =+L24+J25-K25 -> 16967
A26: 46056 | B26: ATRIUM - 10Tenues completes | E26: 350 | F26: =+F25+C26+D26-E26 -> 3152 | I26: =+I25+G26-H26 -> 0 | L26: =+L25+J26-K26 -> 16967
A27: 46056 | B27: PRIMMO - Accessoires divers cfr bon 3119 | E27: 900 | F27: =+F26+C27+D27-E27 -> 2252 | I27: =+I26+G27-H27 -> 0 | L27: =+L26+J27-K27 -> 16967
A28: 46056 | B28: ATRIUM - Divers outillage cfr bon 3002 | E28: 1100 | F28: =+F27+C28+D28-E28 -> 1152 | I28: =+I27+G28-H28 -> 0 | L28: =+L27+J28-K28 -> 16967
A29: 46056 | B29: MAGASIN - 2Pqts pinceaux pour entretien | E29: 30 | F29: =+F28+C29+D29-E29 -> 1122 | I29: =+I28+G29-H29 -> 0 | L29: =+L28+J29-K29 -> 16967
A30: 46056 | B30: MAGASIN - 1Ballon de lock entretien | E30: 100 | F30: =+F29+C30+D30-E30 -> 1022 | I30: =+I29+G30-H30 -> 0 | L30: =+L29+J30-K30 -> 16967
A31: 46056 | B31: MAGASIN - 10 Supports condenseurs | E31: 150 | F31: =+F30+C31+D31-E31 -> 872 | I31: =+I30+G31-H31 -> 0 | L31: =+L30+J31-K31 -> 16967
A32: 46056 | B32: MAGASIN - 50 Capas 1,5µf | E32: 100 | F32: =+F31+C32+D32-E32 -> 772 | I32: =+I31+G32-H32 -> 0 | L32: =+L31+J32-K32 -> 16967
A33: 46056 | B33: DIVERS | E33: 100 | F33: =+F32+C33+D33-E33 -> 672 | I33: =+I32+G33-H33 -> 0 | L33: =+L32+J33-K33 -> 16967
A34: 46057 | B34: RAWBANK USD - RETRAIT | D34: 1500 | F34: =+F33+C34+D34-E34 -> 2172 | H34: 0 | I34: =+I33+G34-H34 -> 0 | L34: =+L33+J34-K34 -> 16967
A35: 46057 | B35: SOFIBANK USD - RETRAIT | D35: 2500 | F35: =+F34+C35+D35-E35 -> 4672 | I35: =+I34+G35-H35 -> 0 | L35: =+L34+J35-K35 -> 16967
A36: 46057 | B36: MOATAZ - Prestations 01/2026 | E36: 2250 | F36: =+F35+C36+D36-E36 -> 2422 | I36: =+I35+G36-H36 -> 0 | K36: 10000 | L36: =+L35+J36-K36 -> 6967
A37: 46057 | B37: CHICK - Communications | E37: 10 | F37: =+F36+C37+D37-E37 -> 2412 | I37: =+I36+G37-H37 -> 0 | L37: =+L36+J37-K37 -> 6967
A38: 46057 | B38: DIDIER - Achat siliconne IST | F38: =+F37+C38+D38-E38 -> 2412 | I38: =+I37+G38-H38 -> 0 | K38: 5000 | L38: =+L37+J38-K38 -> 1967
A39: 46057 | B39: SUCRIERE - Accessoires divers cfr bon 3132 | E39: 635 | F39: =+F38+C39+D39-E39 -> 1777 | I39: =+I38+G39-H39 -> 0 | L39: =+L38+J39-K39 -> 1967
A40: 46057 | B40: PRIMMO - 2 Bouteilles freon azote, 2 acetylene, 2 oxygene | E40: 632 | F40: =+F39+C40+D40-E40 -> 1145 | I40: =+I39+G40-H40 -> 0 | L40: =+L39+J40-K40 -> 1967
A41: 46057 | B41: CHANGE | E41: 100 | F41: =+F40+C41+D41-E41 -> 1045 | I41: =+I40+G41-H41 -> 0 | J41: 220000 | L41: =+L40+J41-K41 -> 221967
A42: 46057 | B42: KINKOLE - Frais maintenanciers HUB+Suppl transport | E42: 500 | F42: =+F41+C42+D42-E42 -> 545 | I42: =+I41+G42-H42 -> 0 | K42: 150000 | L42: =+L41+J42-K42 -> 71967
A43: 46057 | B43: LFRD - Facture 2025/DTT/30 | C43: 50 | F43: =+F42+C43+D43-E43 -> 595 | I43: =+I42+G43-H43 -> 0 | L43: =+L42+J43-K43 -> 71967
A44: 46058 | B44: EBCDC USD - RETRAIT | D44: 1000 | F44: =+F43+C44+D44-E44 -> 1595 | H44: 0 | I44: =+I43+G44-H44 -> 0 | L44: =+L43+J44-K44 -> 71967
A45: 46058 | B45: LOSEMBE 1 - Carburant groupe NDOLO | E45: 100 | F45: =+F44+C45+D45-E45 -> 1495 | I45: =+I44+G45-H45 -> 0 | L45: =+L44+J45-K45 -> 71967
A46: 46058 | B46: MUMBIMBI - Transport SUCRIERE | F46: =+F45+C46+D46-E46 -> 1495 | I46: =+I45+G46-H46 -> 0 | K46: 10000 | L46: =+L45+J46-K46 -> 61967
A47: 46058 | B47: LOSEMBE 1 - Transport RESIDENCE IVAN | F47: =+F46+C47+D47-E47 -> 1495 | I47: =+I46+G47-H47 -> 0 | K47: 10000 | L47: =+L46+J47-K47 -> 51967
A48: 46058 | B48: PRIMMO - Impression 10 plans A0 | E48: 150 | F48: =+F47+C48+D48-E48 -> 1345 | I48: =+I47+G48-H48 -> 0 | L48: =+L47+J48-K48 -> 51967
A49: 46058 | B49: DIDIER - Achat moteur VVT1 IST (PRÊT) | E49: 900 | F49: =+F48+C49+D49-E49 -> 445 | I49: =+I48+G49-H49 -> 0 | L49: =+L48+J49-K49 -> 51967
A50: 46058 | B50: CHANGE | E50: 100 | F50: =+F49+C50+D50-E50 -> 345 | I50: =+I49+G50-H50 -> 0 | J50: 220000 | L50: =+L49+J50-K50 -> 271967
A51: 46058 | B51: DIDIER - Achat huile moteur SAE40 IST | F51: =+F50+C51+D51-E51 -> 345 | I51: =+I50+G51-H51 -> 0 | K51: 90000 | L51: =+L50+J51-K51 -> 181967
A52: 46058 | B52: NANCY - Course de service | F52: =+F51+C52+D52-E52 -> 345 | I52: =+I51+G52-H52 -> 0 | K52: 10000 | L52: =+L51+J52-K52 -> 171967
A53: 46058 | B53: PRIMMO - 1Pqt embouts | E53: 10 | F53: =+F52+C53+D53-E53 -> 335 | I53: =+I52+G53-H53 -> 0 | L53: =+L52+J53-K53 -> 171967
A54: 46058 | B54: rawbank - Accessoires cfr bon 3135 | E54: 298 | F54: =+F53+C54+D54-E54 -> 37 | I54: =+I53+G54-H54 -> 0 | L54: =+L53+J54-K54 -> 171967
A55: 46058 | B55: SHEHENAJ L.M. - Facture 2026.01/SN/18 | C55: 350 | F55: =+F54+C55+D55-E55 -> 387 | I55: =+I54+G55-H55 -> 0 | L55: =+L54+J55-K55 -> 171967
A56: 46058 | B56: SHEHENAJ L.M. - Facture 2026.01/SN/17 | C56: 175 | F56: =+F55+C56+D56-E56 -> 562 | I56: =+I55+G56-H56 -> 0 | L56: =+L55+J56-K56 -> 171967
A57: 46059 | B57: MALEWU - Carburant TATA DELUXE | E57: 50 | F57: =+F56+C57+D57-E57 -> 512 | H57: 0 | I57: =+I56+G57-H57 -> 0 | L57: =+L56+J57-K57 -> 171967
A58: 46059 | B58: UTEX/BCECO - Accessoires cfr bon 3146 | E58: 207 | F58: =+F57+C58+D58-E58 -> 305 | I58: =+I57+G58-H58 -> 0 | L58: =+L57+J58-K58 -> 171967
A59: 46059 | B59: Charles DIVANGAMENE - Pces demarreur PICKUP L200 | E59: 135 | F59: =+F58+C59+D59-E59 -> 170 | I59: =+I58+G59-H59 -> 0 | L59: =+L58+J59-K59 -> 171967
A60: 46059 | B60: ALVARO - Evacuation poubelle NDOLO | F60: =+F59+C60+D60-E60 -> 170 | I60: =+I59+G60-H60 -> 0 | K60: 10000 | L60: =+L59+J60-K60 -> 161967
A61: 46059 | B61: URBAIN - Achat toner imprimante TOSHIBA | E61: 70 | F61: =+F60+C61+D61-E61 -> 100 | I61: =+I60+G61-H61 -> 0 | L61: =+L60+J61-K61 -> 161967
A62: 46062 | B62: RAWBANK USD - RETRAIT | D62: 9500 | F62: =+F61+C62+D62-E62 -> 9600 | H62: 0 | I62: =+I61+G62-H62 -> 0 | L62: =+L61+J62-K62 -> 161967
A63: 46062 | B63: CHANGE | E63: 6100 | F63: =+F62+C63+D63-E63 -> 3500 | I63: =+I62+G63-H63 -> 0 | J63: 14030000 | L63: =+L62+J63-K63 -> 14191967
A64: 46062 | B64: ELECTROCOOL - Quinzaine 02/2026 | F64: =+F63+C64+D64-E64 -> 3500 | I64: =+I63+G64-H64 -> 0 | K64: 2720000 | L64: =+L63+J64-K64 -> 11471967
A65: 46062 | B65: EGSC - Quinzaine 02/2026 | F65: =+F64+C65+D65-E65 -> 3500 | I65: =+I64+G65-H65 -> 0 | K65: 2090000 | L65: =+L64+J65-K65 -> 9381967
A66: 46062 | B66: TEMPORAIRES - Quinzaine 02/2026 | F66: =+F65+C66+D66-E66 -> 3500 | I66: =+I65+G66-H66 -> 0 | K66: 5150000 | L66: =+L65+J66-K66 -> 4231967
A67: 46062 | B67: EGSC - CNSS 01/2026 | F67: =+F66+C67+D67-E67 -> 3500 | I67: =+I66+G67-H67 -> 0 | K67: 2248500 | L67: =+L66+J67-K67 -> 1983467
A68: 46062 | B68: EGSC - Ipr 01/2026 | F68: =+F67+C68+D68-E68 -> 3500 | I68: =+I67+G68-H68 -> 0 | K68: 1780500 | L68: =+L67+J68-K68 -> 202967
A69: 46062 | B69: DIDIER - Achat bourrage boite IST | E69: 15 | F69: =+F68+C69+D69-E69 -> 3485 | I69: =+I68+G69-H69 -> 0 | L69: =+L68+J69-K69 -> 202967
A70: 46062 | B70: EMERAUDE - Accessoires divers cfr bon 3280 | E70: 164 | F70: =+F69+C70+D70-E70 -> 3321 | I70: =+I69+G70-H70 -> 0 | L70: =+L69+J70-K70 -> 202967
A71: 46062 | B71: SUCRIERE - Accessoires divers cfr bon 3131 | E71: 909 | F71: =+F70+C71+D71-E71 -> 2412 | I71: =+I70+G71-H71 -> 0 | L71: =+L70+J71-K71 -> 202967
A72: 46062 | B72: ATRIUM - Accessoires cfr bon 3135 | E72: 298 | F72: =+F71+C72+D72-E72 -> 2114 | I72: =+I71+G72-H72 -> 0 | L72: =+L71+J72-K72 -> 202967
A73: 46062 | B73: SUCRIERE - 1 Split LG 12000, 1split 18000btu&1split 24000btu | E73: 1500 | F73: =+F72+C73+D73-E73 -> 614 | I73: =+I72+G73-H73 -> 0 | L73: =+L72+J73-K73 -> 202967
A74: 46062 | B74: ATRIUM - Impression 3 plans A0 | E74: 45 | F74: =+F73+C74+D74-E74 -> 569 | I74: =+I73+G74-H74 -> 0 | L74: =+L73+J74-K74 -> 202967
A75: 46062 | B75: MNAOUER - Achat extender HDMI Wireless | E75: 52 | F75: =+F74+C75+D75-E75 -> 517 | I75: =+I74+G75-H75 -> 0 | L75: =+L74+J75-K75 -> 202967
A76: 46062 | B76: COMMUNICATIONS willy, nancy, urbain, georges | E76: 80 | F76: =+F75+C76+D76-E76 -> 437 | I76: =+I75+G76-H76 -> 0 | L76: =+L75+J76-K76 -> 202967
A77: 46062 | B77: MNAOUER - Communications | E77: 20 | F77: =+F76+C77+D77-E77 -> 417 | I77: =+I76+G77-H77 -> 0 | L77: =+L76+J77-K77 -> 202967
A78: 46062 | B78: COMMUNICATIONS franck, kusiekita, bangamo, ndona | E78: 40 | F78: =+F77+C78+D78-E78 -> 377 | I78: =+I77+G78-H78 -> 0 | L78: =+L77+J78-K78 -> 202967
A79: 46062 | B79: FRANCK - 2 Journaliers / Evacuation meubles MONTASSAR | F79: =+F78+C79+D79-E79 -> 377 | I79: =+I78+G79-H79 -> 0 | K79: 40000 | L79: =+L78+J79-K79 -> 162967
A80: 46062 | B80: PRIMMO - 4 Journaliers / Charge & dechargement gaines | F80: =+F79+C80+D80-E80 -> 377 | I80: =+I79+G80-H80 -> 0 | K80: 80000 | L80: =+L79+J80-K80 -> 82967
A81: 46062 | B81: DIDIER - Huile de refroidissement radiateur+ huile de frein IST | E81: 28 | F81: =+F80+C81+D81-E81 -> 349 | I81: =+I80+G81-H81 -> 0 | L81: =+L80+J81-K81 -> 82967
A82: 46062 | B82: FRANCK - Trft Serge/KOLWEZI - Transport, hebergement, restau--- | E82: 145 | F82: =+F81+C82+D82-E82 -> 204 | I82: =+I81+G82-H82 -> 0 | L82: =+L81+J82-K82 -> 82967
A83: 46062 | B83: MBENKIE - Carburant TATA/CONTAINER | E83: 50 | F83: =+F82+C83+D83-E83 -> 154 | I83: =+I82+G83-H83 -> 0 | L83: =+L82+J83-K83 -> 82967
A84: 46062 | B84: FRANCK - Achat bons de sortie caisse | F84: =+F83+C84+D84-E84 -> 154 | I84: =+I83+G84-H84 -> 0 | K84: 20000 | L84: =+L83+J84-K84 -> 62967
A85: 46062 | B85: GEORGES - Carburant NISSAN PATROL | E85: 50 | F85: =+F84+C85+D85-E85 -> 104 | I85: =+I84+G85-H85 -> 0 | L85: =+L84+J85-K85 -> 62967
F86: =F85+C86+D86-E86 -> 104 | I86: =I85+G86-H86 -> 0 | L86: =L85+J86-K86 -> 62967
A87: 46063 | B87: Prospère LIHOZA - Carburant NISSAN/DG | E87: 70 | F87: =+F86+C87+D87-E87 -> 34 | H87: 0 | I87: =+I86+G87-H87 -> 0 | L87: =+L86+J87-K87 -> 62967
A88: 46063 | B88: Prospère LIHOZA - Communications | E88: 10 | F88: =+F87+C88+D88-E88 -> 24 | I88: =+I87+G88-H88 -> 0 | L88: =+L87+J88-K88 -> 62967
F89: =+F88+C89+D89-E89 -> 24 | I89: =+I88+G89-H89 -> 0 | L89: =+L88+J89-K89 -> 62967
A90: 46064 | B90: TMB USD - RETRAIT | D90: 1500 | F90: =+F89+C90+D90-E90 -> 1524 | H90: 0 | I90: =+I89+G90-H90 -> 0 | L90: =+L89+J90-K90 -> 62967
A91: 46064 | B91: CHANGE | E91: 100 | F91: =+F90+C91+D91-E91 -> 1424 | I91: =+I90+G91-H91 -> 0 | J91: 225000 | L91: =+L90+J91-K91 -> 287967
A92: 46063 | B92: DIDIER - SAE 40 IST | E92: 10 | F92: =+F91+C92+D92-E92 -> 1414 | I92: =+I91+G92-H92 -> 0 | K92: 70000 | L92: =+L91+J92-K92 -> 217967
A93: 46064 | B93: MAKIESE Pierre - Divers 01/2026 | F93: =+F92+C93+D93-E93 -> 1414 | I93: =+I91+G93-H93 -> 0 | K93: 75000 | L93: =+L92+J93-K93 -> 142967
A94: 46064 | B94: Prospere LIHOZA - Divers 01/2026 | F94: =+F93+C94+D94-E94 -> 1414 | I94: =+I93+G94-H94 -> 0 | K94: 50000 | L94: =+L93+J94-K94 -> 92967
A95: 46064 | B95: MBENKIE - Carburant groupe NDOLO | E95: 100 | F95: =+F94+C95+D95-E95 -> 1314 | I95: =+I94+G95-H95 -> 0 | L95: =+L94+J95-K95 -> 92967
A96: 46064 | B96: ATRIUM - 1 Meleuse 125 de 90w | E96: 150 | F96: =+F95+C96+D96-E96 -> 1164 | I96: =+I95+G96-H96 -> 0 | L96: =+L95+J96-K96 -> 92967
A97: 46064 | B97: ATRIUM - 3Crts colle contact | E97: 180 | F97: =+F96+C97+D97-E97 -> 984 | I97: =+I96+G97-H97 -> 0 | L97: =+L96+J97-K97 -> 92967
A98: 46064 | B98: PRIMMO - 2Pqts embouts | E98: 20 | F98: =+F97+C98+D98-E98 -> 964 | I98: =+I97+G98-H98 -> 0 | L98: =+L97+J98-K98 -> 92967
A99: 46064 | B99: DIDIER - 2Pneus TATA SUPER | E99: 140 | F99: =+F98+C99+D99-E99 -> 824 | I99: =+I98+G99-H99 -> 0 | L99: =+L98+J99-K99 -> 92967
A100: 46064 | B100: LYS CENTER - 1 Disjoncteur modulaire 40A | E100: 35 | F100: =+F99+C100+D100-E100 -> 789 | I100: =+I99+G100-H100 -> 0 | L100: =+L99+J100-K100 -> 92967
A101: 46064 | B101: CDI - Divers | E101: 30 | F101: =+F100+C101+D101-E101 -> 759 | I101: =+I100+G101-H101 -> 0 | L101: =+L100+J101-K101 -> 92967
...

Sheet 012026
A1: ELECTROCOOL
A2: RAPPORT DE CAISSE | L2: 46023
B3: LIBELLES | D3: USD | H3: EUROS | J3: Francs
C4: ENC CLIENT | D4: ENTREE ($) | E4: SORTIE ($) | F4: SOLDE ($) | G4: ENTREE (Euro) | H4: SORTIE (Euro) | I4: SOLDE (Euro) | J4: ENTREE (Francs) | K4: SORTIE (Francs) | L4: SOLDE (francs)
B5: REPORT | D5: 40 | F5: =+D5 -> 40 | G5: 0 | I5: 0 | J5: 148014 | L5: 148014
A6: 46024 | B6: RAWBANK USD - RETRAIT | D6: 4500 | F6: =+F5+C6+D6-E6 -> 4540 | H6: 0 | I6: 0 | L6: 148014
A7: 46024 | B7: RESIDENCE IVAN - Paie agents 12/2025 | E7: 420 | F7: =+F6+C7+D7-E7 -> 4120 | I7: 0 | L7: 148014
A8: 46024 | B8: RESIDENCE DG - Paie agents 12/2025 | E8: 450 | F8: =+F7+C8+D8-E8 -> 3670 | I8: 0 | L8: 148014
A9: 46024 | B9: EGSC - SOLDE PRIME agents 12/2025 | E9: 2100 | F9: =+F8+C9+D9-E9 -> 1570 | I9: 0 | L9: 148014
A10: 46024 | B10: WILLY - Prime 2025 | E10: 900 | F10: =+F9+C10+D10-E10 -> 670 | I10: 0 | L10: 148014
A11: 46024 | B11: WILLY - (Frais funeraires) | E11: 600 | F11: =+F10+C11+D11-E11 -> 70 | I11: 0 | L11: 148014
A12: 46024 | B12: SERGE - TRFT / LUSHI + Frais | E12: 150 | F12: =+F11+C12+D12-E12 -> -80 | I12: 0 | K12: 10000 | L12: 138014
A13: 46024 | B13: RAWBANK USD - RETRAIT | D13: 1500 | F13: =+F12+C13+D13-E13 -> 1420 | I13: 0 | L13: 138014
A14: 46024 | B14: CHANGE | E14: 850 | F14: =+F13+C14+D14-E14 -> 570 | I14: 0 | J14: 1870000 | L14: 2008014
A15: 46024 | B15: CDT - Cotisation syndicale s/Gratification ELECTROCOOL | F15: =+F14+C15+D15-E15 -> 570 | I15: 0 | K15: 410000 | L15: 1598014
A16: 46024 | B16: DIDIER - Rechanges NISSAN DG | F16: =+F15+C16+D16-E16 -> 570 | I16: 0 | K16: 1449000 | L16: 149014
A17: 46024 | B17: MBUTELA Brandon - complement prime 12/2025 | E17: 50 | F17: =+F16+C17+D17-E17 -> 520 | I17: 0 | L17: 149014
A18: 46024 | B18: ATRIUM - 10 Disques c125 | F18: =+F17+C18+D18-E18 -> 520 | I18: 0 | K18: 19800 | L18: 129214
A19: 46024 | B19: FRANCK - Location Véhicule / Transport container colis | E19: 200 | F19: =+F18+C19+D19-E19 -> 320 | I19: 0 | L19: 129214
A20: 46024 | B20: FRANCK - Frais journaliers colis/ CONTAINER | E20: 100 | F20: =+F19+C20+D20-E20 -> 220 | I20: 0 | L20: 129214
A21: 46024 | B21: FRANCK - Transport chauffeurs DIDIER&MBENKIE | F21: =+F20+C21+D21-E21 -> 220 | I21: 0 | K21: 50000 | L21: 79214
A22: 46024 | B22: BENI - Travaux peinture RESIDENCE DG | E22: 55 | F22: =+F21+C22+D22-E22 -> 165 | I22: 0 | L22: 79214
A23: 46024 | B23: RESIDENCE DG - 1 Relais compact 20A cfr GEIRGES | E23: 25 | F23: =+F22+C23+D23-E23 -> 140 | I23: 0 | L23: 79214
A24: 46025 | B24: PGHK - 1Lg flexible non isolé 100 (RETOUR/NON PAYE) | D24: 25 | F24: =+F23+D24-E24 -> 165 | I24: 0 | L24: =+L23+J24-K24 -> 79214
A25: 46025 | B25: LYS CENTER - 1 Bouteille freon 410 (RETOUR/NON PAYE) | D25: 140 | F25: =+F24+D25-E25 -> 305 | I25: 0 | L25: =+L24+J25-K25 -> 79214
A26: 46025 | B26: ALBERT - Carburant NISSAN/DG-PRADO-NISSAN PATROL | E26: 150 | F26: =+F25+D26-E26 -> 155 | I26: 0 | L26: =+L25+J26-K26 -> 79214
A27: 46025 | B27: CDT - Cotisation syndicale s/Gratification ELECTROCOOL | D27: 182 | F27: =+F26+D27-E27 -> 337 | I27: 0 | L27: =+L26+J27-K27 -> 79214
A28: 46025 | B28: ATRIUM - 10 Disques c125 (19800fc) | D28: 9 | F28: =+F27+D28-E28 -> 346 | I28: 0 | L28: =+L27+J28-K28 -> 79214
A29: 46028 | B29: EBCDC USD - RETRAIT | D29: 3000 | F29: =+F28+D29-E29 -> 3346 | H29: 0 | I29: 0 | L29: =+L28+J29-K29 -> 79214
A30: 46025 | B30: DIDIER - Frais electricien ANCIEN JAC | E30: 150 | F30: =+F29+D30-E30 -> 3196 | H30: 0 | I30: 0 | L30: =+L29+J30-K30 -> 79214
A31: 46025 | B31: ALBERT - Frais aero, protocole, parking, bagages | E31: 60 | F31: =+F30+D31-E31 -> 3136 | I31: 0 | L31: =+L30+J31-K31 -> 79214
A32: 46028 | B32: CHICK - Achat eau DG&BUREAU | E32: 20 | F32: =+F31+D32-E32 -> 3116 | I32: 0 | L32: =+L31+J32-K32 -> 79214
A33: 46028 | B33: CLAUDE - Carburant PICKUP L200 | E33: 50 | F33: =+F32+D33-E33 -> 3066 | I33: 0 | L33: =+L32+J33-K33 -> 79214
A34: 46028 | B34: COMMUNICATIONS willy, georges, urbain | E34: 60 | F34: =+F33+D34-E34 -> 3006 | I34: 0 | L34: =+L33+J34-K34 -> 79214
A35: 46028 | B35: HANS - Communications | E35: 20 | F35: =+F34+D35-E35 -> 2986 | I35: 0 | L35: =+L34+J35-K35 -> 79214
A36: 46028 | B36: COMMUNICATIONS franck, kusiekita, bangamo | E36: 30 | F36: =+F35+D36-E36 -> 2956 | I36: 0 | L36: =+L35+J36-K36 -> 79214
A37: 46028 | B37: NDONA - Communications | E37: 10 | F37: =+F36+D37-E37 -> 2946 | I37: 0 | L37: =+L36+J37-K37 -> 79214
A38: 46028 | B38: RESIDENCE IVAN - Electricité prepaid | E38: 100 | F38: =+F37+D38-E38 -> 2846 | I38: 0 | L38: =+L37+J38-K38 -> 79214
A39: 46028 | B39: PGHK - 1Lg flexible non isolé 100 | E39: 25 | F39: =+F38+D39-E39 -> 2821 | I39: 0 | L39: =+L38+J39-K39 -> 79214
A40: 46028 | B40: LYS CENTER - 1 Bouteille freon 410 | E40: 140 | F40: =+F39+D40-E40 -> 2681 | I40: 0 | L40: =+L39+J40-K40 -> 79214
A41: 46028 | B41: CHANGE | E41: 200 | F41: =+F40+D41-E41 -> 2481 | I41: 0 | J41: 440000 | L41: =+L40+J41-K41 -> 519214
A42: 46028 | B42: CDT - Cotisation syndicale / GRATIFICATION 2025 | F42: =+F41+D42-E42 -> 2481 | I42: 0 | K42: 410000 | L42: =+L41+J42-K42 -> 109214
A43: 46028 | B43: ATRIUM - 10 Disques c125 (19800fc) | F43: =+F42+D43-E43 -> 2481 | I43: 0 | K43: 16800 | L43: =+L42+J43-K43 -> 92414
A44: 46028 | B44: PRIMMO - Frais assurance + feri 2CONTAINERS | E44: 2000 | F44: =+F43+D44-E44 -> 481 | I44: 0 | L44: =+L43+J44-K44 -> 92414
A45: 46029 | B45: MALEWU - Carburant TATA/DELUXE | E45: 50 | F45: =+F44+D45-E45 -> 431 | H45: 0 | I45: 0 | L45: =+L44+J45-K45 -> 92414
A46: 46029 | B46: PROSPERE - Reparation pneu NISSAN PATROL | F46: =+F45+D46-E46 -> 431 | I46: 0 | K46: 10000 | L46: =+L45+J46-K46 -> 82414
A47: 46029 | B47: CHICK - Communications | E47: 10 | F47: =+F46+D47-E47 -> 421 | I47: 0 | L47: =+L46+J47-K47 -> 82414
A48: 46029 | B48: CLAUDE - Frais aero, protocole, parking&divers | E48: 40 | F48: =+F47+D48-E48 -> 381 | I48: 0 | L48: =+L47+J48-K48 -> 82414
A49: 46029 | B49: PRIMMO - Impressions 3plans A0 | E49: 60 | F49: =+F48+D49-E49 -> 321 | I49: 0 | L49: =+L48+J49-K49 -> 82414
A50: 46029 | B50: LEKO - Carburant IST | E50: 10 | F50: =+F49+D50-E50 -> 311 | I50: 0 | L50: =+L49+J50-K50 -> 82414
A51: 46029 | B51: LOSEMBE 1 - Transport RESIDENCE DG | F51: =+F50+D51-E51 -> 311 | I51: 0 | K51: 10000 | L51: =+L50+J51-K51 -> 72414
A52: 46029 | B52: CHANGE | E52: 50 | F52: =+F51+D52-E52 -> 261 | I52: 0 | J52: 110000 | L52: =+L51+J52-K52 -> 182414
A53: 46029 | B53: KINKOLE - Frais journaliers entretien CF/HUB | F53: =+F52+D53-E53 -> 261 | I53: 0 | K53: 80000 | L53: =+L52+J53-K53 -> 102414
A54: 46030 | B54: RAWBANK USD - RETRAIT | D54: 2000 | F54: =+F53+C54+D54-E54 -> 2261 | H54: 0 | I54: 0 | L54: =+L53+J54-K54 -> 102414
A55: 46030 | B55: AGL/RES.DG - 1 Disjoncteur GV2 & 1support condenseur | E55: 65 | F55: =+F54+C55+D55-E55 -> 2196 | I55: 0 | L55: =+L54+J55-K55 -> 102414
A56: 46030 | B56: MBENKIE - Carburant JAC/CONTAINER | E56: 50 | F56: =+F55+C56+D56-E56 -> 2146 | I56: 0 | L56: =+L55+J56-K56 -> 102414
A57: 46030 | B57: MAKANDA - Communications | E57: 10 | F57: =+F56+C57+D57-E57 -> 2136 | I57: 0 | L57: =+L56+J57-K57 -> 102414
A58: 46030 | B58: LOSEMBE 1 - Carburant groupe NDOLO | E58: 100 | F58: =+F57+C58+D58-E58 -> 2036 | I58: 0 | L58: =+L57+J58-K58 -> 102414
A59: 46030 | B59: PRIMMO - Impression 7 plans A0 | E59: 140 | F59: =+F58+C59+D59-E59 -> 1896 | I59: 0 | L59: =+L58+J59-K59 -> 102414
A60: 46030 | B60: LEKO - Carburant IST | E60: 10 | F60: =+F59+C60+D60-E60 -> 1886 | I60: 0 | L60: =+L59+J60-K60 -> 102414
A61: 46030 | B61: CHANGE | E61: 1800 | F61: =+F60+C61+D61-E61 -> 86 | I61: 0 | J61: 4050000 | L61: =+L60+J61-K61 -> 4152414
A62: 46030 | B62: EGSC - CNSS 12/2025 | F62: =+F61+C62+D62-E62 -> 86 | I62: 0 | K62: 2248500 | L62: =+L61+J62-K62 -> 1903914
A63: 46030 | B63: EGSC - IPR 12/2025 | F63: =+F62+C63+D63-E63 -> 86 | I63: 0 | K63: 1780062 | L63: =+L62+J63-K63 -> 123852
A64: 46030 | B64: ESPACE SHADARY - Facture 2025/SN/169-170 | C64: 400 | F64: =+F63+C64+D64-E64 -> 486 | I64: 0 | L64: =+L63+J64-K64 -> 123852
A65: 46031 | B65: GEORGES - Carburant NISSAN PATROL | E65: 60 | F65: =+F64+C65+D65-E65 -> 426 | H65: 0 | I65: 0 | L65: =+L64+J65-K65 -> 123852
A66: 46031 | B66: DIDIER - Course de service | F66: =+F65+C66+D66-E66 -> 426 | I66: 0 | K66: 10000 | L66: =+L65+J66-K66 -> 113852
A67: 46031 | B67: ATRIUM - 2Lg planches & 2 disques c230 | E67: 40 | F67: =+F66+C67+D67-E67 -> 386 | I67: 0 | L67: =+L66+J67-K67 -> 113852
A68: 46031 | B68: RESIDENCE IVAN - Eclairage chambre parents | E68: 21 | F68: =+F67+C68+D68-E68 -> 365 | I68: 0 | L68: =+L67+J68-K68 -> 113852
A69: 46031 | B69: RESIDENCE DG - Eclairage salle de bain | E69: 21 | F69: =+F68+C69+D69-E69 -> 344 | I69: 0 | L69: =+L68+J69-K69 -> 113852
A70: 46031 | B70: PRIMMO - 15m cable souple 25mm² | E70: 105 | F70: =+F69+C70+D70-E70 -> 239 | I70: 0 | L70: =+L69+J70-K70 -> 113852
A71: 46031 | B71: PGHK - 1 Carton colle contact | E71: 60 | F71: =+F70+C71+D71-E71 -> 179 | I71: 0 | L71: =+L70+J71-K71 -> 113852
A72: 46031 | B72: ALVARO - Evacuation poubelle NDOLO | F72: =+F71+C72+D72-E72 -> 179 | I72: 0 | K72: 10000 | L72: =+L71+J72-K72 -> 103852
A73: 46031 | B73: LEKO - Carburant IST | E73: 10 | F73: =+F72+C73+D73-E73 -> 169 | I73: 0 | L73: =+L72+J73-K73 -> 103852
A74: 46032 | B74: CHICK - Carburant HYUNDAI SANTAFE | E74: 50 | F74: =+F73+C74+D74-E74 -> 119 | H74: 0 | I74: 0 | L74: =+L73+J74-K74 -> 103852
A75: 46032 | B75: ALBERT - Carburant PRADO/DG | E75: 50 | F75: =+F74+C75+D75-E75 -> 69 | I75: 0 | L75: =+L74+J75-K75 -> 103852
A76: 46032 | B76: CHICK - Frais aero , protocole, parking, bagages, divers | E76: 60 | F76: =+F75+C76+D76-E76 -> 9 | I76: 0 | L76: =+L75+J76-K76 -> 103852
A77: 46034 | B77: RAWBANK USD - RETRAIT | D77: 6000 | F77: =+F76+C77+D77-E77 -> 6009 | H77: 0 | I77: 0 | L77: =+L76+J77-K77 -> 103852
A78: 46034 | B78: SOFIBANK USD - RETRAIT | D78: 9900 | F78: =+F77+C78+D78-E78 -> 15909 | I78: 0 | L78: =+L77+J78-K78 -> 103852
A79: 46034 | B79: ABEL - Rebobinage 2 moteurs condenseurs/AGL | E79: 300 | F79: =+F78+C79+D79-E79 -> 15609 | I79: 0 | L79: =+L78+J79-K79 -> 103852
A80: 46034 | B80: PRIMMO - 5 Pqts colliers plastic | E80: 50 | F80: =+F79+C80+D80-E80 -> 15559 | I80: 0 | L80: =+L79+J80-K80 -> 103852
A81: 46034 | B81: COMMUNICATIONS willy, georges, urbain | E81: 60 | F81: =+F80+C81+D81-E81 -> 15499 | I81: 0 | L81: =+L80+J81-K81 -> 103852
A82: 46034 | B82: MNAOUER - Communications | E82: 20 | F82: =+F81+C82+D82-E82 -> 15479 | I82: 0 | L82: =+L81+J82-K82 -> 103852
A83: 46034 | B83: COMMUNICATIONS franck, kusiekita, bangamo | E83: 30 | F83: =+F82+C83+D83-E83 -> 15449 | I83: 0 | L83: =+L82+J83-K83 -> 103852
A84: 46034 | B84: MONTASSAR&MAIL - Communications | E84: 40 | F84: =+F83+C84+D84-E84 -> 15409 | I84: 0 | L84: =+L83+J84-K84 -> 103852
A85: 46034 | B85: CHANGE | E85: 4500 | F85: =+F84+C85+D85-E85 -> 10909 | I85: 0 | J85: 10350000 | L85: =+L84+J85-K85 -> 10453852
A86: 46034 | B86: ELECTROCOLL - Quinzaine 01/2026 | F86: =+F85+C86+D86-E86 -> 10909 | I86: 0 | K86: 2920000 | L86: =+L85+J86-K86 -> 7533852
A87: 46034 | B87: EGSC - Quinzaine 01/2026 | F87: =+F86+C87+D87-E87 -> 10909 | I87: 0 | K87: 2225000 | L87: =+L86+J87-K87 -> 5308852
A88: 46034 | B88: TEMPORAIRES - Quinzaine 01/2026 | F88: =+F87+C88+D88-E88 -> 10909 | I88: 0 | K88: 5150000 | L88: =+L87+J88-K88 -> 158852
A89: 46034 | B89: EUNICE - 1 Boite SOUDAL cfr GEORGES | E89: 15 | F89: =+F88+C89+D89-E89 -> 10894 | I89: 0 | L89: =+L88+J89-K89 -> 158852
A90: 46035 | B90: SOFIBANK USD - RETRAIT | D90: 9900 | F90: =+F89+C90+D90-E90 -> 20794 | H90: 0 | I90: 0 | L90: =+L89+J90-K90 -> 158852
A91: 46035 | B91: FRANCK - Trft SERGE/LUBUMBASHI | E91: 155 | F91: =+F90+C91+D91-E91 -> 20639 | I91: 0 | L91: =+L90+J91-K91 -> 158852
A92: 46035 | B92: MALEWU - Carburant TATA DELUXE | E92: 60 | F92: =+F91+C92+D92-E92 -> 20579 | I92: 0 | L92: =+L91+J92-K92 -> 158852
A93: 46035 | B93: CLAUDE - Carburant PICKUP L200 | E93: 50 | F93: =+F92+C93+D93-E93 -> 20529 | I93: 0 | L93: =+L92+J93-K93 -> 158852
A94: 46035 | B94: PRIMMO - Acpte container 4&5 cfr GEORGES NAWEJ | E94: 20000 | F94: =+F93+C94+D94-E94 -> 529 | I94: 0 | L94: =+L93+J94-K94 -> 158852
A95: 46035 | B95: DIDIER - Carburant groupe NDOLO | E95: 50 | F95: =+F94+C95+D95-E95 -> 479 | I95: 0 | L95: =+L94+J95-K95 -> 158852
A96: 46035 | B96: CHICK - Carburant PRADO/DG | E96: 50 | F96: =+F95+C96+D96-E96 -> 429 | I96: 0 | L96: =+L95+J96-K96 -> 158852
A97: 46035 | B97: FRANCK - Carburant IST | E97: 40 | F97: =+F96+C97+D97-E97 -> 389 | I97: 0 | L97: =+L96+J97-K97 -> 158852
A98: 46035 | B98: DIDIER - Entretien NISSAN PATROL / GEORGES | E98: 315 | F98: =+F97+C98+D98-E98 -> 74 | I98: 0 | L98: =+L97+J98-K98 -> 158852
A99: 46036 | B99: SOFIBANK USD - RETRAIT | D99: 9900 | F99: =+F98+C99+D99-E99 -> 9974 | H99: 0 | I99: =+I98+G99-H99 -> 0 | L99: =+L98+J99-K99 -> 158852
A100: 46036 | B100: RAWBANK USD -RETRAIT | D100: 1500 | F100: =+F99+C100+D100-E100 -> 11474 | I100: =+I99+G100-H100 -> 0 | L100: =+L99+J100-K100 -> 158852
...
